Workbook

Sheet Lisez-moi
B1: Mon Écran · classeur de configuration (version 2)
B3: À quoi sert ce classeur
B4: Il décrit tout ce que ton dock affiche : compétitions de sport, rubriques et médias d'actus, marchés, plateformes vidéo, chaînes YouTube, chaînes TV, cotes, pages, widgets et thèmes. Tu coches, tu déposes le fichier sur GitHub, et le dock se règle tout seul.
B5: Les lignes déjà cochées correspondent exactement au dock actuel. Le reste est un catalogue de ce que le dock sait récupérer : il suffit de cocher.
B6: En 4 étapes
B7: 1. Ouvre un onglet (Sport, Actus, Marchés…). Mets « Oui » dans la colonne jaune des lignes que tu veux, « Non » pour en exclure une d'une section entière.
B8: 2. Pour ajouter quelque chose qui n'est pas listé, va tout en bas de l'onglet, bloc « MES AJOUTS ». Une rubrique, une région ou un thème qui n'existe pas encore crée une nouvelle section.
B9: 3. Enregistre le fichier sous le nom configuration.xlsx et dépose-le à la racine de ton dépôt GitHub (détail dans l'onglet Tuto).
B10: 4. La tâche GitHub « Configuration » lit le classeur, écrit les réglages du dock, teste les nouveautés et range une copie avec la colonne « Résultat » remplie (config/configuration-resultat.xlsx). Le résumé s'affiche aussi dans la page État de l'appli.
B11: Règles de sélection
B12: • « Oui » sur la ligne « ▸ toute la section » prend tous les éléments de la section, sauf ceux marqués « Non ».
B13: • « Oui » sur un seul élément suffit : sa section apparaît dans l'appli avec cet élément seulement.
... B21: Légende
C22: Case à remplir : « Oui », « Non » ou vide
C23: Ligne choisie (se colore toute seule)
C24: Ligne de section : « ▸ toute la section »
C25: Résultat : ✅ fonctionne · ⚠️ trouvé, à vérifier · ❌ introuvable · « à vérifier » = pas encore testé
B27: Synthèse de tes choix (calculée automatiquement)
B28: Onglet | C28: Éléments cochés | D28: Disponibles | E28: Contenu
B29: Sport | C29: =COUNTIFS(Sport!$H$6:$H$157,"Oui",Sport!$A$6:$A$157,"<>sec:*") -> 41 | D29: =COUNTIFS(Sport!$A$6:$A$157,"<>sec:*",Sport!$A$6:$A$157,"<>") -> 135 | E29: Sport · compétitions suivies
B30: Équipes favorites | C30: =COUNTIFS('Équipes favorites'!$D$6:$D$65,"Oui",'Équipes favorites'!$A$6:$A$65,"<>sec:*") -> 12 | D30: =COUNTIFS('Équipes favorites'!$A$6:$A$65,"<>sec:*",'Équipes favorites'!$A$6:$A$65,"<>") -> 54 | E30: Sport · équipes favorites
B31: Actus | C31: =COUNTIFS(Actus!$F$6:$F$231,"Oui",Actus!$A$6:$A$231,"<>sec:*") -> 33 | D31: =COUNTIFS(Actus!$A$6:$A$231,"<>sec:*",Actus!$A$6:$A$231,"<>") -> 201 | E31: Actus · rubriques et médias (français)
B32: Actus International | C32: =COUNTIFS('Actus International'!$F$6:$F$105,"Oui",'Actus International'!$A$6:$A$105,"<>sec:*") -> 25 | D32: =COUNTIFS('Actus International'!$A$6:$A$105,"<>sec:*",'Actus International'!$A$6:$A$105,"<>") -> 85 | E32: Actus · mode International (anglais)
B33: Marchés | C33: =COUNTIFS(Marchés!$G$6:$G$83,"Oui",Marchés!$A$6:$A$83,"<>sec:*") -> 12 | D33: =COUNTIFS(Marchés!$A$6:$A$83,"<>sec:*",Marchés!$A$6:$A$83,"<>") -> 70 | E33: Investissements · marchés et fonds suivis
B34: Vidéos | C34: =COUNTIFS(Vidéos!$G$6:$G$26,"Oui",Vidéos!$A$6:$A$26,"<>sec:*") -> 7 | D34: =COUNTIFS(Vidéos!$A$6:$A$26,"<>sec:*",Vidéos!$A$6:$A$26,"<>") -> 20 | E34: Vidéos · plateformes de streaming
B35: YouTube | C35: =COUNTIFS(YouTube!$E$6:$E$60,"Oui",YouTube!$A$6:$A$60,"<>sec:*") -> 2 | D35: =COUNTIFS(YouTube!$A$6:$A$60,"<>sec:*",YouTube!$A$6:$A$60,"<>") -> 45 | E35: Vidéos · chaînes YouTube
B36: Programme TV | C36: =COUNTIFS('Programme TV'!$E$6:$E$83,"Oui",'Programme TV'!$A$6:$A$83,"<>sec:*") -> 55 | D36: =COUNTIFS('Programme TV'!$A$6:$A$83,"<>sec:*",'Programme TV'!$A$6:$A$83,"<>") -> 72 | E36: Programme TV · chaînes lues pour les matchs
B37: Cotes | C37: =COUNTIFS(Cotes!$F$6:$F$48,"Oui",Cotes!$A$6:$A$48,"<>sec:*") -> 15 | D37: =COUNTIFS(Cotes!$A$6:$A$48,"<>sec:*",Cotes!$A$6:$A$48,"<>") -> 39 | E37: Cotes des matchs · sites et compétitions
B38: Accueil | C38: =COUNTIFS(Accueil!$E$6:$E$37,"Oui",Accueil!$A$6:$A$37,"<>sec:*") -> 18 | D38: =COUNTIFS(Accueil!$A$6:$A$37,"<>sec:*",Accueil!$A$6:$A$37,"<>") -> 28 | E38: Accueil · pages, widgets et météo
B39: Applis | C39: =COUNTIFS(Applis!$G$6:$G$54,"Oui",Applis!$A$6:$A$54,"<>sec:*") -> 41 | D39: =COUNTIFS(Applis!$A$6:$A$54,"<>sec:*",Applis!$A$6:$A$54,"<>") -> 41 | E39: Accueil · applis, dossiers et liens
B40: Apparence | C40: =COUNTIFS(Apparence!$E$6:$E$17,"Oui",Apparence!$A$6:$A$17,"<>sec:*") -> 8 | D40: =COUNTIFS(Apparence!$A$6:$A$17,"<>sec:*",Apparence!$A$6:$A$17,"<>") -> 10 | E40: Apparence · thèmes et mode
B41: Total | C41: =SUM(C29:C40) -> 269 | D41: =SUM(D29:D40) -> 800
B43: Journal des versions du classeur
B44: Version 1 | C44: 30/10/2026 | D44: Première version : 11 onglets (Sport, Équipes favorites, Actus, Actus International, Marchés, Vidéos, YouTube, Programme TV, Cotes, Accueil, Apparence), pré-cochés à l'identique du dock actuel, catalogue de plus de 500 éléments à essayer, blocs « Mes ajouts », Tuto.
B45: Version 2 | C45: 30/10/2026 | D45: Onglet Applis : dossiers, bandeau du bas et navigation, avec 3 liens par appli (iPhone, Android, web) modifiables. Onglet Cotes : réglages du rapport des écarts. Les pages lisent désormais ces réglages (config/config.js).

Sheet Tuto
B1: Tuto · remplir le classeur et installer sa propre version
B3: Partie 1 · Remplir et déposer le classeur
B4: Pour tout le monde, à chaque changement de réglages.
B5: N° | C5: Étape | D5: Où | E5: Comment
B6: 1 | C6: Ouvrir le classeur | D6: Excel, Numbers ou Google Sheets | E6: Sur iPhone, Numbers ou l'appli Excel conviennent. Les colonnes jaunes sont les seules à remplir.
B7: 2 | C7: Cocher ce que tu veux | D7: Onglets Sport, Actus, Marchés… | E7: « Oui » dans la colonne Oui. « Non » pour exclure un élément d'une section prise en entier. Laisse vide pour ne rien changer.
B8: 3 | C8: Ajouter un élément absent | D8: Bas de chaque onglet, bloc MES AJOUTS | E8: Remplis Section (existante ou nouvelle), Nom et Source (adresse d'un site, @nom YouTube, ISIN, clé ESPN…), puis « Oui ». La ligne d'exemple grise est ignorée.
B9: 4 | C9: Vérifier la synthèse | D9: Onglet Lisez-moi | E9: Le tableau compte tes éléments cochés par onglet : un moyen rapide de voir si rien n'a été oublié.
B10: 5 | C10: Enregistrer | D10: Format .xlsx | E10: Nom du fichier : configuration.xlsx (exactement). Garde le format Excel, pas .numbers ni .csv.
B11: 6 | C11: Déposer sur GitHub | D11: Page de ton dépôt GitHub | E11: Sur la page du dépôt : Add file → Upload files → glisse configuration.xlsx → Commit changes. Il remplace l'ancien.
B12: 7 | C12: Suivre la tâche | D12: Onglet Actions du dépôt | E12: La tâche « Configuration » démarre seule (1 à 3 minutes). Coche verte = réglages appliqués ; croix rouge = ouvre-la pour lire l'erreur.
B13: 8 | C13: Lire le résultat | D13: Page État de l'appli, ou config/configuration-resultat.xlsx | E13: Chaque nouveauté reçoit ✅ (fonctionne), ⚠️ (trouvé, à vérifier) ou ❌ (introuvable, avec la raison). Corrige et redépose si besoin.
B15: Partie 2 · Installer sa propre version (une seule fois)
B16: Pour un ami qui veut son dock à lui. Compter 30 à 45 minutes. Rien de payant.
B17: N° | C17: Étape | D17: Où | E17: Comment
B18: 1 | C18: Créer un compte GitHub | D18: github.com | E18: Gratuit. Choisis un pseudo : il apparaîtra dans l'adresse du dock (https://pseudo.github.io/…).
B19: 2 | C19: Copier le dépôt | D19: Dépôt d'origine (lien) | E19: Bouton « Fork » → garde le même nom → Create fork. Tu as maintenant ta propre copie.
B20: 3 | C20: Activer les tâches | D20: Ta copie → onglet Actions | E20: Sur une copie, GitHub les désactive : bouton « I understand my workflows, go ahead and enable them ».
B21: 4 | C21: Publier le site | D21: Settings → Pages | E21: Source : GitHub Actions. Après la première tâche « Publication », le dock est en ligne à l'adresse affichée en haut de cette page.
B22: 5 | C22: Autoriser les tâches à écrire | D22: Settings → Actions → General | E22: Tout en bas, Workflow permissions : « Read and write permissions » → Save. Sans ça, les données ne peuvent pas être enregistrées.
B23: 6 | C23: Clé TMDB (catalogue vidéo) | D23: themoviedb.org | E23: Crée un compte, puis Paramètres → API → demande une clé « Developer » (usage personnel, gratuit). Copie le long « API Read Access Token » (commence par eyJ…).
B24: 7 | C24: Enregistrer la clé TMDB | D24: Settings → Secrets and variables → Actions | E24: New repository secret : nom TMDB_TOKEN, valeur = le jeton copié. Les secrets ne sont jamais visibles publiquement.
B25: 8 | C25: Clé des cotes (facultatif) | D25: the-odds-api.com | E25: Offre gratuite (500 crédits par mois) : la clé arrive par e-mail. Secret GitHub ODDS_API_KEY. Pour l'actualisation à la main, colle aussi la clé dans État → Cotes des matchs (elle reste sur l'appareil).
B26: 9 | C26: Lancer les tâches une première fois | D26: Onglet Actions | E26: Ouvre chaque tâche (Actus, Marchés, Vidéos, Programme TV sport, Cotes, Publication) → Run workflow. Ensuite elles tournent seules.
B27: 10 | C27: Ajouter le dock à l'iPhone | D27: Safari, sur l'adresse du dock | E27: Bouton Partager → « Sur l'écran d'accueil ». Le dock s'ouvre alors en plein écran comme une appli.
B28: 11 | C28: Choisir son code | D28: Page Investissements ou Coffre | E28: Au premier usage, l'appli demande un code PIN : il chiffre tes montants et ton coffre sur l'appareil. Il n'est jamais envoyé nulle part.
B29: 12 | C29: Synchroniser ses appareils (facultatif) | D29: État → Synchronisation | E29: Crée une clé GitHub « fine-grained » (Repository access : seulement ta copie ; Permissions → Contents : Read and write), puis suis l'assistant : il génère une phrase de 6 mots à garder précieusement. Note : aujourd'hui l'adresse du dépôt de synchronisation est écrite dans synchro.js ; elle passera dans la configuration lors du branchement des pages.
... B31: 14 | C31: Déposer ton classeur | D31: Partie 1, étapes 5 à 8 | E31: Décoche ce qui ne t'intéresse pas (les choix de départ sont ceux de Yoann), ajoute tes équipes, tes villes, tes fonds, puis dépose configuration.xlsx.
B33: Mises à jour de l'appli
B34: Quand une nouvelle version du dock est publiée.
B35: N° | C35: Étape | D35: Où | E35: Comment
B36: 1 | C36: Récupérer la mise à jour | D36: Fichier mise-a-jour-vNN.zip | E36: Dépose-le à la racine de ta copie (Add file → Upload files). La tâche « Mise à jour » l'installe toute seule.
B37: 2 | C37: Fichiers de tâches | D37: Dossier .github/workflows | E37: GitHub interdit aux tâches de modifier ce dossier : si la mise à jour en contient, la tâche les liste et il faut les déposer à la main dans .github/workflows.
B38: 3 | C38: Tes réglages restent | D38: configuration.xlsx | E38: Une mise à jour ne touche jamais tes choix. Si une nouvelle version du classeur est livrée, tes choix sont repris par identifiant.

Sheet Sport
A1: module=sport;version=2 | B1: Sport · compétitions suivies
B2: Coche « Oui » pour afficher une compétition dans la page Sport. « Favori » la met en avant (comme la F1 et le MotoGP aujourd'hui). « Prise en charge » : Oui = l'appli sait déjà l'afficher · À développer = données disponibles, affichage à coder · Non disponible = pas de source gratuite fiable.
B3: À remplir : cases jaunes (« Oui » ou « Non »). Ligne « ▸ toute la section » = tous ses éléments, sauf ceux marqués « Non ». Un seul élément coché suffit pour que sa section apparaisse. Colonne « Résultat » : remplie par la tâche GitHub après dépôt du classeur.
A5: ID | B5: Section | C5: Compétition | D5: Sport | E5: Clé ESPN | F5: Diffuseur(s) en France | G5: Prise en charge | H5: Oui | I5: Favori | J5: Résultat | K5: Note | L5: Technique
A6: sec:sport:fr | B6: France | C6: ▸ toute la section | L6: {"id": "fr", "label": "France"}
A7: sp:fra.1 | B7: France | C7: Ligue 1 | D7: soccer | E7: fra.1 | F7: Ligue 1+ | G7: Oui | H7: Oui | L7: {"support": "ok", "def": {"id": "fra.1", "region": "fr", "flag": "🇫🇷", "sport": "soccer", "group": "foot", "name": "Ligue 1", "tv": ["Ligue 1+"], "rounds": true, "of": "fr.1"}}
A8: sp:fra.2 | B8: France | C8: Ligue 2 | D8: soccer | E8: fra.2 | F8: beIN Sports | G8: Oui | H8: Oui | L8: {"support": "ok", "def": {"id": "fra.2", "region": "fr", "flag": "🇫🇷", "sport": "soccer", "group": "foot", "name": "Ligue 2", "tv": ["beIN Sports"], "rounds": true, "of": "fr.2", "tsdb": {"c": "France", "s": "Soccer", "re": {"re": "ligue 2", "flags": "i"}}}}
A9: sp:fra.coupe_de_france | B9: France | C9: Coupe de France | D9: soccer | E9: fra.coupe_de_france | F9: beIN Sports | G9: Oui | H9: Oui | L9: {"support": "ok", "def": {"id": "fra.coupe_de_france", "region": "fr", "flag": "🇫🇷", "sport": "soccer", "group": "foot", "name": "Coupe de France", "tv": ["beIN Sports"]}}
A10: sp:fra.super_cup | B10: France | C10: Trophée des champions | D10: soccer | E10: fra.super_cup | G10: Oui | H10: Oui | L10: {"support": "ok", "def": {"id": "fra.super_cup", "region": "fr", "flag": "🇫🇷", "sport": "soccer", "group": "foot", "name": "Trophée des champions", "seasonal": true}}
A11: sp:fra.3 | B11: France | C11: National | D11: soccer | E11: fra.3 | G11: Oui | J11: à vérifier | L11: {"support": "ok", "def": {"id": "fra.3", "region": "fr", "flag": "🇫🇷", "sport": "soccer", "group": "foot", "name": "National"}}
A12: sec:sport:ec | B12: Compétitions européennes | C12: ▸ toute la section | L12: {"id": "ec", "label": "Compétitions européennes"}
A13: sp:uefa.champions | B13: Compétitions européennes | C13: Ligue des champions | D13: soccer | E13: uefa.champions | F13: Canal+ | G13: Oui | H13: Oui | L13: {"support": "ok", "def": {"id": "uefa.champions", "region": "ec", "flag": "🇪🇺", "sport": "soccer", "group": "foot", "name": "Ligue des champions", "tv": ["Canal+"]}}
A14: sp:uefa.europa | B14: Compétitions européennes | C14: Ligue Europa | D14: soccer | E14: uefa.europa | F14: Canal+ | G14: Oui | H14: Oui | L14: {"support": "ok", "def": {"id": "uefa.europa", "region": "ec", "flag": "🇪🇺", "sport": "soccer", "group": "foot", "name": "Ligue Europa", "tv": ["Canal+"]}}
A15: sp:uefa.europa.conf | B15: Compétitions européennes | C15: Ligue Conférence | D15: soccer | E15: uefa.europa.conf | F15: Canal+ | G15: Oui | H15: Oui | L15: {"support": "ok", "def": {"id": "uefa.europa.conf", "region": "ec", "flag": "🇪🇺", "sport": "soccer", "group": "foot", "name": "Ligue Conférence", "tv": ["Canal+"]}}
A16: sp:uefa.super_cup | B16: Compétitions européennes | C16: Supercoupe d'Europe | D16: soccer | E16: uefa.super_cup | G16: Oui | H16: Oui | L16: {"support": "ok", "def": {"id": "uefa.super_cup", "region": "ec", "flag": "🇪🇺", "sport": "soccer", "group": "foot", "name": "Supercoupe d'Europe", "seasonal": true}}
A17: sp:uefa.champions_qual | B17: Compétitions européennes | C17: Ligue des champions · qualifications | D17: soccer | E17: uefa.champions_qual | G17: Oui | J17: à vérifier | L17: {"support": "ok", "def": {"id": "uefa.champions_qual", "region": "ec", "flag": "🇪🇺", "sport": "soccer", "group": "foot", "name": "Ligue des champions · qualifications"}}
A18: sp:uefa.europa_qual | B18: Compétitions européennes | C18: Ligue Europa · qualifications | D18: soccer | E18: uefa.europa_qual | G18: Oui | J18: à vérifier | L18: {"support": "ok", "def": {"id": "uefa.europa_qual", "region": "ec", "flag": "🇪🇺", "sport": "soccer", "group": "foot", "name": "Ligue Europa · qualifications"}}
A19: sp:uefa.europa.conf_qual | B19: Compétitions européennes | C19: Ligue Conférence · qualifications | D19: soccer | E19: uefa.europa.conf_qual | G19: Oui | J19: à vérifier | L19: {"support": "ok", "def": {"id": "uefa.europa.conf_qual", "region": "ec", "flag": "🇪🇺", "sport": "soccer", "group": "foot", "name": "Ligue Conférence · qualifications"}}
A20: sp:uefa.youth_league | B20: Compétitions européennes | C20: UEFA Youth League | D20: soccer | E20: uefa.youth_league | G20: Oui | J20: à vérifier | L20: {"support": "ok", "def": {"id": "uefa.youth_league", "region": "ec", "flag": "🇪🇺", "sport": "soccer", "group": "foot", "name": "UEFA Youth League"}}
A21: sec:sport:intl | B21: Football international | C21: ▸ toute la section | L21: {"id": "intl", "label": "Football international"}
A22: sp:fifa.world | B22: Football international | C22: Coupe du monde | D22: soccer | E22: fifa.world | G22: Oui | H22: Oui | L22: {"support": "ok", "def": {"id": "fifa.world", "region": "intl", "flag": "🌍", "sport": "soccer", "group": "foot", "name": "Coupe du monde", "seasonal": true}}
A23: sp:uefa.euro | B23: Football international | C23: Euro | D23: soccer | E23: uefa.euro | G23: Oui | H23: Oui | L23: {"support": "ok", "def": {"id": "uefa.euro", "region": "intl", "flag": "🇪🇺", "sport": "soccer", "group": "foot", "name": "Euro", "seasonal": true}}
A24: sp:fifa.worldq.uefa | B24: Football international | C24: Qualifications Coupe du monde | D24: soccer | E24: fifa.worldq.uefa | F24: TF1 | G24: Oui | H24: Oui | L24: {"support": "ok", "def": {"id": "fifa.worldq.uefa", "region": "intl", "flag": "🌍", "sport": "soccer", "group": "foot", "name": "Qualifications Coupe du monde", "tv": ["TF1"], "tvTeam": "France", "seasonal": true}}
A25: sp:uefa.euroq | B25: Football international | C25: Qualifications Euro | D25: soccer | E25: uefa.euroq | F25: TF1 | G25: Oui | H25: Oui | L25: {"support": "ok", "def": {"id": "uefa.euroq", "region": "intl", "flag": "🇪🇺", "sport": "soccer", "group": "foot", "name": "Qualifications Euro", "tv": ["TF1"], "tvTeam": "France", "seasonal": true}}
A26: sp:uefa.nations | B26: Football international | C26: Ligue des nations | D26: soccer | E26: uefa.nations | F26: TF1 | G26: Oui | H26: Oui | L26: {"support": "ok", "def": {"id": "uefa.nations", "region": "intl", "flag": "🇪🇺", "sport": "soccer", "group": "foot", "name": "Ligue des nations", "tv": ["TF1"], "tvTeam": "France", "seasonal": true}}
A27: sp:fifa.friendly | B27: Football international | C27: Amicaux internationaux | D27: soccer | E27: fifa.friendly | F27: TF1 | G27: Oui | H27: Oui | L27: {"support": "ok", "def": {"id": "fifa.friendly", "region": "intl", "flag": "🌍", "sport": "soccer", "group": "foot", "name": "Amicaux internationaux", "tv": ["TF1"], "tvTeam": "France", "seasonal": true}}
A28: sp:fifa.olympics | B28: Football international | C28: Jeux olympiques | D28: soccer | E28: fifa.olympics | G28: Oui | H28: Oui | L28: {"support": "ok", "def": {"id": "fifa.olympics", "region": "intl", "flag": "🌍", "sport": "soccer", "group": "foot", "name": "Jeux olympiques", "seasonal": true}}
A29: sp:fifa.cwc | B29: Football international | C29: Coupe du monde des clubs | D29: soccer | E29: fifa.cwc | G29: Oui | H29: Oui | L29: {"support": "ok", "def": {"id": "fifa.cwc", "region": "intl", "flag": "🌍", "sport": "soccer", "group": "foot", "name": "Coupe du monde des clubs", "seasonal": true}}
A30: sp:fifa.worldq.conmebol | B30: Football international | C30: Qualifications Coupe du monde · Amérique du Sud | D30: soccer | E30: fifa.worldq.conmebol | G30: Oui | J30: à vérifier | L30: {"support": "ok", "def": {"id": "fifa.worldq.conmebol", "region": "intl", "flag": "🌍", "sport": "soccer", "group": "foot", "name": "Qualifications Coupe du monde · Amérique du Sud"}}
A31: sp:fifa.worldq.concacaf | B31: Football international | C31: Qualifications Coupe du monde · Amérique du Nord | D31: soccer | E31: fifa.worldq.concacaf | G31: Oui | J31: à vérifier | L31: {"support": "ok", "def": {"id": "fifa.worldq.concacaf", "region": "intl", "flag": "🌍", "sport": "soccer", "group": "foot", "name": "Qualifications Coupe du monde · Amérique du Nord"}}
A32: sp:fifa.worldq.caf | B32: Football international | C32: Qualifications Coupe du monde · Afrique | D32: soccer | E32: fifa.worldq.caf | G32: Oui | J32: à vérifier | L32: {"support": "ok", "def": {"id": "fifa.worldq.caf", "region": "intl", "flag": "🌍", "sport": "soccer", "group": "foot", "name": "Qualifications Coupe du monde · Afrique"}}
A33: sp:fifa.worldq.afc | B33: Football international | C33: Qualifications Coupe du monde · Asie | D33: soccer | E33: fifa.worldq.afc | G33: Oui | J33: à vérifier | L33: {"support": "ok", "def": {"id": "fifa.worldq.afc", "region": "intl", "flag": "🌍", "sport": "soccer", "group": "foot", "name": "Qualifications Coupe du monde · Asie"}}
A34: sp:uefa.euro_u21 | B34: Football international | C34: Euro Espoirs (U21) | D34: soccer | E34: uefa.euro_u21 | G34: Oui | J34: à vérifier | L34: {"support": "ok", "def": {"id": "uefa.euro_u21", "region": "intl", "flag": "🇪🇺", "sport": "soccer", "group": "foot", "name": "Euro Espoirs (U21)"}}
A35: sp:caf.nations | B35: Football international | C35: Coupe d'Afrique des nations | D35: soccer | E35: caf.nations | G35: Oui | J35: à vérifier | L35: {"support": "ok", "def": {"id": "caf.nations", "region": "intl", "flag": "🌍", "sport": "soccer", "group": "foot", "name": "Coupe d'Afrique des nations"}}
A36: sp:conmebol.america | B36: Football international | C36: Copa América | D36: soccer | E36: conmebol.america | G36: Oui | J36: à vérifier | L36: {"support": "ok", "def": {"id": "conmebol.america", "region": "intl", "flag": "🌎", "sport": "soccer", "group": "foot", "name": "Copa América"}}
A37: sp:concacaf.gold | B37: Football international | C37: Gold Cup | D37: soccer | E37: concacaf.gold | G37: Oui | J37: à vérifier | L37: {"support": "ok", "def": {"id": "concacaf.gold", "region": "intl", "flag": "🌎", "sport": "soccer", "group": "foot", "name": "Gold Cup"}}
A38: sp:afc.asian.cup | B38: Football international | C38: Coupe d'Asie des nations | D38: soccer | E38: afc.asian.cup | G38: Oui | J38: à vérifier | L38: {"support": "ok", "def": {"id": "afc.asian.cup", "region": "intl", "flag": "🌏", "sport": "soccer", "group": "foot", "name": "Coupe d'Asie des nations"}}
A39: sec:sport:en | B39: Angleterre | C39: ▸ toute la section | L39: {"id": "en", "label": "Angleterre"}
A40: sp:eng.1 | B40: Angleterre | C40: Premier League | D40: soccer | E40: eng.1 | F40: Canal+ | G40: Oui | H40: Oui | L40: {"support": "ok", "def": {"id": "eng.1", "region": "en", "flag": "🏴󠁧󠁢󠁥󠁮󠁧󠁿", "sport": "soccer", "group": "foot", "name": "Premier League", "tv": ["Canal+"], "rounds": true, "of": "en.1"}}
A41: sp:eng.2 | B41: Angleterre | C41: Championship | D41: soccer | E41: eng.2 | G41: Oui | H41: Oui | L41: {"support": "ok", "def": {"id": "eng.2", "region": "en", "flag": "🏴󠁧󠁢󠁥󠁮󠁧󠁿", "sport": "soccer", "group": "foot", "name": "Championship", "rounds": true, "of": "en.2"}}
A42: sp:eng.league_cup | B42: Angleterre | C42: Coupe de la Ligue anglaise | D42: soccer | E42: eng.league_cup | F42: beIN Sports | G42: Oui | H42: Oui | L42: {"support": "ok", "def": {"id": "eng.league_cup", "region": "en", "flag": "🏴󠁧󠁢󠁥󠁮󠁧󠁿", "sport": "soccer", "group": "foot", "name": "Coupe de la Ligue anglaise", "tv": ["beIN Sports"]}}
A43: sp:eng.fa | B43: Angleterre | C43: FA Cup | D43: soccer | E43: eng.fa | G43: Oui | H43: Oui | L43: {"support": "ok", "def": {"id": "eng.fa", "region": "en", "flag": "🏴󠁧󠁢󠁥󠁮󠁧󠁿", "sport": "soccer", "group": "foot", "name": "FA Cup"}}
A44: sp:eng.charity | B44: Angleterre | C44: Community Shield | D44: soccer | E44: eng.charity | G44: Oui | H44: Oui | L44: {"support": "ok", "def": {"id": "eng.charity", "region": "en", "flag": "🏴󠁧󠁢󠁥󠁮󠁧󠁿", "sport": "soccer", "group": "foot", "name": "Community Shield", "seasonal": true}}
A45: sp:eng.3 | B45: Angleterre | C45: League One | D45: soccer | E45: eng.3 | G45: Oui | J45: à vérifier | L45: {"support": "ok", "def": {"id": "eng.3", "region": "en", "flag": "🏴󠁧󠁢󠁥󠁮󠁧󠁿", "sport": "soccer", "group": "foot", "name": "League One"}}
A46: sp:eng.4 | B46: Angleterre | C46: League Two | D46: soccer | E46: eng.4 | G46: Oui | J46: à vérifier | L46: {"support": "ok", "def": {"id": "eng.4", "region": "en", "flag": "🏴󠁧󠁢󠁥󠁮󠁧󠁿", "sport": "soccer", "group": "foot", "name": "League Two"}}
A47: sp:eng.5 | B47: Angleterre | C47: National League | D47: soccer | E47: eng.5 | G47: Oui | J47: à vérifier | L47: {"support": "ok", "def": {"id": "eng.5", "region": "en", "flag": "🏴󠁧󠁢󠁥󠁮󠁧󠁿", "sport": "soccer", "group": "foot", "name": "National League"}}
A48: sp:eng.trophy | B48: Angleterre | C48: EFL Trophy | D48: soccer | E48: eng.trophy | G48: Oui | J48: à vérifier | L48: {"support": "ok", "def": {"id": "eng.trophy", "region": "en", "flag": "🏴󠁧󠁢󠁥󠁮󠁧󠁿", "sport": "soccer", "group": "foot", "name": "EFL Trophy"}}
A49: sec:sport:big | B49: Espagne · Italie · Allemagne | C49: ▸ toute la section | L49: {"id": "big", "label": "Espagne · Italie · Allemagne"}
A50: sp:esp.1 | B50: Espagne · Italie · Allemagne | C50: Liga | D50: soccer | E50: esp.1 | F50: DAZN, Disney+ | G50: Oui | H50: Oui | L50: {"support": "ok", "def": {"id": "esp.1", "region": "big", "flag": "🇪🇸", "sport": "soccer", "group": "foot", "name": "Liga", "tv": ["DAZN", "Disney+"], "rounds": true, "of": "es.1"}}
A51: sp:ita.1 | B51: Espagne · Italie · Allemagne | C51: Serie A | D51: soccer | E51: ita.1 | F51: DAZN | G51: Oui | H51: Oui | L51: {"support": "ok", "def": {"id": "ita.1", "region": "big", "flag": "🇮🇹", "sport": "soccer", "group": "foot", "name": "Serie A", "tv": ["DAZN"], "rounds": true, "of": "it.1"}}
A52: sp:ger.1 | B52: Espagne · Italie · Allemagne | C52: Bundesliga | D52: soccer | E52: ger.1 | F52: beIN Sports | G52: Oui | H52: Oui | L52: {"support": "ok", "def": {"id": "ger.1", "region": "big", "flag": "🇩🇪", "sport": "soccer", "group": "foot", "name": "Bundesliga", "tv": ["beIN Sports"], "rounds": true, "of": "de.1"}}
A53: sp:esp.copa_del_rey | B53: Espagne · Italie · Allemagne | C53: Coupe du Roi | D53: soccer | E53: esp.copa_del_rey | G53: Oui | H53: Oui | L53: {"support": "ok", "def": {"id": "esp.copa_del_rey", "region": "big", "flag": "🇪🇸", "sport": "soccer", "group": "foot", "name": "Coupe du Roi"}}
A54: sp:esp.super_cup | B54: Espagne · Italie · Allemagne | C54: Supercoupe d'Espagne | D54: soccer | E54: esp.super_cup | G54: Oui | H54: Oui | L54: {"support": "ok", "def": {"id": "esp.super_cup", "region": "big", "flag": "🇪🇸", "sport": "soccer", "group": "foot", "name": "Supercoupe d'Espagne", "seasonal": true}}
A55: sp:ita.coppa_italia | B55: Espagne · Italie · Allemagne | C55: Coupe d'Italie | D55: soccer | E55: ita.coppa_italia | G55: Oui | H55: Oui | L55: {"support": "ok", "def": {"id": "ita.coppa_italia", "region": "big", "flag": "🇮🇹", "sport": "soccer", "group": "foot", "name": "Coupe d'Italie"}}
A56: sp:ita.super_cup | B56: Espagne · Italie · Allemagne | C56: Supercoupe d'Italie | D56: soccer | E56: ita.super_cup | G56: Oui | H56: Oui | L56: {"support": "ok", "def": {"id": "ita.super_cup", "region": "big", "flag": "🇮🇹", "sport": "soccer", "group": "foot", "name": "Supercoupe d'Italie", "seasonal": true}}
A57: sp:ger.dfb_pokal | B57: Espagne · Italie · Allemagne | C57: Coupe d'Allemagne | D57: soccer | E57: ger.dfb_pokal | G57: Oui | H57: Oui | L57: {"support": "ok", "def": {"id": "ger.dfb_pokal", "region": "big", "flag": "🇩🇪", "sport": "soccer", "group": "foot", "name": "Coupe d'Allemagne"}}
A58: sp:ger.super_cup | B58: Espagne · Italie · Allemagne | C58: Supercoupe d'Allemagne | D58: soccer | E58: ger.super_cup | G58: Oui | H58: Oui | L58: {"support": "ok", "def": {"id": "ger.super_cup", "region": "big", "flag": "🇩🇪", "sport": "soccer", "group": "foot", "name": "Supercoupe d'Allemagne", "seasonal": true}}
A59: sp:esp.2 | B59: Espagne · Italie · Allemagne | C59: Liga 2 | D59: soccer | E59: esp.2 | G59: Oui | J59: à vérifier | L59: {"support": "ok", "def": {"id": "esp.2", "region": "big", "flag": "🇪🇸", "sport": "soccer", "group": "foot", "name": "Liga 2"}}
A60: sp:ita.2 | B60: Espagne · Italie · Allemagne | C60: Serie B | D60: soccer | E60: ita.2 | G60: Oui | J60: à vérifier | L60: {"support": "ok", "def": {"id": "ita.2", "region": "big", "flag": "🇮🇹", "sport": "soccer", "group": "foot", "name": "Serie B"}}
A61: sp:ger.2 | B61: Espagne · Italie · Allemagne | C61: 2. Bundesliga | D61: soccer | E61: ger.2 | G61: Oui | J61: à vérifier | L61: {"support": "ok", "def": {"id": "ger.2", "region": "big", "flag": "🇩🇪", "sport": "soccer", "group": "foot", "name": "2. Bundesliga"}}
A62: sp:ger.3 | B62: Espagne · Italie · Allemagne | C62: 3. Liga | D62: soccer | E62: ger.3 | G62: Oui | J62: à vérifier | L62: {"support": "ok", "def": {"id": "ger.3", "region": "big", "flag": "🇩🇪", "sport": "soccer", "group": "foot", "name": "3. Liga"}}
A63: sec:sport:rfr | B63: Rugby · France | C63: ▸ toute la section | L63: {"id": "rfr", "label": "Rugby · France"}
A64: sp:270559 | B64: Rugby · France | C64: Top 14 | D64: rugby | E64: 270559 | F64: Canal+ | G64: Oui | H64: Oui | L64: {"support": "ok", "def": {"id": "270559", "region": "rfr", "flag": "🇫🇷", "sport": "rugby", "group": "rugby", "name": "Top 14", "tv": ["Canal+"], "rounds": true, "tsdb": {"c": "France", "s": "Rugby", "re": {"re": "top ?14", "flags": "i"}}, "badges": true}}
A65: sp:prod2 | B65: Rugby · France | C65: Pro D2 | D65: rugby | E65: prod2 | G65: À développer | J65: à vérifier | K65: Absent d'ESPN : passerait par TheSportsDB | L65: {"support": "dev", "def": {"id": "prod2", "region": "rfr", "flag": "🇫🇷", "sport": "rugby", "group": "rugby", "name": "Pro D2"}}
A66: sec:sport:reu | B66: Rugby · Europe | C66: ▸ toute la section | L66: {"id": "reu", "label": "Rugby · Europe"}
A67: sp:271937 | B67: Rugby · Europe | C67: Champions Cup | D67: rugby | E67: 271937 | F67: beIN Sports | G67: Oui | H67: Oui | L67: {"support": "ok", "def": {"id": "271937", "region": "reu", "flag": "🇪🇺", "sport": "rugby", "group": "rugby", "name": "Champions Cup", "tv": ["beIN Sports"], "badges": "270559"}}
A68: sp:272073 | B68: Rugby · Europe | C68: Challenge Cup | D68: rugby | E68: 272073 | G68: Oui | J68: à vérifier | L68: {"support": "ok", "def": {"id": "272073", "region": "reu", "flag": "🇪🇺", "sport": "rugby", "group": "rugby", "name": "Challenge Cup"}}
A69: sp:267979 | B69: Rugby · Europe | C69: Premiership (Angleterre) | D69: rugby | E69: 267979 | G69: Oui | J69: à vérifier | L69: {"support": "ok", "def": {"id": "267979", "region": "reu", "flag": "🏴󠁧󠁢󠁥󠁮󠁧󠁿", "sport": "rugby", "group": "rugby", "name": "Premiership (Angleterre)"}}
A70: sp:270557 | B70: Rugby · Europe | C70: United Rugby Championship | D70: rugby | E70: 270557 | G70: Oui | J70: à vérifier | L70: {"support": "ok", "def": {"id": "270557", "region": "reu", "flag": "🇪🇺", "sport": "rugby", "group": "rugby", "name": "United Rugby Championship"}}
A71: sec:sport:rintl | B71: Rugby · International | C71: ▸ toute la section | L71: {"id": "rintl", "label": "Rugby · International"}
A72: sp:164205 | B72: Rugby · International | C72: Coupe du monde de rugby | D72: rugby | E72: 164205 | F72: TF1 | G72: Oui | H72: Oui | L72: {"support": "ok", "def": {"id": "164205", "region": "rintl", "flag": "🌍", "sport": "rugby", "group": "rugby", "name": "Coupe du monde de rugby", "tv": ["TF1"], "seasonal": true}}
A73: sp:180659 | B73: Rugby · International | C73: Six Nations | D73: rugby | E73: 180659 | F73: France TV | G73: Oui | H73: Oui | L73: {"support": "ok", "def": {"id": "180659", "region": "rintl", "flag": "🇪🇺", "sport": "rugby", "group": "rugby", "name": "Six Nations", "tv": ["France TV"], "seasonal": true}}
A74: sp:289234 | B74: Rugby · International | C74: Tests internationaux | D74: rugby | E74: 289234 | F74: TF1 | G74: Oui | H74: Oui | L74: {"support": "ok", "def": {"id": "289234", "region": "rintl", "flag": "🌍", "sport": "rugby", "group": "rugby", "name": "Tests internationaux", "tv": ["TF1"], "tvTeam": "France", "seasonal": true}}
A75: sp:six-nations-f | B75: Rugby · International | C75: Six Nations féminin | D75: rugby | E75: six-nations-f | G75: À développer | J75: à vérifier | K75: Clé ESPN à trouver | L75: {"support": "dev", "def": {"id": "six-nations-f", "region": "rintl", "flag": "🇪🇺", "sport": "rugby", "group": "rugby", "name": "Six Nations féminin"}}
A76: sec:sport:us | B76: Sports US | C76: ▸ toute la section | L76: {"id": "us", "label": "Sports US"}
A77: sp:nba | B77: Sports US | C77: NBA | D77: basketball | E77: nba | F77: beIN Sports, Prime Video | G77: Oui | H77: Oui | L77: {"support": "ok", "def": {"id": "nba", "region": "us", "flag": "🇺🇸", "sport": "basketball", "group": "basket", "name": "NBA", "tv": ["beIN Sports", "Prime Video"], "partial": true}}
A78: sp:nfl | B78: Sports US | C78: NFL | D78: football | E78: nfl | F78: beIN Sports | G78: Oui | H78: Oui | L78: {"support": "ok", "def": {"id": "nfl", "region": "us", "flag": "🇺🇸", "sport": "football", "group": "nfl", "name": "NFL", "tv": ["beIN Sports"], "partial": true, "rounds": true}}
A79: sp:nhl | B79: Sports US | C79: NHL | D79: hockey | E79: nhl | F79: beIN Sports, DAZN | G79: Oui | H79: Oui | L79: {"support": "ok", "def": {"id": "nhl", "region": "us", "flag": "🇺🇸", "sport": "hockey", "group": "hockey", "name": "NHL", "tv": ["beIN Sports", "DAZN"], "partial": true}}
A80: sp:wnba | B80: Sports US | C80: WNBA | D80: basketball | E80: wnba | G80: Oui | J80: à vérifier | L80: {"support": "ok", "def": {"id": "wnba", "region": "us", "flag": "🇺🇸", "sport": "basketball", "group": "basket", "name": "WNBA"}}
A81: sp:mens-college-basketball | B81: Sports US | C81: Basket universitaire (NCAA) | D81: basketball | E81: mens-college-basketball | G81: Oui | J81: à vérifier | L81: {"support": "ok", "def": {"id": "mens-college-basketball", "region": "us", "flag": "🇺🇸", "sport": "basketball", "group": "basket", "name": "Basket universitaire (NCAA)"}}
A82: sp:womens-college-basketball | B82: Sports US | C82: Basket universitaire féminin (NCAA) | D82: basketball | E82: womens-college-basketball | G82: Oui | J82: à vérifier | L82: {"support": "ok", "def": {"id": "womens-college-basketball", "region": "us", "flag": "🇺🇸", "sport": "basketball", "group": "basket", "name": "Basket universitaire féminin (NCAA)"}}
A83: sp:college-football | B83: Sports US | C83: Football américain universitaire (NCAA) | D83: football | E83: college-football | G83: Oui | J83: à vérifier | L83: {"support": "ok", "def": {"id": "college-football", "region": "us", "flag": "🇺🇸", "sport": "football", "group": "nfl", "name": "Football américain universitaire (NCAA)"}}
A84: sp:mlb | B84: Sports US | C84: MLB (baseball) | D84: baseball | E84: mlb | G84: À développer | J84: à vérifier | K84: Fiche de match baseball à développer | L84: {"support": "dev", "def": {"id": "mlb", "region": "us", "flag": "🇺🇸", "sport": "baseball", "group": "baseball", "name": "MLB (baseball)"}}
A85: sec:sport:moto | B85: Sports mécaniques | C85: ▸ toute la section | L85: {"id": "moto", "label": "Sports mécaniques"}
A86: sp:f1 | B86: Sports mécaniques | C86: Formule 1 | D86: racing | E86: f1 | F86: Canal+ | G86: Oui | H86: Oui | I86: Oui | L86: {"support": "ok", "def": {"id": "f1", "region": "moto", "flag": "🏁", "sport": "racing", "group": "f1", "name": "Formule 1", "tv": ["Canal+"]}}
A87: sp:motogp | B87: Sports mécaniques | C87: MotoGP | D87: racing | E87: motogp | F87: Canal+ | G87: Oui | H87: Oui | I87: Oui | L87: {"support": "ok", "def": {"id": "motogp", "region": "moto", "flag": "🏁", "sport": "racing", "group": "motogp", "name": "MotoGP", "tv": ["Canal+"]}}
A88: sp:irl | B88: Sports mécaniques | C88: IndyCar | D88: racing | E88: irl | G88: À développer | H88: Oui | J88: à vérifier | K88: Calendrier et résultats via ESPN | L88: {"support": "dev", "def": {"id": "irl", "region": "moto", "flag": "🏁", "sport": "racing", "group": "indycar", "name": "IndyCar"}}
A89: sp:nascar-premier | B89: Sports mécaniques | C89: NASCAR Cup Series | D89: racing | E89: nascar-premier | G89: À développer | J89: à vérifier | K89: Calendrier et résultats via ESPN | L89: {"support": "dev", "def": {"id": "nascar-premier", "region": "moto", "flag": "🏁", "sport": "racing", "group": "nascar", "name": "NASCAR Cup Series"}}
A90: sec:sport:eur | B90: Europe · autres championnats | C90: ▸ toute la section | L90: {"id": "eur", "label": "Europe · autres championnats"}
A91: sp:sco.1 | B91: Europe · autres championnats | C91: Écosse · Premiership | D91: soccer | E91: sco.1 | G91: Oui | J91: à vérifier | L91: {"support": "ok", "def": {"id": "sco.1", "region": "eur", "flag": "🏴󠁧󠁢󠁳󠁣󠁴󠁿", "sport": "soccer", "group": "foot", "name": "Écosse · Premiership"}}
A92: sp:sco.2 | B92: Europe · autres championnats | C92: Écosse · Championship | D92: soccer | E92: sco.2 | G92: Oui | J92: à vérifier | L92: {"support": "ok", "def": {"id": "sco.2", "region": "eur", "flag": "🏴󠁧󠁢󠁳󠁣󠁴󠁿", "sport": "soccer", "group": "foot", "name": "Écosse · Championship"}}
A93: sp:sco.tennents | B93: Europe · autres championnats | C93: Écosse · Coupe d'Écosse | D93: soccer | E93: sco.tennents | G93: Oui | J93: à vérifier | L93: {"support": "ok", "def": {"id": "sco.tennents", "region": "eur", "flag": "🏴󠁧󠁢󠁳󠁣󠁴󠁿", "sport": "soccer", "group": "foot", "name": "Écosse · Coupe d'Écosse"}}
A94: sp:sco.cis | B94: Europe · autres championnats | C94: Écosse · Coupe de la Ligue | D94: soccer | E94: sco.cis | G94: Oui | J94: à vérifier | L94: {"support": "ok", "def": {"id": "sco.cis", "region": "eur", "flag": "🏴󠁧󠁢󠁳󠁣󠁴󠁿", "sport": "soccer", "group": "foot", "name": "Écosse · Coupe de la Ligue"}}
A95: sp:ned.1 | B95: Europe · autres championnats | C95: Pays-Bas · Eredivisie | D95: soccer | E95: ned.1 | G95: Oui | J95: à vérifier | L95: {"support": "ok", "def": {"id": "ned.1", "region": "eur", "flag": "🇳🇱", "sport": "soccer", "group": "foot", "name": "Pays-Bas · Eredivisie"}}
A96: sp:ned.2 | B96: Europe · autres championnats | C96: Pays-Bas · Eerste Divisie | D96: soccer | E96: ned.2 | G96: Oui | J96: à vérifier | L96: {"support": "ok", "def": {"id": "ned.2", "region": "eur", "flag": "🇳🇱", "sport": "soccer", "group": "foot", "name": "Pays-Bas · Eerste Divisie"}}
A97: sp:ned.cup | B97: Europe · autres championnats | C97: Pays-Bas · Coupe (KNVB Beker) | D97: soccer | E97: ned.cup | G97: Oui | J97: à vérifier | L97: {"support": "ok", "def": {"id": "ned.cup", "region": "eur", "flag": "🇳🇱", "sport": "soccer", "group": "foot", "name": "Pays-Bas · Coupe (KNVB Beker)"}}
A98: sp:por.1 | B98: Europe · autres championnats | C98: Portugal · Liga Portugal | D98: soccer | E98: por.1 | G98: Oui | J98: à vérifier | L98: {"support": "ok", "def": {"id": "por.1", "region": "eur", "flag": "🇵🇹", "sport": "soccer", "group": "foot", "name": "Portugal · Liga Portugal"}}
A99: sp:por.taca.portugal | B99: Europe · autres championnats | C99: Portugal · Coupe du Portugal | D99: soccer | E99: por.taca.portugal | G99: Oui | J99: à vérifier | L99: {"support": "ok", "def": {"id": "por.taca.portugal", "region": "eur", "flag": "🇵🇹", "sport": "soccer", "group": "foot", "name": "Portugal · Coupe du Portugal"}}
A100: sp:bel.1 | B100: Europe · autres championnats | C100: Belgique · Pro League | D100: soccer | E100: bel.1 | G100: Oui | J100: à vérifier | L100: {"support": "ok", "def": {"id": "bel.1", "region": "eur", "flag": "🇧🇪", "sport": "soccer", "group": "foot", "name": "Belgique · Pro League"}}
A101: sp:sui.1 | B101: Europe · autres championnats | C101: Suisse · Super League | D101: soccer | E101: sui.1 | G101: Oui | J101: à vérifier | L101: {"support": "ok", "def": {"id": "sui.1", "region": "eur", "flag": "🇨🇭", "sport": "soccer", "group": "foot", "name": "Suisse · Super League"}}
...

Sheet Équipes favorites
A1: module=equipes;version=2 | B1: Sport · équipes favorites
B2: Les équipes cochées sont mises en avant (étoile, filtre Favoris, bandeau de l'accueil). Écris le nom tel qu'il apparaît dans les matchs (ex. « Stade Toulousain »).
B3: À remplir : cases jaunes (« Oui » ou « Non »). Ligne « ▸ toute la section » = tous ses éléments, sauf ceux marqués « Non ». Un seul élément coché suffit pour que sa section apparaisse. Colonne « Résultat » : remplie par la tâche GitHub après dépôt du classeur.
A5: ID | B5: Section | C5: Équipe | D5: Oui | E5: Résultat | F5: Note | G5: Technique
A6: sec:equipes:actuelles | B6: Mes équipes actuelles | C6: ▸ toute la section | G6: {"id": "actuelles", "label": "Mes équipes actuelles"}
A7: eq:liverpool | B7: Mes équipes actuelles | C7: Liverpool | D7: Oui | G7: {"support": "ok", "def": {"nom": "Liverpool"}}
A8: eq:arsenal | B8: Mes équipes actuelles | C8: Arsenal | D8: Oui | G8: {"support": "ok", "def": {"nom": "Arsenal"}}
A9: eq:marseille | B9: Mes équipes actuelles | C9: Marseille | D9: Oui | G9: {"support": "ok", "def": {"nom": "Marseille"}}
A10: eq:toulouse | B10: Mes équipes actuelles | C10: Toulouse | D10: Oui | G10: {"support": "ok", "def": {"nom": "Toulouse"}}
A11: eq:rodez | B11: Mes équipes actuelles | C11: Rodez | D11: Oui | G11: {"support": "ok", "def": {"nom": "Rodez"}}
A12: eq:castres | B12: Mes équipes actuelles | C12: Castres | D12: Oui | G12: {"support": "ok", "def": {"nom": "Castres"}}
A13: eq:stade-toulousain | B13: Mes équipes actuelles | C13: Stade Toulousain | D13: Oui | G13: {"support": "ok", "def": {"nom": "Stade Toulousain"}}
A14: eq:lakers | B14: Mes équipes actuelles | C14: Lakers | D14: Oui | G14: {"support": "ok", "def": {"nom": "Lakers"}}
A15: eq:packers | B15: Mes équipes actuelles | C15: Packers | D15: Oui | G15: {"support": "ok", "def": {"nom": "Packers"}}
A16: eq:steelers | B16: Mes équipes actuelles | C16: Steelers | D16: Oui | G16: {"support": "ok", "def": {"nom": "Steelers"}}
A17: eq:maple-leafs | B17: Mes équipes actuelles | C17: Maple Leafs | D17: Oui | G17: {"support": "ok", "def": {"nom": "Maple Leafs"}}
A18: sec:equipes:foot-france | B18: Foot · France | C18: ▸ toute la section | G18: {"id": "foot-france", "label": "Foot · France"}
A19: eq:paris-sg | B19: Foot · France | C19: Paris SG | G19: {"support": "ok", "def": {"nom": "Paris SG"}}
A20: eq:lyon | B20: Foot · France | C20: Lyon | G20: {"support": "ok", "def": {"nom": "Lyon"}}
A21: eq:lens | B21: Foot · France | C21: Lens | G21: {"support": "ok", "def": {"nom": "Lens"}}
A22: eq:lille | B22: Foot · France | C22: Lille | G22: {"support": "ok", "def": {"nom": "Lille"}}
A23: eq:monaco | B23: Foot · France | C23: Monaco | D23: Oui | G23: {"support": "ok", "def": {"nom": "Monaco"}}
A24: eq:nice | B24: Foot · France | C24: Nice | G24: {"support": "ok", "def": {"nom": "Nice"}}
A25: eq:rennes | B25: Foot · France | C25: Rennes | G25: {"support": "ok", "def": {"nom": "Rennes"}}
A26: eq:nantes | B26: Foot · France | C26: Nantes | G26: {"support": "ok", "def": {"nom": "Nantes"}}
A27: eq:strasbourg | B27: Foot · France | C27: Strasbourg | G27: {"support": "ok", "def": {"nom": "Strasbourg"}}
A28: eq:montpellier | B28: Foot · France | C28: Montpellier | G28: {"support": "ok", "def": {"nom": "Montpellier"}}
A29: eq:saint-etienne | B29: Foot · France | C29: Saint-Étienne | G29: {"support": "ok", "def": {"nom": "Saint-Étienne"}}
A30: eq:bordeaux | B30: Foot · France | C30: Bordeaux | G30: {"support": "ok", "def": {"nom": "Bordeaux"}}
A31: sec:equipes:foot-europe | B31: Foot · Europe | C31: ▸ toute la section | G31: {"id": "foot-europe", "label": "Foot · Europe"}
A32: eq:real-madrid | B32: Foot · Europe | C32: Real Madrid | G32: {"support": "ok", "def": {"nom": "Real Madrid"}}
A33: eq:fc-barcelone | B33: Foot · Europe | C33: FC Barcelone | G33: {"support": "ok", "def": {"nom": "FC Barcelone"}}
A34: eq:bayern-munich | B34: Foot · Europe | C34: Bayern Munich | G34: {"support": "ok", "def": {"nom": "Bayern Munich"}}
A35: eq:manchester-city | B35: Foot · Europe | C35: Manchester City | G35: {"support": "ok", "def": {"nom": "Manchester City"}}
... A65: eq:yankees | B65: US | C65: Yankees | G65: {"support": "ok", "def": {"nom": "Yankees"}}
B68: MES AJOUTS — tape ce que tu veux ajouter : la tâche essaie de le récupérer et écrit le résultat (✅ / ⚠️ / ❌) dans la colonne « Résultat »
B69: Catégorie | C69: Nom de l'équipe | D69: Oui | E69: Résultat | F69: Note
A70: exemple | B70: Mes équipes actuelles | C70: Montpellier HSC | D70: Oui | F70: Ligne d'exemple : ignorée par la tâche
A71: ajout:1
A72: ajout:2
A73: ajout:3
A74: ajout:4
A75: ajout:5
A76: ajout:6
A77: ajout:7
A78: ajout:8
A79: ajout:9
A80: ajout:10
A81: ajout:11
A82: ajout:12
... A90: ajout:20

Sheet Actus
A1: module=actus;version=2 | B1: Actus · rubriques et médias (français)
B2: Une rubrique = un onglet de la page Actus. Coche un média : sa rubrique apparaît avec lui. Coche la ligne « toute la rubrique » pour prendre tous ses médias (et mets « Non » sur ceux que tu ne veux pas). Les flux « Google » suivent un mot-clé plutôt qu'un site.
B3: À remplir : cases jaunes (« Oui » ou « Non »). Ligne « ▸ toute la section » = tous ses éléments, sauf ceux marqués « Non ». Un seul élément coché suffit pour que sa section apparaisse. Colonne « Résultat » : remplie par la tâche GitHub après dépôt du classeur.
A5: ID | B5: Section | C5: Média | D5: Adresse du flux | E5: Site (secours) | F5: Oui | G5: Résultat | H5: Note | I5: Technique
A6: sec:actus:une | B6: À la une | C6: ▸ toute la section | I6: {"id": "une", "label": "À la une", "liste": "principal"}
A7: actus:une:france-info | B7: À la une | C7: France Info | D7: https://www.francetvinfo.fr/titres.rss | F7: Oui | I7: {"support": "ok", "def": {"name": "France Info", "color": "#f2b705", "url": "https://www.francetvinfo.fr/titres.rss"}}
A8: actus:une:le-monde | B8: À la une | C8: Le Monde | D8: https://www.lemonde.fr/rss/une.xml | F8: Oui | I8: {"support": "ok", "def": {"name": "Le Monde", "color": "#2b2b2b", "url": "https://www.lemonde.fr/rss/une.xml"}}
A9: actus:une:le-figaro | B9: À la une | C9: Le Figaro | D9: https://www.lefigaro.fr/rss/figaro_actualites.xml | F9: Oui | I9: {"support": "ok", "def": {"name": "Le Figaro", "color": "#163860", "url": "https://www.lefigaro.fr/rss/figaro_actualites.xml"}}
A10: actus:une:liberation | B10: À la une | C10: Libération | D10: https://www.liberation.fr/arc/outboundfeeds/rss-all/?outputType=xml | F10: Oui | I10: {"support": "ok", "def": {"name": "Libération", "color": "#e2001a", "url": "https://www.liberation.fr/arc/outboundfeeds/rss-all/?outputType=xml"}}
A11: actus:une:20-minutes | B11: À la une | C11: 20 Minutes | D11: https://www.20minutes.fr/feeds/rss-une.xml | F11: Oui | I11: {"support": "ok", "def": {"name": "20 Minutes", "color": "#0b5fb4", "url": "https://www.20minutes.fr/feeds/rss-une.xml"}}
A12: actus:une:ouest-france | B12: À la une | C12: Ouest-France | D12: https://www.ouest-france.fr/rss/une | E12: https://www.ouest-france.fr/ | G12: à vérifier | I12: {"support": "ok", "def": {"name": "Ouest-France", "color": "#e2001a", "url": "https://www.ouest-france.fr/rss/une", "site": "https://www.ouest-france.fr/", "alt": ["https://news.google.com/rss/search?q=site:ouest-france.fr&hl=fr&gl=FR&ceid=FR:fr"]}}
A13: actus:une:le-parisien | B13: À la une | C13: Le Parisien | D13: https://feeds.leparisien.fr/leparisien/rss | E13: https://www.leparisien.fr/ | G13: à vérifier | I13: {"support": "ok", "def": {"name": "Le Parisien", "color": "#1a4c8b", "url": "https://feeds.leparisien.fr/leparisien/rss", "site": "https://www.leparisien.fr/", "alt": ["https://news.google.com/rss/search?q=site:leparisien.fr&hl=fr&gl=FR&ceid=FR:fr"]}}
A14: actus:une:le-point | B14: À la une | C14: Le Point | D14: https://www.lepoint.fr/rss.xml | E14: https://www.lepoint.fr/ | G14: à vérifier | I14: {"support": "ok", "def": {"name": "Le Point", "color": "#c8102e", "url": "https://www.lepoint.fr/rss.xml", "site": "https://www.lepoint.fr/", "alt": ["https://news.google.com/rss/search?q=site:lepoint.fr&hl=fr&gl=FR&ceid=FR:fr"]}}
A15: actus:une:l-express | B15: À la une | C15: L'Express | D15: https://www.lexpress.fr/arc/outboundfeeds/rss/alaune.xml | E15: https://www.lexpress.fr/ | G15: à vérifier | I15: {"support": "ok", "def": {"name": "L'Express", "color": "#e2001a", "url": "https://www.lexpress.fr/arc/outboundfeeds/rss/alaune.xml", "site": "https://www.lexpress.fr/", "alt": ["https://news.google.com/rss/search?q=site:lexpress.fr&hl=fr&gl=FR&ceid=FR:fr"]}}
A16: actus:une:la-croix | B16: À la une | C16: La Croix | D16: https://www.la-croix.com/RSS/UNIVERS | E16: https://www.la-croix.com/ | G16: à vérifier | I16: {"support": "ok", "def": {"name": "La Croix", "color": "#1f3f75", "url": "https://www.la-croix.com/RSS/UNIVERS", "site": "https://www.la-croix.com/", "alt": ["https://news.google.com/rss/search?q=site:la-croix.com&hl=fr&gl=FR&ceid=FR:fr"]}}
A17: actus:une:huffpost | B17: À la une | C17: HuffPost | D17: https://www.huffingtonpost.fr/feeds/index.xml | E17: https://www.huffingtonpost.fr/ | G17: à vérifier | I17: {"support": "ok", "def": {"name": "HuffPost", "color": "#0dbe98", "url": "https://www.huffingtonpost.fr/feeds/index.xml", "site": "https://www.huffingtonpost.fr/", "alt": ["https://news.google.com/rss/search?q=site:huffingtonpost.fr&hl=fr&gl=FR&ceid=FR:fr"]}}
A18: actus:une:bfmtv | B18: À la une | C18: BFMTV | D18: https://www.bfmtv.com/rss/news-24-7/ | E18: https://www.bfmtv.com/ | G18: à vérifier | I18: {"support": "ok", "def": {"name": "BFMTV", "color": "#0a2c5a", "url": "https://www.bfmtv.com/rss/news-24-7/", "site": "https://www.bfmtv.com/", "alt": ["https://news.google.com/rss/search?q=site:bfmtv.com&hl=fr&gl=FR&ceid=FR:fr"]}}
A19: actus:une:tf1-info | B19: À la une | C19: TF1 Info | D19: https://www.tf1info.fr/feeds/rss-une.xml | E19: https://www.tf1info.fr/ | G19: à vérifier | I19: {"support": "ok", "def": {"name": "TF1 Info", "color": "#0067b1", "url": "https://www.tf1info.fr/feeds/rss-une.xml", "site": "https://www.tf1info.fr/", "alt": ["https://news.google.com/rss/search?q=site:tf1info.fr&hl=fr&gl=FR&ceid=FR:fr"]}}
A20: actus:une:france-24 | B20: À la une | C20: France 24 | D20: https://www.france24.com/fr/rss | E20: https://www.france24.com/fr/ | G20: à vérifier | I20: {"support": "ok", "def": {"name": "France 24", "color": "#00a3e0", "url": "https://www.france24.com/fr/rss", "site": "https://www.france24.com/fr/", "alt": ["https://news.google.com/rss/search?q=site:france24.com&hl=fr&gl=FR&ceid=FR:fr"]}}
A21: actus:une:rfi | B21: À la une | C21: RFI | D21: https://www.rfi.fr/fr/rss | E21: https://www.rfi.fr/fr/ | G21: à vérifier | I21: {"support": "ok", "def": {"name": "RFI", "color": "#e5004d", "url": "https://www.rfi.fr/fr/rss", "site": "https://www.rfi.fr/fr/", "alt": ["https://news.google.com/rss/search?q=site:rfi.fr&hl=fr&gl=FR&ceid=FR:fr"]}}
A22: actus:une:mediapart | B22: À la une | C22: Mediapart | D22: https://www.mediapart.fr/articles/feed | E22: https://www.mediapart.fr/ | G22: à vérifier | I22: {"support": "ok", "def": {"name": "Mediapart", "color": "#e5004c", "url": "https://www.mediapart.fr/articles/feed", "site": "https://www.mediapart.fr/", "alt": ["https://news.google.com/rss/search?q=site:mediapart.fr&hl=fr&gl=FR&ceid=FR:fr"]}}
A23: actus:une:l-humanite | B23: À la une | C23: L'Humanité | D23: https://www.humanite.fr/feed | E23: https://www.humanite.fr/ | G23: à vérifier | I23: {"support": "ok", "def": {"name": "L'Humanité", "color": "#d30000", "url": "https://www.humanite.fr/feed", "site": "https://www.humanite.fr/", "alt": ["https://news.google.com/rss/search?q=site:humanite.fr&hl=fr&gl=FR&ceid=FR:fr"]}}
... A25: actus:une:europe-1 | B25: À la une | C25: Europe 1 | D25: https://www.europe1.fr/rss.xml | E25: https://www.europe1.fr/ | G25: à vérifier | I25: {"support": "ok", "def": {"name": "Europe 1", "color": "#e30613", "url": "https://www.europe1.fr/rss.xml", "site": "https://www.europe1.fr/", "alt": ["https://news.google.com/rss/search?q=site:europe1.fr&hl=fr&gl=FR&ceid=FR:fr"]}}
A26: sec:actus:france | B26: France | C26: ▸ toute la section | I26: {"id": "france", "label": "France", "liste": "principal"}
A27: actus:france:france-info | B27: France | C27: France Info | D27: https://www.francetvinfo.fr/france.rss | F27: Oui | I27: {"support": "ok", "def": {"name": "France Info", "color": "#f2b705", "url": "https://www.francetvinfo.fr/france.rss"}}
A28: actus:france:le-monde | B28: France | C28: Le Monde | D28: https://www.lemonde.fr/politique/rss_full.xml | F28: Oui | I28: {"support": "ok", "def": {"name": "Le Monde", "color": "#2b2b2b", "url": "https://www.lemonde.fr/politique/rss_full.xml"}}
A29: actus:france:le-figaro | B29: France | C29: Le Figaro | D29: https://www.lefigaro.fr/rss/figaro_politique.xml | F29: Oui | I29: {"support": "ok", "def": {"name": "Le Figaro", "color": "#163860", "url": "https://www.lefigaro.fr/rss/figaro_politique.xml"}}
A30: actus:france:public-senat | B30: France | C30: Public Sénat | D30: https://www.publicsenat.fr/rss.xml | E30: https://www.publicsenat.fr/ | G30: à vérifier | I30: {"support": "ok", "def": {"name": "Public Sénat", "color": "#c8102e", "url": "https://www.publicsenat.fr/rss.xml", "site": "https://www.publicsenat.fr/", "alt": ["https://news.google.com/rss/search?q=site:publicsenat.fr&hl=fr&gl=FR&ceid=FR:fr"]}}
A31: actus:france:lcp | B31: France | C31: LCP | D31: https://lcp.fr/rss.xml | E31: https://lcp.fr/ | G31: à vérifier | I31: {"support": "ok", "def": {"name": "LCP", "color": "#003c71", "url": "https://lcp.fr/rss.xml", "site": "https://lcp.fr/", "alt": ["https://news.google.com/rss/search?q=site:lcp.fr&hl=fr&gl=FR&ceid=FR:fr"]}}
A32: actus:france:france-info-politique | B32: France | C32: France Info · Politique | D32: https://www.francetvinfo.fr/politique.rss | G32: à vérifier | I32: {"support": "ok", "def": {"name": "France Info · Politique", "color": "#f2b705", "url": "https://www.francetvinfo.fr/politique.rss", "alt": ["https://news.google.com/rss/search?q=site:francetvinfo.fr&hl=fr&gl=FR&ceid=FR:fr"]}}
A33: actus:france:vie-publique-fr | B33: France | C33: Vie-publique.fr | D33: https://www.vie-publique.fr/actualites.xml | E33: https://www.vie-publique.fr/ | G33: à vérifier | I33: {"support": "ok", "def": {"name": "Vie-publique.fr", "color": "#000091", "url": "https://www.vie-publique.fr/actualites.xml", "site": "https://www.vie-publique.fr/", "alt": ["https://news.google.com/rss/search?q=site:vie-publique.fr&hl=fr&gl=FR&ceid=FR:fr"]}}
A34: sec:actus:monde | B34: Monde | C34: ▸ toute la section | I34: {"id": "monde", "label": "Monde", "liste": "principal"}
A35: actus:monde:france-info | B35: Monde | C35: France Info | D35: https://www.francetvinfo.fr/monde.rss | F35: Oui | I35: {"support": "ok", "def": {"name": "France Info", "color": "#f2b705", "url": "https://www.francetvinfo.fr/monde.rss"}}
A36: actus:monde:le-monde | B36: Monde | C36: Le Monde | D36: https://www.lemonde.fr/international/rss_full.xml | F36: Oui | I36: {"support": "ok", "def": {"name": "Le Monde", "color": "#2b2b2b", "url": "https://www.lemonde.fr/international/rss_full.xml"}}
A37: actus:monde:courrier-international | B37: Monde | C37: Courrier international | D37: https://www.courrierinternational.com/feed/all/rss.xml | F37: Oui | I37: {"support": "ok", "def": {"name": "Courrier international", "color": "#c8102e", "url": "https://www.courrierinternational.com/feed/all/rss.xml"}}
A38: actus:monde:france-24-monde | B38: Monde | C38: France 24 · Monde | D38: https://www.france24.com/fr/monde/rss | E38: https://www.france24.com/fr/ | G38: à vérifier | I38: {"support": "ok", "def": {"name": "France 24 · Monde", "color": "#00a3e0", "url": "https://www.france24.com/fr/monde/rss", "site": "https://www.france24.com/fr/", "alt": ["https://news.google.com/rss/search?q=site:france24.com&hl=fr&gl=FR&ceid=FR:fr"]}}
A39: actus:monde:rfi-monde | B39: Monde | C39: RFI · Monde | D39: https://www.rfi.fr/fr/monde/rss | E39: https://www.rfi.fr/fr/ | G39: à vérifier | I39: {"support": "ok", "def": {"name": "RFI · Monde", "color": "#e5004d", "url": "https://www.rfi.fr/fr/monde/rss", "site": "https://www.rfi.fr/fr/", "alt": ["https://news.google.com/rss/search?q=site:rfi.fr&hl=fr&gl=FR&ceid=FR:fr"]}}
A40: actus:monde:le-grand-continent | B40: Monde | C40: Le Grand Continent | D40: https://legrandcontinent.eu/fr/feed/ | E40: https://legrandcontinent.eu/fr/ | G40: à vérifier | I40: {"support": "ok", "def": {"name": "Le Grand Continent", "color": "#111111", "url": "https://legrandcontinent.eu/fr/feed/", "site": "https://legrandcontinent.eu/fr/", "alt": ["https://news.google.com/rss/search?q=site:legrandcontinent.eu&hl=fr&gl=FR&ceid=FR:fr"]}}
A41: actus:monde:le-monde-diplomatique | B41: Monde | C41: Le Monde diplomatique | D41: https://www.monde-diplomatique.fr/rss/ | E41: https://www.monde-diplomatique.fr/ | G41: à vérifier | I41: {"support": "ok", "def": {"name": "Le Monde diplomatique", "color": "#5a0f0f", "url": "https://www.monde-diplomatique.fr/rss/", "site": "https://www.monde-diplomatique.fr/", "alt": ["https://news.google.com/rss/search?q=site:monde-diplomatique.fr&hl=fr&gl=FR&ceid=FR:fr"]}}
A42: actus:monde:tv5monde-info | B42: Monde | C42: TV5Monde Info | D42: https://information.tv5monde.com/rss.xml | E42: https://information.tv5monde.com/ | G42: à vérifier | I42: {"support": "ok", "def": {"name": "TV5Monde Info", "color": "#2a2a7a", "url": "https://information.tv5monde.com/rss.xml", "site": "https://information.tv5monde.com/", "alt": ["https://news.google.com/rss/search?q=site:information.tv5monde.com&hl=fr&gl=FR&ceid=FR:fr"]}}
A43: sec:actus:eco | B43: Éco | C43: ▸ toute la section | I43: {"id": "eco", "label": "Éco", "liste": "principal"}
A44: actus:eco:les-echos | B44: Éco | C44: Les Échos | D44: https://syndication.lesechos.fr/rss/rss_une.xml | E44: https://www.lesechos.fr/ | F44: Oui | I44: {"support": "ok", "def": {"name": "Les Échos", "color": "#8a1538", "url": "https://syndication.lesechos.fr/rss/rss_une.xml", "site": "https://www.lesechos.fr/", "alt": ["https://news.google.com/rss/search?q=site:lesechos.fr&hl=fr&gl=FR&ceid=FR:fr"]}}
A45: actus:eco:la-tribune | B45: Éco | C45: La Tribune | D45: https://www.latribune.fr/feed.xml | E45: https://www.latribune.fr/ | F45: Oui | I45: {"support": "ok", "def": {"name": "La Tribune", "color": "#0b6a8a", "url": "https://www.latribune.fr/feed.xml", "site": "https://www.latribune.fr/", "alt": ["https://news.google.com/rss/search?q=site:latribune.fr&hl=fr&gl=FR&ceid=FR:fr"]}}
A46: actus:eco:l-usine-nouvelle | B46: Éco | C46: L'Usine Nouvelle | D46: https://www.usinenouvelle.com/rss/ | F46: Oui | I46: {"support": "ok", "def": {"name": "L'Usine Nouvelle", "color": "#f08a00", "url": "https://www.usinenouvelle.com/rss/"}}
A47: actus:eco:france-info | B47: Éco | C47: France Info | D47: https://www.francetvinfo.fr/economie.rss | F47: Oui | I47: {"support": "ok", "def": {"name": "France Info", "color": "#f2b705", "url": "https://www.francetvinfo.fr/economie.rss"}}
A48: actus:eco:le-monde | B48: Éco | C48: Le Monde | D48: https://www.lemonde.fr/economie/rss_full.xml | F48: Oui | I48: {"support": "ok", "def": {"name": "Le Monde", "color": "#2b2b2b", "url": "https://www.lemonde.fr/economie/rss_full.xml"}}
A49: actus:eco:capital | B49: Éco | C49: Capital | D49: https://www.capital.fr/rss | E49: https://www.capital.fr/ | G49: à vérifier | I49: {"support": "ok", "def": {"name": "Capital", "color": "#e2001a", "url": "https://www.capital.fr/rss", "site": "https://www.capital.fr/", "alt": ["https://news.google.com/rss/search?q=site:capital.fr&hl=fr&gl=FR&ceid=FR:fr"]}}
A50: actus:eco:challenges | B50: Éco | C50: Challenges | D50: https://www.challenges.fr/rss.xml | E50: https://www.challenges.fr/ | G50: à vérifier | I50: {"support": "ok", "def": {"name": "Challenges", "color": "#c8102e", "url": "https://www.challenges.fr/rss.xml", "site": "https://www.challenges.fr/", "alt": ["https://news.google.com/rss/search?q=site:challenges.fr&hl=fr&gl=FR&ceid=FR:fr"]}}
A51: actus:eco:bfm-business | B51: Éco | C51: BFM Business | D51: https://www.bfmtv.com/rss/economie/ | E51: https://www.bfmtv.com/economie/ | G51: à vérifier | I51: {"support": "ok", "def": {"name": "BFM Business", "color": "#0a2c5a", "url": "https://www.bfmtv.com/rss/economie/", "site": "https://www.bfmtv.com/economie/", "alt": ["https://news.google.com/rss/search?q=site:bfmtv.com&hl=fr&gl=FR&ceid=FR:fr"]}}
A52: actus:eco:alternatives-economiques | B52: Éco | C52: Alternatives Économiques | D52: https://www.alternatives-economiques.fr/rss.xml | E52: https://www.alternatives-economiques.fr/ | G52: à vérifier | I52: {"support": "ok", "def": {"name": "Alternatives Économiques", "color": "#e94e1b", "url": "https://www.alternatives-economiques.fr/rss.xml", "site": "https://www.alternatives-economiques.fr/", "alt": ["https://news.google.com/rss/search?q=site:alternatives-economiques.fr&hl=fr&gl=FR&ceid=FR:fr"]}}
A53: actus:eco:le-figaro-economie | B53: Éco | C53: Le Figaro Économie | D53: https://www.lefigaro.fr/rss/figaro_economie.xml | G53: à vérifier | I53: {"support": "ok", "def": {"name": "Le Figaro Économie", "color": "#163860", "url": "https://www.lefigaro.fr/rss/figaro_economie.xml", "alt": ["https://news.google.com/rss/search?q=site:lefigaro.fr&hl=fr&gl=FR&ceid=FR:fr"]}}
A54: actus:eco:insee | B54: Éco | C54: Insee | D54: https://www.insee.fr/fr/flux/1 | E54: https://www.insee.fr/fr/accueil | G54: à vérifier | I54: {"support": "ok", "def": {"name": "Insee", "color": "#ab1f33", "url": "https://www.insee.fr/fr/flux/1", "site": "https://www.insee.fr/fr/accueil", "alt": ["https://news.google.com/rss/search?q=site:insee.fr&hl=fr&gl=FR&ceid=FR:fr"]}}
A55: sec:actus:sport | B55: Sport | C55: ▸ toute la section | I55: {"id": "sport", "label": "Sport", "liste": "principal"}
A56: actus:sport:l-equipe | B56: Sport | C56: L'Équipe | D56: https://dwh.lequipe.fr/api/edito/rss?path=/ | F56: Oui | I56: {"support": "ok", "def": {"name": "L'Équipe", "color": "#e30613", "url": "https://dwh.lequipe.fr/api/edito/rss?path=/"}}
A57: actus:sport:l-equipe-rugby | B57: Sport | C57: L'Équipe Rugby | D57: https://dwh.lequipe.fr/api/edito/rss?path=/Rugby/ | F57: Oui | I57: {"support": "ok", "def": {"name": "L'Équipe Rugby", "color": "#a3121a", "url": "https://dwh.lequipe.fr/api/edito/rss?path=/Rugby/"}}
A58: actus:sport:rmc-sport | B58: Sport | C58: RMC Sport | D58: https://rmcsport.bfmtv.com/rss/info/flux-rss/flux-toutes-les-actualites/ | E58: https://rmcsport.bfmtv.com/ | F58: Oui | I58: {"support": "ok", "def": {"name": "RMC Sport", "color": "#4a4a4a", "url": "https://rmcsport.bfmtv.com/rss/info/flux-rss/flux-toutes-les-actualites/", "site": "https://rmcsport.bfmtv.com/", "alt": ["https://news.google.com/rss/search?q=site:rmcsport.bfmtv.com&hl=fr&gl=FR&ceid=FR:fr"]}}
A59: actus:sport:france-info | B59: Sport | C59: France Info | D59: https://www.francetvinfo.fr/sports.rss | F59: Oui | I59: {"support": "ok", "def": {"name": "France Info", "color": "#f2b705", "url": "https://www.francetvinfo.fr/sports.rss"}}
A60: actus:sport:l-equipe-football | B60: Sport | C60: L'Équipe Football | D60: https://dwh.lequipe.fr/api/edito/rss?path=/Football/ | G60: à vérifier | I60: {"support": "ok", "def": {"name": "L'Équipe Football", "color": "#e30613", "url": "https://dwh.lequipe.fr/api/edito/rss?path=/Football/"}}
A61: actus:sport:l-equipe-tennis | B61: Sport | C61: L'Équipe Tennis | D61: https://dwh.lequipe.fr/api/edito/rss?path=/Tennis/ | G61: à vérifier | I61: {"support": "ok", "def": {"name": "L'Équipe Tennis", "color": "#e30613", "url": "https://dwh.lequipe.fr/api/edito/rss?path=/Tennis/"}}
A62: actus:sport:l-equipe-cyclisme | B62: Sport | C62: L'Équipe Cyclisme | D62: https://dwh.lequipe.fr/api/edito/rss?path=/Cyclisme/ | G62: à vérifier | I62: {"support": "ok", "def": {"name": "L'Équipe Cyclisme", "color": "#e30613", "url": "https://dwh.lequipe.fr/api/edito/rss?path=/Cyclisme/"}}
A63: actus:sport:l-equipe-basket | B63: Sport | C63: L'Équipe Basket | D63: https://dwh.lequipe.fr/api/edito/rss?path=/Basket/ | G63: à vérifier | I63: {"support": "ok", "def": {"name": "L'Équipe Basket", "color": "#e30613", "url": "https://dwh.lequipe.fr/api/edito/rss?path=/Basket/"}}
A64: actus:sport:l-equipe-formule-1 | B64: Sport | C64: L'Équipe Formule 1 | D64: https://dwh.lequipe.fr/api/edito/rss?path=/Formule-1/ | G64: à vérifier | I64: {"support": "ok", "def": {"name": "L'Équipe Formule 1", "color": "#e30613", "url": "https://dwh.lequipe.fr/api/edito/rss?path=/Formule-1/"}}
A65: actus:sport:l-equipe-handball | B65: Sport | C65: L'Équipe Handball | D65: https://dwh.lequipe.fr/api/edito/rss?path=/Handball/ | G65: à vérifier | I65: {"support": "ok", "def": {"name": "L'Équipe Handball", "color": "#e30613", "url": "https://dwh.lequipe.fr/api/edito/rss?path=/Handball/"}}
A66: actus:sport:eurosport | B66: Sport | C66: Eurosport | D66: https://www.eurosport.fr/rss.xml | E66: https://www.eurosport.fr/ | G66: à vérifier | I66: {"support": "ok", "def": {"name": "Eurosport", "color": "#141b4d", "url": "https://www.eurosport.fr/rss.xml", "site": "https://www.eurosport.fr/", "alt": ["https://news.google.com/rss/search?q=site:eurosport.fr&hl=fr&gl=FR&ceid=FR:fr"]}}
A67: actus:sport:so-foot | B67: Sport | C67: So Foot | D67: https://www.sofoot.com/rss.xml | E67: https://www.sofoot.com/ | G67: à vérifier | I67: {"support": "ok", "def": {"name": "So Foot", "color": "#111111", "url": "https://www.sofoot.com/rss.xml", "site": "https://www.sofoot.com/", "alt": ["https://news.google.com/rss/search?q=site:sofoot.com&hl=fr&gl=FR&ceid=FR:fr"]}}
A68: actus:sport:foot-mercato | B68: Sport | C68: Foot Mercato | D68: https://www.footmercato.net/flux-rss | E68: https://www.footmercato.net/ | G68: à vérifier | I68: {"support": "ok", "def": {"name": "Foot Mercato", "color": "#0e9f6e", "url": "https://www.footmercato.net/flux-rss", "site": "https://www.footmercato.net/", "alt": ["https://news.google.com/rss/search?q=site:footmercato.net&hl=fr&gl=FR&ceid=FR:fr"]}}
A69: actus:sport:rugbyrama | B69: Sport | C69: Rugbyrama | D69: https://www.rugbyrama.fr/rss.xml | E69: https://www.rugbyrama.fr/ | G69: à vérifier | I69: {"support": "ok", "def": {"name": "Rugbyrama", "color": "#0b6e4f", "url": "https://www.rugbyrama.fr/rss.xml", "site": "https://www.rugbyrama.fr/", "alt": ["https://news.google.com/rss/search?q=site:rugbyrama.fr&hl=fr&gl=FR&ceid=FR:fr"]}}
A70: actus:sport:midi-olympique | B70: Sport | C70: Midi Olympique | D70: https://www.midi-olympique.fr/rss | E70: https://www.midi-olympique.fr/ | G70: à vérifier | I70: {"support": "ok", "def": {"name": "Midi Olympique", "color": "#c8102e", "url": "https://www.midi-olympique.fr/rss", "site": "https://www.midi-olympique.fr/", "alt": ["https://news.google.com/rss/search?q=site:midi-olympique.fr&hl=fr&gl=FR&ceid=FR:fr"]}}
A71: actus:sport:le-rugbynistere | B71: Sport | C71: Le Rugbynistère | D71: https://www.lerugbynistere.fr/feed | E71: https://www.lerugbynistere.fr/ | G71: à vérifier | I71: {"support": "ok", "def": {"name": "Le Rugbynistère", "color": "#1d5c2e", "url": "https://www.lerugbynistere.fr/feed", "site": "https://www.lerugbynistere.fr/", "alt": ["https://news.google.com/rss/search?q=site:lerugbynistere.fr&hl=fr&gl=FR&ceid=FR:fr"]}}
A72: sec:actus:tech | B72: Tech | C72: ▸ toute la section | I72: {"id": "tech", "label": "Tech", "liste": "principal"}
A73: actus:tech:numerama | B73: Tech | C73: Numerama | D73: https://www.numerama.com/feed/ | F73: Oui | I73: {"support": "ok", "def": {"name": "Numerama", "color": "#e4007c", "url": "https://www.numerama.com/feed/"}}
A74: actus:tech:les-numeriques | B74: Tech | C74: Les Numériques | D74: https://www.lesnumeriques.com/rss.xml | F74: Oui | I74: {"support": "ok", "def": {"name": "Les Numériques", "color": "#0a8f6a", "url": "https://www.lesnumeriques.com/rss.xml"}}
A75: actus:tech:frandroid | B75: Tech | C75: Frandroid | D75: https://www.frandroid.com/feed | F75: Oui | I75: {"support": "ok", "def": {"name": "Frandroid", "color": "#29a8e0", "url": "https://www.frandroid.com/feed"}}
A76: actus:tech:01net | B76: Tech | C76: 01net | D76: https://www.01net.com/feed/ | F76: Oui | I76: {"support": "ok", "def": {"name": "01net", "color": "#d6002a", "url": "https://www.01net.com/feed/"}}
A77: actus:tech:next | B77: Tech | C77: Next | D77: https://next.ink/feed/ | E77: https://next.ink/ | G77: à vérifier | I77: {"support": "ok", "def": {"name": "Next", "color": "#ff5a1f", "url": "https://next.ink/feed/", "site": "https://next.ink/", "alt": ["https://news.google.com/rss/search?q=site:next.ink&hl=fr&gl=FR&ceid=FR:fr"]}}
A78: actus:tech:clubic | B78: Tech | C78: Clubic | D78: https://www.clubic.com/feed/news.rss | E78: https://www.clubic.com/ | G78: à vérifier | I78: {"support": "ok", "def": {"name": "Clubic", "color": "#0057b8", "url": "https://www.clubic.com/feed/news.rss", "site": "https://www.clubic.com/", "alt": ["https://news.google.com/rss/search?q=site:clubic.com&hl=fr&gl=FR&ceid=FR:fr"]}}
A79: actus:tech:korben | B79: Tech | C79: Korben | D79: https://korben.info/feed | E79: https://korben.info/ | G79: à vérifier | I79: {"support": "ok", "def": {"name": "Korben", "color": "#1e1e1e", "url": "https://korben.info/feed", "site": "https://korben.info/", "alt": ["https://news.google.com/rss/search?q=site:korben.info&hl=fr&gl=FR&ceid=FR:fr"]}}
A80: actus:tech:journal-du-geek | B80: Tech | C80: Journal du Geek | D80: https://www.journaldugeek.com/feed/ | E80: https://www.journaldugeek.com/ | G80: à vérifier | I80: {"support": "ok", "def": {"name": "Journal du Geek", "color": "#e5004d", "url": "https://www.journaldugeek.com/feed/", "site": "https://www.journaldugeek.com/", "alt": ["https://news.google.com/rss/search?q=site:journaldugeek.com&hl=fr&gl=FR&ceid=FR:fr"]}}
A81: actus:tech:presse-citron | B81: Tech | C81: Presse-citron | D81: https://www.presse-citron.net/feed/ | E81: https://www.presse-citron.net/ | G81: à vérifier | I81: {"support": "ok", "def": {"name": "Presse-citron", "color": "#f5a300", "url": "https://www.presse-citron.net/feed/", "site": "https://www.presse-citron.net/", "alt": ["https://news.google.com/rss/search?q=site:presse-citron.net&hl=fr&gl=FR&ceid=FR:fr"]}}
A82: actus:tech:igeneration-apple | B82: Tech | C82: iGeneration (Apple) | D82: https://www.igen.fr/rss.xml | E82: https://www.igen.fr/ | G82: à vérifier | I82: {"support": "ok", "def": {"name": "iGeneration (Apple)", "color": "#3b82f6", "url": "https://www.igen.fr/rss.xml", "site": "https://www.igen.fr/", "alt": ["https://news.google.com/rss/search?q=site:igen.fr&hl=fr&gl=FR&ceid=FR:fr"]}}
A83: actus:tech:macgeneration | B83: Tech | C83: MacGeneration | D83: https://www.macg.co/rss.xml | E83: https://www.macg.co/ | G83: à vérifier | I83: {"support": "ok", "def": {"name": "MacGeneration", "color": "#4c4c4c", "url": "https://www.macg.co/rss.xml", "site": "https://www.macg.co/", "alt": ["https://news.google.com/rss/search?q=site:macg.co&hl=fr&gl=FR&ceid=FR:fr"]}}
A84: actus:tech:zdnet-france | B84: Tech | C84: ZDNet France | D84: https://www.zdnet.fr/feeds/rss/ | E84: https://www.zdnet.fr/ | G84: à vérifier | I84: {"support": "ok", "def": {"name": "ZDNet France", "color": "#d41f2b", "url": "https://www.zdnet.fr/feeds/rss/", "site": "https://www.zdnet.fr/", "alt": ["https://news.google.com/rss/search?q=site:zdnet.fr&hl=fr&gl=FR&ceid=FR:fr"]}}
A85: actus:tech:le-monde-informatique | B85: Tech | C85: Le Monde Informatique | D85: https://www.lemondeinformatique.fr/flux-rss/thematique/toutes-les-actualites/rss.xml | E85: https://www.lemondeinformatique.fr/ | G85: à vérifier | I85: {"support": "ok", "def": {"name": "Le Monde Informatique", "color": "#00539f", "url": "https://www.lemondeinformatique.fr/flux-rss/thematique/toutes-les-actualites/rss.xml", "site": "https://www.lemondeinformatique.fr/", "alt": ["https://news.google.com/rss/search?q=site:lemondeinformatique.fr&hl=fr&gl=FR&ceid=FR:fr"]}}
A86: actus:tech:le-monde-pixels | B86: Tech | C86: Le Monde Pixels | D86: https://www.lemonde.fr/pixels/rss_full.xml | G86: à vérifier | I86: {"support": "ok", "def": {"name": "Le Monde Pixels", "color": "#2b2b2b", "url": "https://www.lemonde.fr/pixels/rss_full.xml", "alt": ["https://news.google.com/rss/search?q=site:lemonde.fr&hl=fr&gl=FR&ceid=FR:fr"]}}
A87: actus:tech:siecle-digital | B87: Tech | C87: Siècle Digital | D87: https://siecledigital.fr/feed/ | E87: https://siecledigital.fr/ | G87: à vérifier | I87: {"support": "ok", "def": {"name": "Siècle Digital", "color": "#7c3aed", "url": "https://siecledigital.fr/feed/", "site": "https://siecledigital.fr/", "alt": ["https://news.google.com/rss/search?q=site:siecledigital.fr&hl=fr&gl=FR&ceid=FR:fr"]}}
A88: sec:actus:local | B88: Tarn | C88: ▸ toute la section | I88: {"id": "local", "label": "Tarn", "liste": "principal"}
A89: actus:local:le-tarn-libre | B89: Tarn | C89: Le Tarn Libre | D89: https://www.letarnlibre.com/feed/ | E89: https://www.letarnlibre.com/ | F89: Oui | I89: {"support": "ok", "def": {"name": "Le Tarn Libre", "color": "#e85d0c", "url": "https://www.letarnlibre.com/feed/", "site": "https://www.letarnlibre.com/", "alt": ["https://news.google.com/rss/search?q=site:letarnlibre.com&hl=fr&gl=FR&ceid=FR:fr"]}}
A90: actus:local:la-depeche-tarn | B90: Tarn | C90: La Dépêche Tarn | D90: https://www.ladepeche.fr/tarn/rss.xml | E90: https://www.ladepeche.fr/tarn/ | F90: Oui | I90: {"support": "ok", "def": {"name": "La Dépêche Tarn", "color": "#d4021d", "url": "https://www.ladepeche.fr/tarn/rss.xml", "site": "https://www.ladepeche.fr/tarn/", "hint": "tarn", "alt": ["https://news.google.com/rss/search?q=site:ladepeche.fr+Tarn&hl=fr&gl=FR&ceid=FR:fr"]}}
A91: actus:local:france-3-occitanie | B91: Tarn | C91: France 3 Occitanie | D91: https://france3-regions.franceinfo.fr/occitanie/rss | F91: Oui | I91: {"support": "ok", "def": {"name": "France 3 Occitanie", "color": "#1f5ba8", "url": "https://france3-regions.franceinfo.fr/occitanie/rss"}}
A92: actus:local:la-depeche-toulouse | B92: Tarn | C92: La Dépêche Toulouse | D92: https://www.ladepeche.fr/communes/toulouse,31555/rss.xml | E92: https://www.ladepeche.fr/communes/toulouse,31555.html | G92: à vérifier | I92: {"support": "ok", "def": {"name": "La Dépêche Toulouse", "color": "#d4021d", "url": "https://www.ladepeche.fr/communes/toulouse,31555/rss.xml", "site": "https://www.ladepeche.fr/communes/toulouse,31555.html", "alt": ["https://news.google.com/rss/search?q=site:ladepeche.fr%20Toulouse&hl=fr&gl=FR&ceid=FR:fr"]}}
A93: actus:local:actu-toulouse | B93: Tarn | C93: Actu Toulouse | D93: https://actu.fr/occitanie/toulouse_31555/rss.xml | E93: https://actu.fr/toulouse/ | G93: à vérifier | I93: {"support": "ok", "def": {"name": "Actu Toulouse", "color": "#ff3d00", "url": "https://actu.fr/occitanie/toulouse_31555/rss.xml", "site": "https://actu.fr/toulouse/", "alt": ["https://news.google.com/rss/search?q=site:actu.fr&hl=fr&gl=FR&ceid=FR:fr"]}}
A94: actus:local:mazamet-castres-google | B94: Tarn | C94: Mazamet / Castres (Google) | D94: https://news.google.com/rss/search?q=Mazamet%20OR%20Castres&hl=fr&gl=FR&ceid=FR:fr | G94: à vérifier | H94: Flux Google Actualités (mot-clé) | I94: {"support": "ok", "def": {"name": "Mazamet / Castres (Google)", "color": "#6b7280", "url": "https://news.google.com/rss/search?q=Mazamet%20OR%20Castres&hl=fr&gl=FR&ceid=FR:fr"}}
A95: actus:local:albi-google | B95: Tarn | C95: Albi (Google) | D95: https://news.google.com/rss/search?q=Albi%20Tarn&hl=fr&gl=FR&ceid=FR:fr | G95: à vérifier | H95: Flux Google Actualités (mot-clé) | I95: {"support": "ok", "def": {"name": "Albi (Google)", "color": "#6b7280", "url": "https://news.google.com/rss/search?q=Albi%20Tarn&hl=fr&gl=FR&ceid=FR:fr"}}
A96: sec:actus:marches | B96: Marchés (page Investissements) | C96: ▸ toute la section | I96: {"id": "marches", "label": "Marchés", "liste": "autres"}
A97: actus:marches:les-echos-marches | B97: Marchés (page Investissements) | C97: Les Échos Marchés | D97: https://syndication.lesechos.fr/rss/rss_finance-marches.xml | E97: https://www.lesechos.fr/finance-marches | F97: Oui | I97: {"support": "ok", "def": {"name": "Les Échos Marchés", "color": "#8a1538", "url": "https://syndication.lesechos.fr/rss/rss_finance-marches.xml", "site": "https://www.lesechos.fr/finance-marches", "alt": ["https://news.google.com/rss/search?q=site:lesechos.fr/finance-marches&hl=fr&gl=FR&ceid=FR:fr"]}}
A98: actus:marches:investir | B98: Marchés (page Investissements) | C98: Investir | D98: https://investir.lesechos.fr/rss | E98: https://investir.lesechos.fr/ | F98: Oui | I98: {"support": "ok", "def": {"name": "Investir", "color": "#0f4c81", "url": "https://investir.lesechos.fr/rss", "site": "https://investir.lesechos.fr/", "alt": ["https://news.google.com/rss/search?q=site:investir.lesechos.fr&hl=fr&gl=FR&ceid=FR:fr"]}}
A99: actus:marches:boursorama | B99: Marchés (page Investissements) | C99: Boursorama | D99: https://www.boursorama.com/rss/actualites/marches | E99: https://www.boursorama.com/bourse/actualites/ | F99: Oui | I99: {"support": "ok", "def": {"name": "Boursorama", "color": "#c4006a", "url": "https://www.boursorama.com/rss/actualites/marches", "site": "https://www.boursorama.com/bourse/actualites/", "alt": ["https://news.google.com/rss/search?q=site:boursorama.com/bourse/actualites&hl=fr&gl=FR&ceid=FR:fr"]}}
A100: actus:marches:zonebourse | B100: Marchés (page Investissements) | C100: Zonebourse | D100: https://www.zonebourse.com/rss/ | E100: https://www.zonebourse.com/ | F100: Oui | I100: {"support": "ok", "def": {"name": "Zonebourse", "color": "#1f6f43", "url": "https://www.zonebourse.com/rss/", "site": "https://www.zonebourse.com/", "alt": ["https://news.google.com/rss/search?q=site:zonebourse.com&hl=fr&gl=FR&ceid=FR:fr"]}}
A101: actus:marches:amf | B101: Marchés (page Investissements) | C101: AMF | D101: https://www.amf-france.org/fr/flux-rss/display/22 | E101: https://www.amf-france.org/fr/actualites-publications | F101: Oui | I101: {"support": "ok", "def": {"name": "AMF", "color": "#1d3c78", "url": "https://www.amf-france.org/fr/flux-rss/display/22", "site": "https://www.amf-france.org/fr/actualites-publications", "alt": ["https://news.google.com/rss/search?q=site:amf-france.org&hl=fr&gl=FR&ceid=FR:fr"]}}
A102: actus:marches:boursier-com | B102: Marchés (page Investissements) | C102: Boursier.com | D102: https://www.boursier.com/rss.xml | E102: https://www.boursier.com/ | G102: à vérifier | I102: {"support": "ok", "def": {"name": "Boursier.com", "color": "#0b4f8a", "url": "https://www.boursier.com/rss.xml", "site": "https://www.boursier.com/", "alt": ["https://news.google.com/rss/search?q=site:boursier.com&hl=fr&gl=FR&ceid=FR:fr"]}}
...

Sheet Actus International
A1: module=actus-en;version=2 | B1: Actus · mode International (anglais)
B2: Mêmes rubriques, médias anglophones : affichés quand tu touches la bulle 🇺🇸 de la page Actus.
B3: À remplir : cases jaunes (« Oui » ou « Non »). Ligne « ▸ toute la section » = tous ses éléments, sauf ceux marqués « Non ». Un seul élément coché suffit pour que sa section apparaisse. Colonne « Résultat » : remplie par la tâche GitHub après dépôt du classeur.
A5: ID | B5: Section | C5: Média | D5: Adresse du flux | E5: Site (secours) | F5: Oui | G5: Résultat | H5: Note | I5: Technique
A6: sec:actus-en:une | B6: À la une | C6: ▸ toute la section | I6: {"id": "une", "label": "À la une", "liste": "principal"}
A7: actus-en:une:bbc-news | B7: À la une | C7: BBC News | D7: https://feeds.bbci.co.uk/news/rss.xml | F7: Oui | I7: {"support": "ok", "def": {"name": "BBC News", "color": "#bb1919", "url": "https://feeds.bbci.co.uk/news/rss.xml"}}
A8: actus-en:une:sky-news | B8: À la une | C8: Sky News | D8: https://feeds.skynews.com/feeds/rss/home.xml | F8: Oui | I8: {"support": "ok", "def": {"name": "Sky News", "color": "#c4122f", "url": "https://feeds.skynews.com/feeds/rss/home.xml"}}
A9: actus-en:une:euronews | B9: À la une | C9: Euronews | D9: https://www.euronews.com/rss?format=mrss&level=theme&name=news | F9: Oui | I9: {"support": "ok", "def": {"name": "Euronews", "color": "#0b3c8c", "url": "https://www.euronews.com/rss?format=mrss&level=theme&name=news"}}
A10: actus-en:une:the-guardian | B10: À la une | C10: The Guardian | D10: https://www.theguardian.com/international/rss | F10: Oui | I10: {"support": "ok", "def": {"name": "The Guardian", "color": "#052962", "url": "https://www.theguardian.com/international/rss"}}
A11: actus-en:une:new-york-times | B11: À la une | C11: New York Times | D11: https://rss.nytimes.com/services/xml/rss/nyt/HomePage.xml | F11: Oui | I11: {"support": "ok", "def": {"name": "New York Times", "color": "#2b2b2b", "url": "https://rss.nytimes.com/services/xml/rss/nyt/HomePage.xml"}}
A12: actus-en:une:wall-street-journal | B12: À la une | C12: Wall Street Journal | D12: https://feeds.content.dowjones.io/public/rss/RSSWorldNews | F12: Oui | I12: {"support": "ok", "def": {"name": "Wall Street Journal", "color": "#0274b6", "url": "https://feeds.content.dowjones.io/public/rss/RSSWorldNews", "alt": ["https://news.google.com/rss/search?q=site:wsj.com&hl=en-US&gl=US&ceid=US:en"]}}
A13: actus-en:une:npr | B13: À la une | C13: NPR | D13: https://feeds.npr.org/1001/rss.xml | E13: https://www.npr.org/ | G13: à vérifier | I13: {"support": "ok", "def": {"name": "NPR", "color": "#2b2b2b", "url": "https://feeds.npr.org/1001/rss.xml", "site": "https://www.npr.org/", "alt": ["https://news.google.com/rss/search?q=site:npr.org&hl=en-US&gl=US&ceid=US:en"]}}
A14: actus-en:une:reuters-google | B14: À la une | C14: Reuters (Google) | D14: https://news.google.com/rss/search?q=site:reuters.com&hl=en-US&gl=US&ceid=US:en | G14: à vérifier | H14: Flux Google Actualités (mot-clé) | I14: {"support": "ok", "def": {"name": "Reuters (Google)", "color": "#ff8000", "url": "https://news.google.com/rss/search?q=site:reuters.com&hl=en-US&gl=US&ceid=US:en"}}
A15: actus-en:une:associated-press-google | B15: À la une | C15: Associated Press (Google) | D15: https://news.google.com/rss/search?q=site:apnews.com&hl=en-US&gl=US&ceid=US:en | G15: à vérifier | H15: Flux Google Actualités (mot-clé) | I15: {"support": "ok", "def": {"name": "Associated Press (Google)", "color": "#e2001a", "url": "https://news.google.com/rss/search?q=site:apnews.com&hl=en-US&gl=US&ceid=US:en"}}
A16: actus-en:une:cnn | B16: À la une | C16: CNN | D16: http://rss.cnn.com/rss/edition.rss | E16: https://edition.cnn.com/ | G16: à vérifier | I16: {"support": "ok", "def": {"name": "CNN", "color": "#cc0000", "url": "http://rss.cnn.com/rss/edition.rss", "site": "https://edition.cnn.com/", "alt": ["https://news.google.com/rss/search?q=site:edition.cnn.com&hl=en-US&gl=US&ceid=US:en"]}}
A17: actus-en:une:washington-post | B17: À la une | C17: Washington Post | D17: https://feeds.washingtonpost.com/rss/world | E17: https://www.washingtonpost.com/ | G17: à vérifier | I17: {"support": "ok", "def": {"name": "Washington Post", "color": "#111111", "url": "https://feeds.washingtonpost.com/rss/world", "site": "https://www.washingtonpost.com/", "alt": ["https://news.google.com/rss/search?q=site:washingtonpost.com&hl=en-US&gl=US&ceid=US:en"]}}
A18: actus-en:une:the-independent | B18: À la une | C18: The Independent | D18: https://www.independent.co.uk/news/rss | E18: https://www.independent.co.uk/ | G18: à vérifier | I18: {"support": "ok", "def": {"name": "The Independent", "color": "#e2001a", "url": "https://www.independent.co.uk/news/rss", "site": "https://www.independent.co.uk/", "alt": ["https://news.google.com/rss/search?q=site:independent.co.uk&hl=en-US&gl=US&ceid=US:en"]}}
A19: sec:actus-en:france | B19: France | C19: ▸ toute la section | I19: {"id": "france", "label": "France", "liste": "principal"}
A20: actus-en:france:france-24 | B20: France | C20: France 24 | D20: https://www.france24.com/en/france/rss | F20: Oui | I20: {"support": "ok", "def": {"name": "France 24", "color": "#00a3e0", "url": "https://www.france24.com/en/france/rss"}}
A21: actus-en:france:rfi | B21: France | C21: RFI | D21: https://www.rfi.fr/en/france/rss | F21: Oui | I21: {"support": "ok", "def": {"name": "RFI", "color": "#e5004d", "url": "https://www.rfi.fr/en/france/rss", "alt": ["https://news.google.com/rss/search?q=site:rfi.fr/en&hl=en-US&gl=US&ceid=US:en"]}}
A22: actus-en:france:the-local | B22: France | C22: The Local | D22: https://www.thelocal.fr/feeds/rss.php | E22: https://www.thelocal.fr/ | F22: Oui | I22: {"support": "ok", "def": {"name": "The Local", "color": "#e2001a", "url": "https://www.thelocal.fr/feeds/rss.php", "site": "https://www.thelocal.fr/", "alt": ["https://news.google.com/rss/search?q=site:thelocal.fr&hl=en-US&gl=US&ceid=US:en"]}}
A23: sec:actus-en:monde | B23: Monde | C23: ▸ toute la section | I23: {"id": "monde", "label": "Monde", "liste": "principal"}
A24: actus-en:monde:bbc-news | B24: Monde | C24: BBC News | D24: https://feeds.bbci.co.uk/news/world/rss.xml | F24: Oui | I24: {"support": "ok", "def": {"name": "BBC News", "color": "#bb1919", "url": "https://feeds.bbci.co.uk/news/world/rss.xml"}}
A25: actus-en:monde:the-guardian | B25: Monde | C25: The Guardian | D25: https://www.theguardian.com/world/rss | F25: Oui | I25: {"support": "ok", "def": {"name": "The Guardian", "color": "#052962", "url": "https://www.theguardian.com/world/rss"}}
A26: actus-en:monde:new-york-times | B26: Monde | C26: New York Times | D26: https://rss.nytimes.com/services/xml/rss/nyt/World.xml | F26: Oui | I26: {"support": "ok", "def": {"name": "New York Times", "color": "#2b2b2b", "url": "https://rss.nytimes.com/services/xml/rss/nyt/World.xml"}}
A27: actus-en:monde:sky-news | B27: Monde | C27: Sky News | D27: https://feeds.skynews.com/feeds/rss/world.xml | F27: Oui | I27: {"support": "ok", "def": {"name": "Sky News", "color": "#c4122f", "url": "https://feeds.skynews.com/feeds/rss/world.xml"}}
A28: actus-en:monde:wall-street-journal | B28: Monde | C28: Wall Street Journal | D28: https://feeds.content.dowjones.io/public/rss/RSSWorldNews | F28: Oui | I28: {"support": "ok", "def": {"name": "Wall Street Journal", "color": "#0274b6", "url": "https://feeds.content.dowjones.io/public/rss/RSSWorldNews"}}
A29: actus-en:monde:al-jazeera | B29: Monde | C29: Al Jazeera | D29: https://www.aljazeera.com/xml/rss/all.xml | F29: Oui | I29: {"support": "ok", "def": {"name": "Al Jazeera", "color": "#d39c1f", "url": "https://www.aljazeera.com/xml/rss/all.xml"}}
A30: actus-en:monde:deutsche-welle | B30: Monde | C30: Deutsche Welle | D30: https://rss.dw.com/rdf/rss-en-all | E30: https://www.dw.com/en/ | G30: à vérifier | I30: {"support": "ok", "def": {"name": "Deutsche Welle", "color": "#0c4da2", "url": "https://rss.dw.com/rdf/rss-en-all", "site": "https://www.dw.com/en/", "alt": ["https://news.google.com/rss/search?q=site:dw.com&hl=en-US&gl=US&ceid=US:en"]}}
A31: actus-en:monde:politico-europe | B31: Monde | C31: Politico Europe | D31: https://www.politico.eu/feed/ | E31: https://www.politico.eu/ | G31: à vérifier | I31: {"support": "ok", "def": {"name": "Politico Europe", "color": "#d6001c", "url": "https://www.politico.eu/feed/", "site": "https://www.politico.eu/", "alt": ["https://news.google.com/rss/search?q=site:politico.eu&hl=en-US&gl=US&ceid=US:en"]}}
A32: actus-en:monde:foreign-policy | B32: Monde | C32: Foreign Policy | D32: https://foreignpolicy.com/feed/ | E32: https://foreignpolicy.com/ | G32: à vérifier | I32: {"support": "ok", "def": {"name": "Foreign Policy", "color": "#111111", "url": "https://foreignpolicy.com/feed/", "site": "https://foreignpolicy.com/", "alt": ["https://news.google.com/rss/search?q=site:foreignpolicy.com&hl=en-US&gl=US&ceid=US:en"]}}
A33: actus-en:monde:the-atlantic | B33: Monde | C33: The Atlantic | D33: https://www.theatlantic.com/feed/all/ | E33: https://www.theatlantic.com/ | G33: à vérifier | I33: {"support": "ok", "def": {"name": "The Atlantic", "color": "#111111", "url": "https://www.theatlantic.com/feed/all/", "site": "https://www.theatlantic.com/", "alt": ["https://news.google.com/rss/search?q=site:theatlantic.com&hl=en-US&gl=US&ceid=US:en"]}}
A34: sec:actus-en:eco | B34: Éco | C34: ▸ toute la section | I34: {"id": "eco", "label": "Éco", "liste": "principal"}
A35: actus-en:eco:financial-times | B35: Éco | C35: Financial Times | D35: https://www.ft.com/rss/home | F35: Oui | I35: {"support": "ok", "def": {"name": "Financial Times", "color": "#990f3d", "url": "https://www.ft.com/rss/home", "alt": ["https://news.google.com/rss/search?q=site:ft.com&hl=en-US&gl=US&ceid=US:en"]}}
A36: actus-en:eco:the-economist | B36: Éco | C36: The Economist | D36: https://www.economist.com/finance-and-economics/rss.xml | F36: Oui | I36: {"support": "ok", "def": {"name": "The Economist", "color": "#e3120b", "url": "https://www.economist.com/finance-and-economics/rss.xml", "alt": ["https://news.google.com/rss/search?q=site:economist.com&hl=en-US&gl=US&ceid=US:en"]}}
A37: actus-en:eco:wall-street-journal | B37: Éco | C37: Wall Street Journal | D37: https://feeds.content.dowjones.io/public/rss/RSSMarketsMain | F37: Oui | I37: {"support": "ok", "def": {"name": "Wall Street Journal", "color": "#0274b6", "url": "https://feeds.content.dowjones.io/public/rss/RSSMarketsMain", "alt": ["https://news.google.com/rss/search?q=site:wsj.com&hl=en-US&gl=US&ceid=US:en"]}}
A38: actus-en:eco:bbc-news | B38: Éco | C38: BBC News | D38: https://feeds.bbci.co.uk/news/business/rss.xml | F38: Oui | I38: {"support": "ok", "def": {"name": "BBC News", "color": "#bb1919", "url": "https://feeds.bbci.co.uk/news/business/rss.xml"}}
A39: actus-en:eco:cnbc | B39: Éco | C39: CNBC | D39: https://www.cnbc.com/id/100003114/device/rss/rss.html | E39: https://www.cnbc.com/ | G39: à vérifier | I39: {"support": "ok", "def": {"name": "CNBC", "color": "#005594", "url": "https://www.cnbc.com/id/100003114/device/rss/rss.html", "site": "https://www.cnbc.com/", "alt": ["https://news.google.com/rss/search?q=site:cnbc.com&hl=en-US&gl=US&ceid=US:en"]}}
A40: actus-en:eco:bloomberg-google | B40: Éco | C40: Bloomberg (Google) | D40: https://news.google.com/rss/search?q=site:bloomberg.com&hl=en-US&gl=US&ceid=US:en | G40: à vérifier | H40: Flux Google Actualités (mot-clé) | I40: {"support": "ok", "def": {"name": "Bloomberg (Google)", "color": "#111111", "url": "https://news.google.com/rss/search?q=site:bloomberg.com&hl=en-US&gl=US&ceid=US:en"}}
A41: actus-en:eco:marketwatch | B41: Éco | C41: MarketWatch | D41: https://feeds.content.dowjones.io/public/rss/mw_topstories | E41: https://www.marketwatch.com/ | G41: à vérifier | I41: {"support": "ok", "def": {"name": "MarketWatch", "color": "#0a7a3b", "url": "https://feeds.content.dowjones.io/public/rss/mw_topstories", "site": "https://www.marketwatch.com/", "alt": ["https://news.google.com/rss/search?q=site:marketwatch.com&hl=en-US&gl=US&ceid=US:en"]}}
A42: sec:actus-en:sport | B42: Sport | C42: ▸ toute la section | I42: {"id": "sport", "label": "Sport", "liste": "principal"}
A43: actus-en:sport:bbc-sport | B43: Sport | C43: BBC Sport | D43: https://feeds.bbci.co.uk/sport/rss.xml | F43: Oui | I43: {"support": "ok", "def": {"name": "BBC Sport", "color": "#e8b400", "url": "https://feeds.bbci.co.uk/sport/rss.xml"}}
A44: actus-en:sport:the-guardian | B44: Sport | C44: The Guardian | D44: https://www.theguardian.com/uk/sport/rss | F44: Oui | I44: {"support": "ok", "def": {"name": "The Guardian", "color": "#052962", "url": "https://www.theguardian.com/uk/sport/rss"}}
A45: actus-en:sport:sky-sports | B45: Sport | C45: Sky Sports | D45: https://www.skysports.com/rss/12040 | F45: Oui | I45: {"support": "ok", "def": {"name": "Sky Sports", "color": "#d0021b", "url": "https://www.skysports.com/rss/12040"}}
A46: actus-en:sport:espn | B46: Sport | C46: ESPN | D46: https://www.espn.com/espn/rss/news | E46: https://www.espn.com/ | G46: à vérifier | I46: {"support": "ok", "def": {"name": "ESPN", "color": "#d00", "url": "https://www.espn.com/espn/rss/news", "site": "https://www.espn.com/", "alt": ["https://news.google.com/rss/search?q=site:espn.com&hl=en-US&gl=US&ceid=US:en"]}}
A47: actus-en:sport:bbc-sport-football | B47: Sport | C47: BBC Sport · Football | D47: https://feeds.bbci.co.uk/sport/football/rss.xml | G47: à vérifier | I47: {"support": "ok", "def": {"name": "BBC Sport · Football", "color": "#e8b400", "url": "https://feeds.bbci.co.uk/sport/football/rss.xml", "alt": ["https://news.google.com/rss/search?q=site:feeds.bbci.co.uk&hl=en-US&gl=US&ceid=US:en"]}}
A48: actus-en:sport:bbc-sport-rugby | B48: Sport | C48: BBC Sport · Rugby | D48: https://feeds.bbci.co.uk/sport/rugby-union/rss.xml | G48: à vérifier | I48: {"support": "ok", "def": {"name": "BBC Sport · Rugby", "color": "#e8b400", "url": "https://feeds.bbci.co.uk/sport/rugby-union/rss.xml", "alt": ["https://news.google.com/rss/search?q=site:feeds.bbci.co.uk&hl=en-US&gl=US&ceid=US:en"]}}
A49: actus-en:sport:the-athletic-google | B49: Sport | C49: The Athletic (Google) | D49: https://news.google.com/rss/search?q=site:nytimes.com/athletic&hl=en-US&gl=US&ceid=US:en | G49: à vérifier | H49: Flux Google Actualités (mot-clé) | I49: {"support": "ok", "def": {"name": "The Athletic (Google)", "color": "#111111", "url": "https://news.google.com/rss/search?q=site:nytimes.com/athletic&hl=en-US&gl=US&ceid=US:en"}}
A50: sec:actus-en:tech | B50: Tech | C50: ▸ toute la section | I50: {"id": "tech", "label": "Tech", "liste": "principal"}
A51: actus-en:tech:the-verge | B51: Tech | C51: The Verge | D51: https://www.theverge.com/rss/index.xml | F51: Oui | I51: {"support": "ok", "def": {"name": "The Verge", "color": "#5200ff", "url": "https://www.theverge.com/rss/index.xml"}}
A52: actus-en:tech:ars-technica | B52: Tech | C52: Ars Technica | D52: https://feeds.arstechnica.com/arstechnica/index | F52: Oui | I52: {"support": "ok", "def": {"name": "Ars Technica", "color": "#ff4e00", "url": "https://feeds.arstechnica.com/arstechnica/index"}}
A53: actus-en:tech:bbc-news | B53: Tech | C53: BBC News | D53: https://feeds.bbci.co.uk/news/technology/rss.xml | F53: Oui | I53: {"support": "ok", "def": {"name": "BBC News", "color": "#bb1919", "url": "https://feeds.bbci.co.uk/news/technology/rss.xml"}}
A54: actus-en:tech:techcrunch | B54: Tech | C54: TechCrunch | D54: https://techcrunch.com/feed/ | E54: https://techcrunch.com/ | G54: à vérifier | I54: {"support": "ok", "def": {"name": "TechCrunch", "color": "#0a9e01", "url": "https://techcrunch.com/feed/", "site": "https://techcrunch.com/", "alt": ["https://news.google.com/rss/search?q=site:techcrunch.com&hl=en-US&gl=US&ceid=US:en"]}}
A55: actus-en:tech:wired | B55: Tech | C55: Wired | D55: https://www.wired.com/feed/rss | E55: https://www.wired.com/ | G55: à vérifier | I55: {"support": "ok", "def": {"name": "Wired", "color": "#111111", "url": "https://www.wired.com/feed/rss", "site": "https://www.wired.com/", "alt": ["https://news.google.com/rss/search?q=site:wired.com&hl=en-US&gl=US&ceid=US:en"]}}
A56: actus-en:tech:engadget | B56: Tech | C56: Engadget | D56: https://www.engadget.com/rss.xml | E56: https://www.engadget.com/ | G56: à vérifier | I56: {"support": "ok", "def": {"name": "Engadget", "color": "#7b2bf9", "url": "https://www.engadget.com/rss.xml", "site": "https://www.engadget.com/", "alt": ["https://news.google.com/rss/search?q=site:engadget.com&hl=en-US&gl=US&ceid=US:en"]}}
A57: actus-en:tech:mit-technology-review | B57: Tech | C57: MIT Technology Review | D57: https://www.technologyreview.com/feed/ | E57: https://www.technologyreview.com/ | G57: à vérifier | I57: {"support": "ok", "def": {"name": "MIT Technology Review", "color": "#111111", "url": "https://www.technologyreview.com/feed/", "site": "https://www.technologyreview.com/", "alt": ["https://news.google.com/rss/search?q=site:technologyreview.com&hl=en-US&gl=US&ceid=US:en"]}}
A58: actus-en:tech:hacker-news | B58: Tech | C58: Hacker News | D58: https://hnrss.org/frontpage | E58: https://news.ycombinator.com/ | G58: à vérifier | I58: {"support": "ok", "def": {"name": "Hacker News", "color": "#ff6600", "url": "https://hnrss.org/frontpage", "site": "https://news.ycombinator.com/"}}
A59: actus-en:tech:9to5mac | B59: Tech | C59: 9to5Mac | D59: https://9to5mac.com/feed/ | E59: https://9to5mac.com/ | G59: à vérifier | I59: {"support": "ok", "def": {"name": "9to5Mac", "color": "#1f6feb", "url": "https://9to5mac.com/feed/", "site": "https://9to5mac.com/", "alt": ["https://news.google.com/rss/search?q=site:9to5mac.com&hl=en-US&gl=US&ceid=US:en"]}}
A60: sec:actus-en:sciences | B60: Sciences | C60: ▸ toute la section | I60: {"id": "sciences", "label": "Sciences", "liste": "principal"}
A61: actus-en:sciences:nature-news | B61: Sciences | C61: Nature News | D61: https://www.nature.com/nature.rss | E61: https://www.nature.com/ | G61: à vérifier | I61: {"support": "ok", "def": {"name": "Nature News", "color": "#c00", "url": "https://www.nature.com/nature.rss", "site": "https://www.nature.com/", "alt": ["https://news.google.com/rss/search?q=site:nature.com&hl=en-US&gl=US&ceid=US:en"]}}
A62: actus-en:sciences:new-scientist | B62: Sciences | C62: New Scientist | D62: https://www.newscientist.com/feed/home/ | E62: https://www.newscientist.com/ | G62: à vérifier | I62: {"support": "ok", "def": {"name": "New Scientist", "color": "#d6001c", "url": "https://www.newscientist.com/feed/home/", "site": "https://www.newscientist.com/", "alt": ["https://news.google.com/rss/search?q=site:newscientist.com&hl=en-US&gl=US&ceid=US:en"]}}
A63: actus-en:sciences:sciencedaily | B63: Sciences | C63: ScienceDaily | D63: https://www.sciencedaily.com/rss/all.xml | E63: https://www.sciencedaily.com/ | G63: à vérifier | I63: {"support": "ok", "def": {"name": "ScienceDaily", "color": "#1f4e79", "url": "https://www.sciencedaily.com/rss/all.xml", "site": "https://www.sciencedaily.com/", "alt": ["https://news.google.com/rss/search?q=site:sciencedaily.com&hl=en-US&gl=US&ceid=US:en"]}}
A64: actus-en:sciences:quanta-magazine | B64: Sciences | C64: Quanta Magazine | D64: https://www.quantamagazine.org/feed/ | E64: https://www.quantamagazine.org/ | G64: à vérifier | I64: {"support": "ok", "def": {"name": "Quanta Magazine", "color": "#111111", "url": "https://www.quantamagazine.org/feed/", "site": "https://www.quantamagazine.org/", "alt": ["https://news.google.com/rss/search?q=site:quantamagazine.org&hl=en-US&gl=US&ceid=US:en"]}}
A65: actus-en:sciences:ars-technica-science | B65: Sciences | C65: Ars Technica Science | D65: https://feeds.arstechnica.com/arstechnica/science | G65: à vérifier | I65: {"support": "ok", "def": {"name": "Ars Technica Science", "color": "#ff4e00", "url": "https://feeds.arstechnica.com/arstechnica/science", "alt": ["https://news.google.com/rss/search?q=site:feeds.arstechnica.com&hl=en-US&gl=US&ceid=US:en"]}}
A66: sec:actus-en:espace | B66: Astronomie et espace | C66: ▸ toute la section | I66: {"id": "espace", "label": "Astronomie et espace", "liste": "principal"}
A67: actus-en:espace:nasa | B67: Astronomie et espace | C67: NASA | D67: https://www.nasa.gov/news-release/feed/ | E67: https://www.nasa.gov/ | G67: à vérifier | I67: {"support": "ok", "def": {"name": "NASA", "color": "#0b3d91", "url": "https://www.nasa.gov/news-release/feed/", "site": "https://www.nasa.gov/", "alt": ["https://news.google.com/rss/search?q=site:nasa.gov&hl=en-US&gl=US&ceid=US:en"]}}
A68: actus-en:espace:space-com | B68: Astronomie et espace | C68: Space.com | D68: https://www.space.com/feeds/all | E68: https://www.space.com/ | G68: à vérifier | I68: {"support": "ok", "def": {"name": "Space.com", "color": "#111111", "url": "https://www.space.com/feeds/all", "site": "https://www.space.com/", "alt": ["https://news.google.com/rss/search?q=site:space.com&hl=en-US&gl=US&ceid=US:en"]}}
A69: actus-en:espace:esa | B69: Astronomie et espace | C69: ESA | D69: https://www.esa.int/rssfeed/Our_Activities/Space_Science | E69: https://www.esa.int/ | G69: à vérifier | I69: {"support": "ok", "def": {"name": "ESA", "color": "#003247", "url": "https://www.esa.int/rssfeed/Our_Activities/Space_Science", "site": "https://www.esa.int/", "alt": ["https://news.google.com/rss/search?q=site:esa.int&hl=en-US&gl=US&ceid=US:en"]}}
A70: actus-en:espace:spacenews | B70: Astronomie et espace | C70: SpaceNews | D70: https://spacenews.com/feed/ | E70: https://spacenews.com/ | G70: à vérifier | I70: {"support": "ok", "def": {"name": "SpaceNews", "color": "#0f172a", "url": "https://spacenews.com/feed/", "site": "https://spacenews.com/", "alt": ["https://news.google.com/rss/search?q=site:spacenews.com&hl=en-US&gl=US&ceid=US:en"]}}
A71: actus-en:espace:universe-today | B71: Astronomie et espace | C71: Universe Today | D71: https://www.universetoday.com/feed/ | E71: https://www.universetoday.com/ | G71: à vérifier | I71: {"support": "ok", "def": {"name": "Universe Today", "color": "#1e3a8a", "url": "https://www.universetoday.com/feed/", "site": "https://www.universetoday.com/", "alt": ["https://news.google.com/rss/search?q=site:universetoday.com&hl=en-US&gl=US&ceid=US:en"]}}
A72: actus-en:espace:sky-telescope | B72: Astronomie et espace | C72: Sky & Telescope | D72: https://skyandtelescope.org/feed/ | E72: https://skyandtelescope.org/ | G72: à vérifier | I72: {"support": "ok", "def": {"name": "Sky & Telescope", "color": "#0b1e3f", "url": "https://skyandtelescope.org/feed/", "site": "https://skyandtelescope.org/", "alt": ["https://news.google.com/rss/search?q=site:skyandtelescope.org&hl=en-US&gl=US&ceid=US:en"]}}
A73: sec:actus-en:jeux | B73: Jeux vidéo | C73: ▸ toute la section | I73: {"id": "jeux", "label": "Jeux vidéo", "liste": "principal"}
A74: actus-en:jeux:ign | B74: Jeux vidéo | C74: IGN | D74: https://feeds.feedburner.com/ign/all | E74: https://www.ign.com/ | G74: à vérifier | I74: {"support": "ok", "def": {"name": "IGN", "color": "#bf1313", "url": "https://feeds.feedburner.com/ign/all", "site": "https://www.ign.com/", "alt": ["https://news.google.com/rss/search?q=site:ign.com&hl=en-US&gl=US&ceid=US:en"]}}
A75: actus-en:jeux:eurogamer | B75: Jeux vidéo | C75: Eurogamer | D75: https://www.eurogamer.net/feed | E75: https://www.eurogamer.net/ | G75: à vérifier | I75: {"support": "ok", "def": {"name": "Eurogamer", "color": "#1f6feb", "url": "https://www.eurogamer.net/feed", "site": "https://www.eurogamer.net/", "alt": ["https://news.google.com/rss/search?q=site:eurogamer.net&hl=en-US&gl=US&ceid=US:en"]}}
A76: actus-en:jeux:polygon | B76: Jeux vidéo | C76: Polygon | D76: https://www.polygon.com/rss/index.xml | E76: https://www.polygon.com/ | G76: à vérifier | I76: {"support": "ok", "def": {"name": "Polygon", "color": "#ff0090", "url": "https://www.polygon.com/rss/index.xml", "site": "https://www.polygon.com/", "alt": ["https://news.google.com/rss/search?q=site:polygon.com&hl=en-US&gl=US&ceid=US:en"]}}
A77: actus-en:jeux:pc-gamer | B77: Jeux vidéo | C77: PC Gamer | D77: https://www.pcgamer.com/rss/ | E77: https://www.pcgamer.com/ | G77: à vérifier | I77: {"support": "ok", "def": {"name": "PC Gamer", "color": "#c8102e", "url": "https://www.pcgamer.com/rss/", "site": "https://www.pcgamer.com/", "alt": ["https://news.google.com/rss/search?q=site:pcgamer.com&hl=en-US&gl=US&ceid=US:en"]}}
A78: actus-en:jeux:kotaku | B78: Jeux vidéo | C78: Kotaku | D78: https://kotaku.com/rss | E78: https://kotaku.com/ | G78: à vérifier | I78: {"support": "ok", "def": {"name": "Kotaku", "color": "#111111", "url": "https://kotaku.com/rss", "site": "https://kotaku.com/", "alt": ["https://news.google.com/rss/search?q=site:kotaku.com&hl=en-US&gl=US&ceid=US:en"]}}
A79: actus-en:jeux:rock-paper-shotgun | B79: Jeux vidéo | C79: Rock Paper Shotgun | D79: https://www.rockpapershotgun.com/feed | E79: https://www.rockpapershotgun.com/ | G79: à vérifier | I79: {"support": "ok", "def": {"name": "Rock Paper Shotgun", "color": "#c8102e", "url": "https://www.rockpapershotgun.com/feed", "site": "https://www.rockpapershotgun.com/", "alt": ["https://news.google.com/rss/search?q=site:rockpapershotgun.com&hl=en-US&gl=US&ceid=US:en"]}}
A80: sec:actus-en:defense | B80: Défense et conflits | C80: ▸ toute la section | I80: {"id": "defense", "label": "Défense et conflits", "liste": "principal"}
A81: actus-en:defense:defense-news | B81: Défense et conflits | C81: Defense News | D81: https://www.defensenews.com/arc/outboundfeeds/rss/ | E81: https://www.defensenews.com/ | G81: à vérifier | I81: {"support": "ok", "def": {"name": "Defense News", "color": "#0f172a", "url": "https://www.defensenews.com/arc/outboundfeeds/rss/", "site": "https://www.defensenews.com/", "alt": ["https://news.google.com/rss/search?q=site:defensenews.com&hl=en-US&gl=US&ceid=US:en"]}}
A82: actus-en:defense:breaking-defense | B82: Défense et conflits | C82: Breaking Defense | D82: https://breakingdefense.com/feed/ | E82: https://breakingdefense.com/ | G82: à vérifier | I82: {"support": "ok", "def": {"name": "Breaking Defense", "color": "#c8102e", "url": "https://breakingdefense.com/feed/", "site": "https://breakingdefense.com/", "alt": ["https://news.google.com/rss/search?q=site:breakingdefense.com&hl=en-US&gl=US&ceid=US:en"]}}
A83: actus-en:defense:the-war-zone | B83: Défense et conflits | C83: The War Zone | D83: https://www.twz.com/feed | E83: https://www.twz.com/ | G83: à vérifier | I83: {"support": "ok", "def": {"name": "The War Zone", "color": "#111111", "url": "https://www.twz.com/feed", "site": "https://www.twz.com/", "alt": ["https://news.google.com/rss/search?q=site:twz.com&hl=en-US&gl=US&ceid=US:en"]}}
A84: actus-en:defense:war-on-the-rocks | B84: Défense et conflits | C84: War on the Rocks | D84: https://warontherocks.com/feed/ | E84: https://warontherocks.com/ | G84: à vérifier | I84: {"support": "ok", "def": {"name": "War on the Rocks", "color": "#7f1d1d", "url": "https://warontherocks.com/feed/", "site": "https://warontherocks.com/", "alt": ["https://news.google.com/rss/search?q=site:warontherocks.com&hl=en-US&gl=US&ceid=US:en"]}}
A85: actus-en:defense:institute-for-the-study-of-war | B85: Défense et conflits | C85: Institute for the Study of War | D85: https://www.understandingwar.org/rss.xml | E85: https://www.understandingwar.org/ | G85: à vérifier | I85: {"support": "ok", "def": {"name": "Institute for the Study of War", "color": "#1e3a8a", "url": "https://www.understandingwar.org/rss.xml", "site": "https://www.understandingwar.org/", "alt": ["https://news.google.com/rss/search?q=site:understandingwar.org&hl=en-US&gl=US&ceid=US:en"]}}
A86: actus-en:defense:kyiv-independent | B86: Défense et conflits | C86: Kyiv Independent | D86: https://kyivindependent.com/news-archive/rss/ | E86: https://kyivindependent.com/ | G86: à vérifier | I86: {"support": "ok", "def": {"name": "Kyiv Independent", "color": "#0057b7", "url": "https://kyivindependent.com/news-archive/rss/", "site": "https://kyivindependent.com/", "alt": ["https://news.google.com/rss/search?q=site:kyivindependent.com&hl=en-US&gl=US&ceid=US:en"]}}
A87: sec:actus-en:ia | B87: Intelligence artificielle | C87: ▸ toute la section | I87: {"id": "ia", "label": "Intelligence artificielle", "liste": "principal"}
A88: actus-en:ia:the-verge-ai | B88: Intelligence artificielle | C88: The Verge AI | D88: https://www.theverge.com/rss/ai-artificial-intelligence/index.xml | G88: à vérifier | I88: {"support": "ok", "def": {"name": "The Verge AI", "color": "#5200ff", "url": "https://www.theverge.com/rss/ai-artificial-intelligence/index.xml", "alt": ["https://news.google.com/rss/search?q=site:theverge.com&hl=en-US&gl=US&ceid=US:en"]}}
A89: actus-en:ia:venturebeat-ai | B89: Intelligence artificielle | C89: VentureBeat AI | D89: https://venturebeat.com/category/ai/feed/ | E89: https://venturebeat.com/ai/ | G89: à vérifier | I89: {"support": "ok", "def": {"name": "VentureBeat AI", "color": "#ed1c24", "url": "https://venturebeat.com/category/ai/feed/", "site": "https://venturebeat.com/ai/", "alt": ["https://news.google.com/rss/search?q=site:venturebeat.com&hl=en-US&gl=US&ceid=US:en"]}}
A90: actus-en:ia:mit-news-ai | B90: Intelligence artificielle | C90: MIT News AI | D90: https://news.mit.edu/rss/topic/artificial-intelligence2 | E90: https://news.mit.edu/ | G90: à vérifier | I90: {"support": "ok", "def": {"name": "MIT News AI", "color": "#a31f34", "url": "https://news.mit.edu/rss/topic/artificial-intelligence2", "site": "https://news.mit.edu/", "alt": ["https://news.google.com/rss/search?q=site:news.mit.edu&hl=en-US&gl=US&ceid=US:en"]}}
A91: sec:actus-en:planete | B91: Environnement et climat | C91: ▸ toute la section | I91: {"id": "planete", "label": "Environnement et climat", "liste": "principal"}
A92: actus-en:planete:the-guardian-environment | B92: Environnement et climat | C92: The Guardian Environment | D92: https://www.theguardian.com/environment/rss | G92: à vérifier | I92: {"support": "ok", "def": {"name": "The Guardian Environment", "color": "#052962", "url": "https://www.theguardian.com/environment/rss", "alt": ["https://news.google.com/rss/search?q=site:theguardian.com&hl=en-US&gl=US&ceid=US:en"]}}
A93: actus-en:planete:carbon-brief | B93: Environnement et climat | C93: Carbon Brief | D93: https://www.carbonbrief.org/feed/ | E93: https://www.carbonbrief.org/ | G93: à vérifier | I93: {"support": "ok", "def": {"name": "Carbon Brief", "color": "#0f766e", "url": "https://www.carbonbrief.org/feed/", "site": "https://www.carbonbrief.org/", "alt": ["https://news.google.com/rss/search?q=site:carbonbrief.org&hl=en-US&gl=US&ceid=US:en"]}}
A94: actus-en:planete:inside-climate-news | B94: Environnement et climat | C94: Inside Climate News | D94: https://insideclimatenews.org/feed/ | E94: https://insideclimatenews.org/ | G94: à vérifier | I94: {"support": "ok", "def": {"name": "Inside Climate News", "color": "#065f46", "url": "https://insideclimatenews.org/feed/", "site": "https://insideclimatenews.org/", "alt": ["https://news.google.com/rss/search?q=site:insideclimatenews.org&hl=en-US&gl=US&ceid=US:en"]}}
A95: sec:actus-en:sante | B95: Santé | C95: ▸ toute la section | I95: {"id": "sante", "label": "Santé", "liste": "principal"}
A96: actus-en:sante:bbc-health | B96: Santé | C96: BBC Health | D96: https://feeds.bbci.co.uk/news/health/rss.xml | G96: à vérifier | I96: {"support": "ok", "def": {"name": "BBC Health", "color": "#bb1919", "url": "https://feeds.bbci.co.uk/news/health/rss.xml", "alt": ["https://news.google.com/rss/search?q=site:feeds.bbci.co.uk&hl=en-US&gl=US&ceid=US:en"]}}
A97: actus-en:sante:stat | B97: Santé | C97: STAT | D97: https://www.statnews.com/feed/ | E97: https://www.statnews.com/ | G97: à vérifier | I97: {"support": "ok", "def": {"name": "STAT", "color": "#e11d48", "url": "https://www.statnews.com/feed/", "site": "https://www.statnews.com/", "alt": ["https://news.google.com/rss/search?q=site:statnews.com&hl=en-US&gl=US&ceid=US:en"]}}
A98: sec:actus-en:cine | B98: Cinéma et séries | C98: ▸ toute la section | I98: {"id": "cine", "label": "Cinéma et séries", "liste": "principal"}
A99: actus-en:cine:variety | B99: Cinéma et séries | C99: Variety | D99: https://variety.com/feed/ | E99: https://variety.com/ | G99: à vérifier | I99: {"support": "ok", "def": {"name": "Variety", "color": "#111111", "url": "https://variety.com/feed/", "site": "https://variety.com/", "alt": ["https://news.google.com/rss/search?q=site:variety.com&hl=en-US&gl=US&ceid=US:en"]}}
A100: actus-en:cine:deadline | B100: Cinéma et séries | C100: Deadline | D100: https://deadline.com/feed/ | E100: https://deadline.com/ | G100: à vérifier | I100: {"support": "ok", "def": {"name": "Deadline", "color": "#111111", "url": "https://deadline.com/feed/", "site": "https://deadline.com/", "alt": ["https://news.google.com/rss/search?q=site:deadline.com&hl=en-US&gl=US&ceid=US:en"]}}
A101: actus-en:cine:the-hollywood-reporter | B101: Cinéma et séries | C101: The Hollywood Reporter | D101: https://www.hollywoodreporter.com/feed/ | E101: https://www.hollywoodreporter.com/ | G101: à vérifier | I101: {"support": "ok", "def": {"name": "The Hollywood Reporter", "color": "#111111", "url": "https://www.hollywoodreporter.com/feed/", "site": "https://www.hollywoodreporter.com/", "alt": ["https://news.google.com/rss/search?q=site:hollywoodreporter.com&hl=en-US&gl=US&ceid=US:en"]}}
...

Sheet Marchés
A1: module=marches;version=2 | B1: Investissements · marchés et fonds suivis
B2: Indices, devises, matières premières, taux, cryptos et fonds affichés dans la page Investissements. « Widget accueil » : affiché aussi sur l'écran d'accueil. Pour tes fonds, l'ISIN suffit (jamais de quantités ni de montants ici : le dépôt est public).
B3: À remplir : cases jaunes (« Oui » ou « Non »). Ligne « ▸ toute la section » = tous ses éléments, sauf ceux marqués « Non ». Un seul élément coché suffit pour que sa section apparaisse. Colonne « Résultat » : remplie par la tâche GitHub après dépôt du classeur.
A5: ID | B5: Section | C5: Nom | D5: Code de cotation | E5: ISIN | F5: Précision | G5: Oui | H5: Widget accueil | I5: Résultat | J5: Note | K5: Technique
A6: sec:marches:idx_eu | B6: Indices · Europe | C6: ▸ toute la section | K6: {"id": "idx_eu", "label": "Indices · Europe", "liste": "indices"}
A7: mk:cac40 | B7: Indices · Europe | C7: CAC 40 | D7: ^FCHI | G7: Oui | H7: Oui | K7: {"support": "ok", "def": {"id": "cac40", "code": "^FCHI", "nom": "CAC 40"}}
A8: mk:eurostoxx50 | B8: Indices · Europe | C8: Euro Stoxx 50 | D8: ^STOXX50E | G8: Oui | K8: {"support": "ok", "def": {"id": "eurostoxx50", "code": "^STOXX50E", "nom": "Euro Stoxx 50"}}
A9: mk:sbf120 | B9: Indices · Europe | C9: SBF 120 | D9: ^SBF120 | I9: à vérifier | K9: {"support": "ok", "def": {"id": "sbf120", "code": "^SBF120", "nom": "SBF 120"}}
A10: mk:stoxx600 | B10: Indices · Europe | C10: Stoxx Europe 600 | D10: ^STOXX | I10: à vérifier | K10: {"support": "ok", "def": {"id": "stoxx600", "code": "^STOXX", "nom": "Stoxx Europe 600"}}
A11: mk:dax | B11: Indices · Europe | C11: DAX (Allemagne) | D11: ^GDAXI | I11: à vérifier | K11: {"support": "ok", "def": {"id": "dax", "code": "^GDAXI", "nom": "DAX (Allemagne)"}}
A12: mk:ftse100 | B12: Indices · Europe | C12: FTSE 100 (Royaume-Uni) | D12: ^FTSE | I12: à vérifier | K12: {"support": "ok", "def": {"id": "ftse100", "code": "^FTSE", "nom": "FTSE 100 (Royaume-Uni)"}}
A13: mk:ibex35 | B13: Indices · Europe | C13: IBEX 35 (Espagne) | D13: ^IBEX | I13: à vérifier | K13: {"support": "ok", "def": {"id": "ibex35", "code": "^IBEX", "nom": "IBEX 35 (Espagne)"}}
A14: mk:ftsemib | B14: Indices · Europe | C14: FTSE MIB (Italie) | D14: FTSEMIB.MI | I14: à vérifier | K14: {"support": "ok", "def": {"id": "ftsemib", "code": "FTSEMIB.MI", "nom": "FTSE MIB (Italie)"}}
A15: mk:aex | B15: Indices · Europe | C15: AEX (Pays-Bas) | D15: ^AEX | I15: à vérifier | K15: {"support": "ok", "def": {"id": "aex", "code": "^AEX", "nom": "AEX (Pays-Bas)"}}
A16: mk:smi | B16: Indices · Europe | C16: SMI (Suisse) | D16: ^SSMI | I16: à vérifier | K16: {"support": "ok", "def": {"id": "smi", "code": "^SSMI", "nom": "SMI (Suisse)"}}
A17: mk:bel20 | B17: Indices · Europe | C17: BEL 20 (Belgique) | D17: ^BFX | I17: à vérifier | K17: {"support": "ok", "def": {"id": "bel20", "code": "^BFX", "nom": "BEL 20 (Belgique)"}}
A18: sec:marches:idx_us | B18: Indices · États-Unis | C18: ▸ toute la section | K18: {"id": "idx_us", "label": "Indices · États-Unis", "liste": "indices"}
A19: mk:sp500 | B19: Indices · États-Unis | C19: S&P 500 | D19: ^GSPC | G19: Oui | H19: Oui | K19: {"support": "ok", "def": {"id": "sp500", "code": "^GSPC", "nom": "S&P 500"}}
A20: mk:nasdaq100 | B20: Indices · États-Unis | C20: Nasdaq 100 | D20: ^NDX | G20: Oui | K20: {"support": "ok", "def": {"id": "nasdaq100", "code": "^NDX", "nom": "Nasdaq 100"}}
A21: mk:dowjones | B21: Indices · États-Unis | C21: Dow Jones | D21: ^DJI | I21: à vérifier | K21: {"support": "ok", "def": {"id": "dowjones", "code": "^DJI", "nom": "Dow Jones"}}
A22: mk:nasdaq | B22: Indices · États-Unis | C22: Nasdaq Composite | D22: ^IXIC | I22: à vérifier | K22: {"support": "ok", "def": {"id": "nasdaq", "code": "^IXIC", "nom": "Nasdaq Composite"}}
A23: mk:russell2000 | B23: Indices · États-Unis | C23: Russell 2000 | D23: ^RUT | I23: à vérifier | K23: {"support": "ok", "def": {"id": "russell2000", "code": "^RUT", "nom": "Russell 2000"}}
A24: mk:vix | B24: Indices · États-Unis | C24: VIX (volatilité) | D24: ^VIX | I24: à vérifier | K24: {"support": "ok", "def": {"id": "vix", "code": "^VIX", "nom": "VIX (volatilité)"}}
A25: sec:marches:idx_monde | B25: Indices · Monde | C25: ▸ toute la section | K25: {"id": "idx_monde", "label": "Indices · Monde", "liste": "indices"}
A26: mk:monde | B26: Indices · Monde | C26: MSCI World | D26: EUNL.DE | F26: via un ETF en euros | G26: Oui | H26: Oui | K26: {"support": "ok", "def": {"id": "monde", "code": "EUNL.DE", "nom": "MSCI World", "note": "via un ETF en euros"}}
A27: mk:emergents | B27: Indices · Monde | C27: Émergents | D27: IS3N.DE | F27: via un ETF en euros | G27: Oui | K27: {"support": "ok", "def": {"id": "emergents", "code": "IS3N.DE", "nom": "Émergents", "note": "via un ETF en euros"}}
A28: mk:nikkei | B28: Indices · Monde | C28: Nikkei 225 (Japon) | D28: ^N225 | I28: à vérifier | K28: {"support": "ok", "def": {"id": "nikkei", "code": "^N225", "nom": "Nikkei 225 (Japon)"}}
A29: mk:hangseng | B29: Indices · Monde | C29: Hang Seng (Hong Kong) | D29: ^HSI | I29: à vérifier | K29: {"support": "ok", "def": {"id": "hangseng", "code": "^HSI", "nom": "Hang Seng (Hong Kong)"}}
A30: mk:shanghai | B30: Indices · Monde | C30: Shanghai Composite | D30: 000001.SS | I30: à vérifier | K30: {"support": "ok", "def": {"id": "shanghai", "code": "000001.SS", "nom": "Shanghai Composite"}}
A31: mk:sensex | B31: Indices · Monde | C31: Sensex (Inde) | D31: ^BSESN | I31: à vérifier | K31: {"support": "ok", "def": {"id": "sensex", "code": "^BSESN", "nom": "Sensex (Inde)"}}
A32: mk:kospi | B32: Indices · Monde | C32: KOSPI (Corée) | D32: ^KS11 | I32: à vérifier | K32: {"support": "ok", "def": {"id": "kospi", "code": "^KS11", "nom": "KOSPI (Corée)"}}
A33: mk:asx200 | B33: Indices · Monde | C33: ASX 200 (Australie) | D33: ^AXJO | I33: à vérifier | K33: {"support": "ok", "def": {"id": "asx200", "code": "^AXJO", "nom": "ASX 200 (Australie)"}}
A34: mk:tsx | B34: Indices · Monde | C34: TSX (Canada) | D34: ^GSPTSE | I34: à vérifier | K34: {"support": "ok", "def": {"id": "tsx", "code": "^GSPTSE", "nom": "TSX (Canada)"}}
A35: mk:bovespa | B35: Indices · Monde | C35: Bovespa (Brésil) | D35: ^BVSP | I35: à vérifier | K35: {"support": "ok", "def": {"id": "bovespa", "code": "^BVSP", "nom": "Bovespa (Brésil)"}}
A36: sec:marches:matieres | B36: Matières premières | C36: ▸ toute la section | K36: {"id": "matieres", "label": "Matières premières", "liste": "indices"}
A37: mk:or | B37: Matières premières | C37: Or | D37: GC=F | F37: en dollars | G37: Oui | K37: {"support": "ok", "def": {"id": "or", "code": "GC=F", "nom": "Or", "note": "en dollars"}}
A38: mk:brent | B38: Matières premières | C38: Pétrole Brent | D38: BZ=F | F38: en dollars | G38: Oui | K38: {"support": "ok", "def": {"id": "brent", "code": "BZ=F", "nom": "Pétrole Brent", "note": "en dollars"}}
A39: mk:argent | B39: Matières premières | C39: Argent | D39: SI=F | F39: en dollars | I39: à vérifier | K39: {"support": "ok", "def": {"id": "argent", "code": "SI=F", "nom": "Argent", "note": "en dollars"}}
A40: mk:platine | B40: Matières premières | C40: Platine | D40: PL=F | F40: en dollars | I40: à vérifier | K40: {"support": "ok", "def": {"id": "platine", "code": "PL=F", "nom": "Platine", "note": "en dollars"}}
A41: mk:cuivre | B41: Matières premières | C41: Cuivre | D41: HG=F | F41: en dollars | I41: à vérifier | K41: {"support": "ok", "def": {"id": "cuivre", "code": "HG=F", "nom": "Cuivre", "note": "en dollars"}}
A42: mk:wti | B42: Matières premières | C42: Pétrole WTI | D42: CL=F | F42: en dollars | I42: à vérifier | K42: {"support": "ok", "def": {"id": "wti", "code": "CL=F", "nom": "Pétrole WTI", "note": "en dollars"}}
A43: mk:gaz | B43: Matières premières | C43: Gaz naturel | D43: NG=F | F43: en dollars | I43: à vérifier | K43: {"support": "ok", "def": {"id": "gaz", "code": "NG=F", "nom": "Gaz naturel", "note": "en dollars"}}
A44: mk:ble | B44: Matières premières | C44: Blé | D44: ZW=F | F44: en dollars | I44: à vérifier | K44: {"support": "ok", "def": {"id": "ble", "code": "ZW=F", "nom": "Blé", "note": "en dollars"}}
A45: mk:mais | B45: Matières premières | C45: Maïs | D45: ZC=F | F45: en dollars | I45: à vérifier | K45: {"support": "ok", "def": {"id": "mais", "code": "ZC=F", "nom": "Maïs", "note": "en dollars"}}
A46: mk:cacao | B46: Matières premières | C46: Cacao | D46: CC=F | F46: en dollars | I46: à vérifier | K46: {"support": "ok", "def": {"id": "cacao", "code": "CC=F", "nom": "Cacao", "note": "en dollars"}}
A47: mk:cafe | B47: Matières premières | C47: Café | D47: KC=F | F47: en dollars | I47: à vérifier | K47: {"support": "ok", "def": {"id": "cafe", "code": "KC=F", "nom": "Café", "note": "en dollars"}}
A48: sec:marches:devises | B48: Devises | C48: ▸ toute la section | K48: {"id": "devises", "label": "Devises", "liste": "indices"}
A49: mk:eurusd | B49: Devises | C49: EUR / USD | D49: EURUSD=X | G49: Oui | H49: Oui | K49: {"support": "ok", "def": {"id": "eurusd", "code": "EURUSD=X", "nom": "EUR / USD", "change": true}}
A50: mk:eurgbp | B50: Devises | C50: EUR / GBP | D50: EURGBP=X | I50: à vérifier | K50: {"support": "ok", "def": {"id": "eurgbp", "code": "EURGBP=X", "nom": "EUR / GBP", "change": true}}
A51: mk:eurchf | B51: Devises | C51: EUR / CHF | D51: EURCHF=X | I51: à vérifier | K51: {"support": "ok", "def": {"id": "eurchf", "code": "EURCHF=X", "nom": "EUR / CHF", "change": true}}
A52: mk:eurjpy | B52: Devises | C52: EUR / JPY | D52: EURJPY=X | I52: à vérifier | K52: {"support": "ok", "def": {"id": "eurjpy", "code": "EURJPY=X", "nom": "EUR / JPY", "change": true}}
A53: mk:eurcad | B53: Devises | C53: EUR / CAD | D53: EURCAD=X | I53: à vérifier | K53: {"support": "ok", "def": {"id": "eurcad", "code": "EURCAD=X", "nom": "EUR / CAD", "change": true}}
A54: mk:eurcny | B54: Devises | C54: EUR / CNY | D54: EURCNY=X | I54: à vérifier | K54: {"support": "ok", "def": {"id": "eurcny", "code": "EURCNY=X", "nom": "EUR / CNY", "change": true}}
A55: mk:gbpusd | B55: Devises | C55: GBP / USD | D55: GBPUSD=X | I55: à vérifier | K55: {"support": "ok", "def": {"id": "gbpusd", "code": "GBPUSD=X", "nom": "GBP / USD", "change": true}}
A56: mk:usdjpy | B56: Devises | C56: USD / JPY | D56: USDJPY=X | I56: à vérifier | K56: {"support": "ok", "def": {"id": "usdjpy", "code": "USDJPY=X", "nom": "USD / JPY", "change": true}}
A57: mk:dxy | B57: Devises | C57: Indice dollar (DXY) | D57: DX-Y.NYB | I57: à vérifier | K57: {"support": "ok", "def": {"id": "dxy", "code": "DX-Y.NYB", "nom": "Indice dollar (DXY)"}}
A58: sec:marches:taux | B58: Taux d'intérêt | C58: ▸ toute la section | K58: {"id": "taux", "label": "Taux d'intérêt", "liste": "indices"}
A59: mk:us10 | B59: Taux d'intérêt | C59: Taux US 10 ans | D59: ^TNX | I59: à vérifier | K59: {"support": "ok", "def": {"id": "us10", "code": "^TNX", "nom": "Taux US 10 ans"}}
A60: mk:us30 | B60: Taux d'intérêt | C60: Taux US 30 ans | D60: ^TYX | I60: à vérifier | K60: {"support": "ok", "def": {"id": "us30", "code": "^TYX", "nom": "Taux US 30 ans"}}
A61: mk:us3m | B61: Taux d'intérêt | C61: Taux US 3 mois | D61: ^IRX | I61: à vérifier | K61: {"support": "ok", "def": {"id": "us3m", "code": "^IRX", "nom": "Taux US 3 mois"}}
A62: sec:marches:crypto | B62: Cryptomonnaies | C62: ▸ toute la section | K62: {"id": "crypto", "label": "Cryptomonnaies", "liste": "indices"}
A63: mk:btc | B63: Cryptomonnaies | C63: Bitcoin | D63: BTC-EUR | F63: en euros | I63: à vérifier | K63: {"support": "ok", "def": {"id": "btc", "code": "BTC-EUR", "nom": "Bitcoin", "note": "en euros"}}
A64: mk:eth | B64: Cryptomonnaies | C64: Ethereum | D64: ETH-EUR | F64: en euros | I64: à vérifier | K64: {"support": "ok", "def": {"id": "eth", "code": "ETH-EUR", "nom": "Ethereum", "note": "en euros"}}
A65: mk:sol | B65: Cryptomonnaies | C65: Solana | D65: SOL-EUR | F65: en euros | I65: à vérifier | K65: {"support": "ok", "def": {"id": "sol", "code": "SOL-EUR", "nom": "Solana", "note": "en euros"}}
A66: mk:xrp | B66: Cryptomonnaies | C66: XRP | D66: XRP-EUR | F66: en euros | I66: à vérifier | K66: {"support": "ok", "def": {"id": "xrp", "code": "XRP-EUR", "nom": "XRP", "note": "en euros"}}
A67: mk:bnb | B67: Cryptomonnaies | C67: BNB | D67: BNB-EUR | F67: en euros | I67: à vérifier | K67: {"support": "ok", "def": {"id": "bnb", "code": "BNB-EUR", "nom": "BNB", "note": "en euros"}}
A68: mk:ada | B68: Cryptomonnaies | C68: Cardano | D68: ADA-EUR | F68: en euros | I68: à vérifier | K68: {"support": "ok", "def": {"id": "ada", "code": "ADA-EUR", "nom": "Cardano", "note": "en euros"}}
A69: mk:doge | B69: Cryptomonnaies | C69: Dogecoin | D69: DOGE-EUR | F69: en euros | I69: à vérifier | K69: {"support": "ok", "def": {"id": "doge", "code": "DOGE-EUR", "nom": "Dogecoin", "note": "en euros"}}
A70: sec:marches:fonds | B70: Fonds et ETF suivis (ISIN) | C70: ▸ toute la section | K70: {"id": "fonds", "label": "Fonds et ETF suivis", "liste": "suivi"}
A71: fd:IE00B4L5Y983 | B71: Fonds et ETF suivis (ISIN) | C71: iShares Core MSCI World (Acc) | D71: EUNL.DE | E71: IE00B4L5Y983 | G71: Oui | K71: {"support": "ok", "def": {"isin": "IE00B4L5Y983", "code": "EUNL.DE", "nom": "iShares Core MSCI World (Acc)"}}
A72: fd:LU1681045370 | B72: Fonds et ETF suivis (ISIN) | C72: Amundi MSCI Emerging Markets (Acc) | D72: AEEM.PA | E72: LU1681045370 | G72: Oui | K72: {"support": "ok", "def": {"isin": "LU1681045370", "code": "AEEM.PA", "nom": "Amundi MSCI Emerging Markets (Acc)"}}
A73: fd:LU1681048804 | B73: Fonds et ETF suivis (ISIN) | C73: Amundi S&P 500 (Acc) | D73: 500.PA | E73: LU1681048804 | G73: Oui | K73: {"support": "ok", "def": {"isin": "LU1681048804", "code": "500.PA", "nom": "Amundi S&P 500 (Acc)"}}
A74: fd:LU1681043599 | B74: Fonds et ETF suivis (ISIN) | C74: Amundi MSCI World (Acc) | D74: CW8.PA | E74: LU1681043599 | I74: à vérifier | K74: {"support": "ok", "def": {"isin": "LU1681043599", "code": "CW8.PA", "nom": "Amundi MSCI World (Acc)"}}
A75: fd:FR0011869353 | B75: Fonds et ETF suivis (ISIN) | C75: Amundi PEA Monde (MSCI World) | D75: EWLD.PA | E75: FR0011869353 | I75: à vérifier | K75: {"support": "ok", "def": {"isin": "FR0011869353", "code": "EWLD.PA", "nom": "Amundi PEA Monde (MSCI World)"}}
A76: fd:FR0011871128 | B76: Fonds et ETF suivis (ISIN) | C76: Amundi PEA S&P 500 | D76: PSP5.PA | E76: FR0011871128 | I76: à vérifier | K76: {"support": "ok", "def": {"isin": "FR0011871128", "code": "PSP5.PA", "nom": "Amundi PEA S&P 500"}}
A77: fd:FR0011871110 | B77: Fonds et ETF suivis (ISIN) | C77: Amundi PEA Nasdaq-100 | D77: PUST.PA | E77: FR0011871110 | I77: à vérifier | K77: {"support": "ok", "def": {"isin": "FR0011871110", "code": "PUST.PA", "nom": "Amundi PEA Nasdaq-100"}}
A78: fd:FR0011550185 | B78: Fonds et ETF suivis (ISIN) | C78: BNP Paribas Easy S&P 500 | D78: ESE.PA | E78: FR0011550185 | I78: à vérifier | K78: {"support": "ok", "def": {"isin": "FR0011550185", "code": "ESE.PA", "nom": "BNP Paribas Easy S&P 500"}}
A79: fd:IE00B5BMR087 | B79: Fonds et ETF suivis (ISIN) | C79: iShares Core S&P 500 (Acc) | D79: SXR8.DE | E79: IE00B5BMR087 | I79: à vérifier | K79: {"support": "ok", "def": {"isin": "IE00B5BMR087", "code": "SXR8.DE", "nom": "iShares Core S&P 500 (Acc)"}}
A80: fd:IE00BK5BQT80 | B80: Fonds et ETF suivis (ISIN) | C80: Vanguard FTSE All-World (Acc) | D80: VWCE.DE | E80: IE00BK5BQT80 | I80: à vérifier | K80: {"support": "ok", "def": {"isin": "IE00BK5BQT80", "code": "VWCE.DE", "nom": "Vanguard FTSE All-World (Acc)"}}
A81: fd:IE00B6R52259 | B81: Fonds et ETF suivis (ISIN) | C81: iShares MSCI ACWI (Acc) | D81: IUSQ.DE | E81: IE00B6R52259 | I81: à vérifier | K81: {"support": "ok", "def": {"isin": "IE00B6R52259", "code": "IUSQ.DE", "nom": "iShares MSCI ACWI (Acc)"}}
A82: fd:IE00BKM4GZ66 | B82: Fonds et ETF suivis (ISIN) | C82: iShares Core MSCI EM IMI (Acc) | D82: IS3N.DE | E82: IE00BKM4GZ66 | I82: à vérifier | K82: {"support": "ok", "def": {"isin": "IE00BKM4GZ66", "code": "IS3N.DE", "nom": "iShares Core MSCI EM IMI (Acc)"}}
A83: fd:LU0908500753 | B83: Fonds et ETF suivis (ISIN) | C83: Amundi Stoxx Europe 600 (Acc) | D83: MEUD.PA | E83: LU0908500753 | I83: à vérifier | K83: {"support": "ok", "def": {"isin": "LU0908500753", "code": "MEUD.PA", "nom": "Amundi Stoxx Europe 600 (Acc)"}}
B86: MES AJOUTS — tape ce que tu veux ajouter : la tâche essaie de le récupérer et écrit le résultat (✅ / ⚠️ / ❌) dans la colonne « Résultat »
B87: Section (Fonds et ETF suivis, ou autre) | C87: Nom | D87: ISIN ou code de cotation | G87: Oui | I87: Résultat | J87: Note
A88: exemple | B88: Indices · Europe | C88: Amundi PEA Monde | D88: FR0011869353 | G88: Oui | J88: Ligne d'exemple : ignorée par la tâche
A89: ajout:1
A90: ajout:2
A91: ajout:3
A92: ajout:4
A93: ajout:5
A94: ajout:6
A95: ajout:7
A96: ajout:8
A97: ajout:9
A98: ajout:10
A99: ajout:11
A100: ajout:12
... A108: ajout:20

Sheet Vidéos
A1: module=videos;version=2 | B1: Vidéos · plateformes de streaming
B2: « Oui » = la plateforme apparaît dans les filtres de la page Vidéos. « Abonné » = elle fait partie de « Mes abonnements » par défaut. Seuls les titres inclus dans l'abonnement sont listés (pas la location ni l'achat).
B3: À remplir : cases jaunes (« Oui » ou « Non »). Ligne « ▸ toute la section » = tous ses éléments, sauf ceux marqués « Non ». Un seul élément coché suffit pour que sa section apparaisse. Colonne « Résultat » : remplie par la tâche GitHub après dépôt du classeur.
A5: ID | B5: Section | C5: Plateforme | D5: Badge | E5: Lien d'ouverture de l'appli | F5: Précision | G5: Oui | H5: Abonné | I5: Résultat | J5: Note | K5: Technique
A6: sec:videos:plateformes | B6: Plateformes | C6: ▸ toute la section | K6: {"id": "plateformes", "label": "Plateformes"}
A7: pf:netflix | B7: Plateformes | C7: Netflix | D7: N | E7: nflx:// | G7: Oui | H7: Oui | K7: {"support": "ok", "def": {"id": "netflix", "nom": "Netflix", "court": "N", "coul": "#e50914", "tmdb": "^netflix", "app": "nflx://", "web": "https://www.netflix.com/search?q="}}
A8: pf:prime | B8: Plateformes | C8: Prime Video | D8: prime | E8: aiv:// | G8: Oui | H8: Oui | K8: {"support": "ok", "def": {"id": "prime", "nom": "Prime Video", "court": "prime", "coul": "#1a98ff", "tmdb": "^amazon prime video", "app": "aiv://", "web": "https://www.primevideo.com/search/ref=atv_nb_sr?phrase="}}
A9: pf:disney | B9: Plateformes | C9: Disney+ | D9: D+ | E9: disneyplus:// | G9: Oui | K9: {"support": "ok", "def": {"id": "disney", "nom": "Disney+", "court": "D+", "coul": "#113ccf", "tmdb": "^disney ?(plus|\\+)", "app": "disneyplus://", "web": "https://www.disneyplus.com/search?q="}}
A10: pf:hbo | B10: Plateformes | C10: HBO Max | D10: HBO | E10: hbomax:// | G10: Oui | K10: {"support": "ok", "def": {"id": "hbo", "nom": "HBO Max", "court": "HBO", "coul": "#5b2bd1", "tmdb": "^(hbo )?max$|^hbo max", "app": "hbomax://", "web": "https://play.hbomax.com/search?q="}}
A11: pf:apple | B11: Plateformes | C11: Apple TV | D11: tv | E11: videos:// | G11: Oui | K11: {"support": "ok", "def": {"id": "apple", "nom": "Apple TV", "court": "tv", "coul": "#1d1d1f", "tmdb": "^apple tv", "app": "videos://", "web": "https://tv.apple.com/fr/search?term="}}
A12: pf:canal | B12: Plateformes | C12: Canal+ | D12: C+ | E12: mycanal:// | G12: Oui | K12: {"support": "ok", "def": {"id": "canal", "nom": "Canal+", "court": "C+", "coul": "#111111", "tmdb": "^canal ?(\\+|plus)", "app": "mycanal://", "web": "https://www.canalplus.com/recherche/?q="}}
A13: pf:ocs | B13: Plateformes | C13: OCS | D13: OCS | E13: mycanal:// | G13: Oui | K13: {"support": "ok", "def": {"id": "ocs", "nom": "OCS", "court": "OCS", "coul": "#f26522", "tmdb": "^ocs", "app": "mycanal://", "web": "https://www.canalplus.com/recherche/?q="}}
A14: pf:paramount | B14: Plateformes | C14: Paramount+ | D14: P+ | E14: paramountplus:// | I14: à vérifier | K14: {"support": "ok", "def": {"id": "paramount", "nom": "Paramount+", "court": "P+", "coul": "#0064ff", "tmdb": "^paramount ?(\\+|plus)", "app": "paramountplus://", "web": "https://www.paramountplus.com/fr/search/?q="}}
A15: pf:crunchyroll | B15: Plateformes | C15: Crunchyroll | D15: CR | E15: crunchyroll:// | F15: animation japonaise | I15: à vérifier | K15: {"support": "ok", "def": {"id": "crunchyroll", "nom": "Crunchyroll", "court": "CR", "coul": "#f47521", "tmdb": "^crunchyroll", "app": "crunchyroll://", "web": "https://www.crunchyroll.com/fr/search?q="}}
A16: pf:adn | B16: Plateformes | C16: ADN | D16: ADN | E16: adn:// | F16: animation japonaise | I16: à vérifier | K16: {"support": "ok", "def": {"id": "adn", "nom": "ADN", "court": "ADN", "coul": "#0096d6", "tmdb": "^(adn|animation digital network)", "app": "adn://", "web": "https://animationdigitalnetwork.com/search?query="}}
A17: pf:arte | B17: Plateformes | C17: Arte | D17: arte | E17: arte:// | F17: gratuit | I17: à vérifier | K17: {"support": "ok", "def": {"id": "arte", "nom": "Arte", "court": "arte", "coul": "#fa481c", "tmdb": "^arte", "app": "arte://", "web": "https://www.arte.tv/fr/search/?q="}}
A18: pf:francetv | B18: Plateformes | C18: france.tv | D18: f.tv | E18: francetv:// | F18: gratuit | I18: à vérifier | K18: {"support": "ok", "def": {"id": "francetv", "nom": "france.tv", "court": "f.tv", "coul": "#2a2aff", "tmdb": "^france ?tv", "app": "francetv://", "web": "https://www.france.tv/recherche/?q="}}
A19: pf:tf1 | B19: Plateformes | C19: TF1+ | D19: TF1 | E19: tf1plus:// | F19: gratuit | I19: à vérifier | K19: {"support": "ok", "def": {"id": "tf1", "nom": "TF1+", "court": "TF1", "coul": "#0067b1", "tmdb": "^tf1", "app": "tf1plus://", "web": "https://www.tf1.fr/recherche?q="}}
A20: pf:m6 | B20: Plateformes | C20: M6+ | D20: M6 | E20: m6plus:// | F20: gratuit | I20: à vérifier | K20: {"support": "ok", "def": {"id": "m6", "nom": "M6+", "court": "M6", "coul": "#ff0f64", "tmdb": "^(m6|6play)", "app": "m6plus://", "web": "https://www.m6.fr/recherche?q="}}
A21: pf:pluto | B21: Plateformes | C21: Pluto TV | D21: PL | E21: plutotv:// | F21: gratuit avec pubs | I21: à vérifier | K21: {"support": "ok", "def": {"id": "pluto", "nom": "Pluto TV", "court": "PL", "coul": "#2f2f2f", "tmdb": "^pluto", "app": "plutotv://", "web": "https://pluto.tv/fr/search/details?query="}}
A22: pf:mubi | B22: Plateformes | C22: MUBI | D22: MUBI | E22: mubi:// | F22: cinéma d'auteur | I22: à vérifier | K22: {"support": "ok", "def": {"id": "mubi", "nom": "MUBI", "court": "MUBI", "coul": "#001489", "tmdb": "^mubi", "app": "mubi://", "web": "https://mubi.com/fr/search/films?query="}}
A23: pf:universcine | B23: Plateformes | C23: UniversCiné | D23: UC | F23: cinéma indépendant | I23: à vérifier | K23: {"support": "ok", "def": {"id": "universcine", "nom": "UniversCiné", "court": "UC", "coul": "#e30613", "tmdb": "^universcin", "app": "", "web": "https://www.universcine.com/recherche?q="}}
A24: pf:shadowz | B24: Plateformes | C24: Shadowz | D24: SZ | F24: horreur | I24: à vérifier | K24: {"support": "ok", "def": {"id": "shadowz", "nom": "Shadowz", "court": "SZ", "coul": "#7a0000", "tmdb": "^shadowz", "app": "", "web": "https://www.shadowz.fr/search?q="}}
A25: pf:filmo | B25: Plateformes | C25: FILMO | D25: FO | I25: à vérifier | K25: {"support": "ok", "def": {"id": "filmo", "nom": "FILMO", "court": "FO", "coul": "#ff5a00", "tmdb": "^filmo", "app": "", "web": "https://www.filmo.tv/recherche?q="}}
A26: pf:rakuten | B26: Plateformes | C26: Rakuten TV | D26: RK | E26: rakutentv:// | F26: partie gratuite | I26: à vérifier | K26: {"support": "ok", "def": {"id": "rakuten", "nom": "Rakuten TV", "court": "RK", "coul": "#bf0000", "tmdb": "^rakuten", "app": "rakutentv://", "web": "https://www.rakuten.tv/fr/search?q="}}
B29: MES AJOUTS — tape ce que tu veux ajouter : la tâche essaie de le récupérer et écrit le résultat (✅ / ⚠️ / ❌) dans la colonne « Résultat »
B30: Section | C30: Nom de la plateforme | D30: Nom exact chez JustWatch / TMDB | G30: Oui | I30: Résultat | J30: Note
A31: exemple | B31: Plateformes | C31: Molotov | D31: Molotov TV | G31: Oui | J31: Ligne d'exemple : ignorée par la tâche
A32: ajout:1
A33: ajout:2
A34: ajout:3
A35: ajout:4
A36: ajout:5
A37: ajout:6
A38: ajout:7
A39: ajout:8
A40: ajout:9
A41: ajout:10
A42: ajout:11
A43: ajout:12
... A51: ajout:20

Sheet YouTube
A1: module=youtube;version=2 | B1: Vidéos · chaînes YouTube
B2: Les vidéos récentes des chaînes cochées s'affichent dans l'onglet YouTube de la page Vidéos. L'identifiant peut être un @nom, un lien de chaîne ou un identifiant UC….
B3: À remplir : cases jaunes (« Oui » ou « Non »). Ligne « ▸ toute la section » = tous ses éléments, sauf ceux marqués « Non ». Un seul élément coché suffit pour que sa section apparaisse. Colonne « Résultat » : remplie par la tâche GitHub après dépôt du classeur.
A5: ID | B5: Section | C5: Chaîne | D5: Identifiant (@nom, lien ou UC…) | E5: Oui | F5: Résultat | G5: Note | H5: Technique
A6: sec:youtube:actuelles | B6: Mes chaînes actuelles | C6: ▸ toute la section | H6: {"id": "actuelles", "label": "Mes chaînes actuelles"}
A7: yt:UCFKDEp9si4RmHFWJW1vYsMA | B7: Mes chaînes actuelles | C7: EthosLab | D7: UCFKDEp9si4RmHFWJW1vYsMA | E7: Oui | H7: {"support": "ok", "def": {"id": "UCFKDEp9si4RmHFWJW1vYsMA", "nom": "EthosLab"}}
A8: yt:UCTdicWbtwYfLyZ7S1M9XuIQ | B8: Mes chaînes actuelles | C8: Oliech | D8: UCTdicWbtwYfLyZ7S1M9XuIQ | E8: Oui | H8: {"support": "ok", "def": {"id": "UCTdicWbtwYfLyZ7S1M9XuIQ", "nom": "Oliech"}}
A9: sec:youtube:actualite | B9: Actualité | C9: ▸ toute la section | H9: {"id": "actualite", "label": "Actualité"}
A10: yt:@hugodecrypte | B10: Actualité | C10: HugoDécrypte | D10: @HugoDecrypte | F10: à vérifier | H10: {"support": "ok", "def": {"id": "@HugoDecrypte", "nom": "HugoDécrypte"}}
A11: yt:@franceinfo | B11: Actualité | C11: franceinfo | D11: @franceinfo | F11: à vérifier | H11: {"support": "ok", "def": {"id": "@franceinfo", "nom": "franceinfo"}}
A12: yt:@artefr | B12: Actualité | C12: ARTE | D12: @ARTEfr | F12: à vérifier | H12: {"support": "ok", "def": {"id": "@ARTEfr", "nom": "ARTE"}}
A13: yt:@lemondefr | B13: Actualité | C13: Le Monde | D13: @LeMondefr | F13: à vérifier | H13: {"support": "ok", "def": {"id": "@LeMondefr", "nom": "Le Monde"}}
A14: yt:@mediapart | B14: Actualité | C14: Mediapart | D14: @Mediapart | F14: à vérifier | H14: {"support": "ok", "def": {"id": "@Mediapart", "nom": "Mediapart"}}
A15: sec:youtube:sciences | B15: Sciences | C15: ▸ toute la section | H15: {"id": "sciences", "label": "Sciences"}
A16: yt:@scienceetonnante | B16: Sciences | C16: ScienceÉtonnante | D16: @ScienceEtonnante | F16: à vérifier | H16: {"support": "ok", "def": {"id": "@ScienceEtonnante", "nom": "ScienceÉtonnante"}}
A17: yt:@dirtybiology | B17: Sciences | C17: DirtyBiology | D17: @DirtyBiology | F17: à vérifier | H17: {"support": "ok", "def": {"id": "@DirtyBiology", "nom": "DirtyBiology"}}
A18: yt:@fouloscopie | B18: Sciences | C18: Fouloscopie | D18: @Fouloscopie | F18: à vérifier | H18: {"support": "ok", "def": {"id": "@Fouloscopie", "nom": "Fouloscopie"}}
A19: yt:@veritasium | B19: Sciences | C19: Veritasium | D19: @veritasium | F19: à vérifier | H19: {"support": "ok", "def": {"id": "@veritasium", "nom": "Veritasium"}}
A20: yt:@kurzgesagt | B20: Sciences | C20: Kurzgesagt | D20: @kurzgesagt | F20: à vérifier | H20: {"support": "ok", "def": {"id": "@kurzgesagt", "nom": "Kurzgesagt"}}
A21: yt:@3blue1brown | B21: Sciences | C21: 3Blue1Brown | D21: @3blue1brown | F21: à vérifier | H21: {"support": "ok", "def": {"id": "@3blue1brown", "nom": "3Blue1Brown"}}
A22: yt:@markrober | B22: Sciences | C22: Mark Rober | D22: @MarkRober | F22: à vérifier | H22: {"support": "ok", "def": {"id": "@MarkRober", "nom": "Mark Rober"}}
A23: yt:@smartereveryday | B23: Sciences | C23: SmarterEveryDay | D23: @smartereveryday | F23: à vérifier | H23: {"support": "ok", "def": {"id": "@smartereveryday", "nom": "SmarterEveryDay"}}
A24: sec:youtube:astronomie-et-espace | B24: Astronomie et espace | C24: ▸ toute la section | H24: {"id": "astronomie-et-espace", "label": "Astronomie et espace"}
A25: yt:@nasa | B25: Astronomie et espace | C25: NASA | D25: @NASA | F25: à vérifier | H25: {"support": "ok", "def": {"id": "@NASA", "nom": "NASA"}}
A26: yt:@spacex | B26: Astronomie et espace | C26: SpaceX | D26: @SpaceX | F26: à vérifier | H26: {"support": "ok", "def": {"id": "@SpaceX", "nom": "SpaceX"}}
A27: yt:@europeanspaceagency | B27: Astronomie et espace | C27: ESA | D27: @EuropeanSpaceAgency | F27: à vérifier | H27: {"support": "ok", "def": {"id": "@EuropeanSpaceAgency", "nom": "ESA"}}
A28: yt:@scottmanley | B28: Astronomie et espace | C28: Scott Manley | D28: @scottmanley | F28: à vérifier | H28: {"support": "ok", "def": {"id": "@scottmanley", "nom": "Scott Manley"}}
A29: yt:@everydayastronaut | B29: Astronomie et espace | C29: Everyday Astronaut | D29: @EverydayAstronaut | F29: à vérifier | H29: {"support": "ok", "def": {"id": "@EverydayAstronaut", "nom": "Everyday Astronaut"}}
A30: sec:youtube:histoire-et-geopolitique | B30: Histoire et géopolitique | C30: ▸ toute la section | H30: {"id": "histoire-et-geopolitique", "label": "Histoire et géopolitique"}
A31: yt:@notabenemovies | B31: Histoire et géopolitique | C31: Nota Bene | D31: @NotaBeneMovies | F31: à vérifier | H31: {"support": "ok", "def": {"id": "@NotaBeneMovies", "nom": "Nota Bene"}}
A32: yt:@ledessousdescartes | B32: Histoire et géopolitique | C32: Le Dessous des cartes | D32: @LeDessousDesCartes | F32: à vérifier | H32: {"support": "ok", "def": {"id": "@LeDessousDesCartes", "nom": "Le Dessous des cartes"}}
A33: yt:@reallifelore | B33: Histoire et géopolitique | C33: RealLifeLore | D33: @RealLifeLore | F33: à vérifier | H33: {"support": "ok", "def": {"id": "@RealLifeLore", "nom": "RealLifeLore"}}
A34: yt:@perunau | B34: Histoire et géopolitique | C34: Perun (défense) | D34: @PerunAU | F34: à vérifier | H34: {"support": "ok", "def": {"id": "@PerunAU", "nom": "Perun (défense)"}}
A35: yt:@taskandpurpose | B35: Histoire et géopolitique | C35: Task & Purpose (défense) | D35: @TaskandPurpose | F35: à vérifier | H35: {"support": "ok", "def": {"id": "@TaskandPurpose", "nom": "Task & Purpose (défense)"}}
A36: sec:youtube:tech | B36: Tech | C36: ▸ toute la section | H36: {"id": "tech", "label": "Tech"}
A37: yt:@micode | B37: Tech | C37: Micode | D37: @Micode | F37: à vérifier | H37: {"support": "ok", "def": {"id": "@Micode", "nom": "Micode"}}
A38: yt:@underscoretalk | B38: Tech | C38: Underscore_ | D38: @UnderscoreTalk | F38: à vérifier | H38: {"support": "ok", "def": {"id": "@UnderscoreTalk", "nom": "Underscore_"}}
A39: yt:@mkbhd | B39: Tech | C39: Marques Brownlee | D39: @mkbhd | F39: à vérifier | H39: {"support": "ok", "def": {"id": "@mkbhd", "nom": "Marques Brownlee"}}
A40: yt:@linustechtips | B40: Tech | C40: Linus Tech Tips | D40: @LinusTechTips | F40: à vérifier | H40: {"support": "ok", "def": {"id": "@LinusTechTips", "nom": "Linus Tech Tips"}}
A41: yt:@monsieurdream | B41: Tech | C41: Monsieur Dream | D41: @Monsieurdream | F41: à vérifier | H41: {"support": "ok", "def": {"id": "@Monsieurdream", "nom": "Monsieur Dream"}}
A42: sec:youtube:jeux-video | B42: Jeux vidéo | C42: ▸ toute la section | H42: {"id": "jeux-video", "label": "Jeux vidéo"}
A43: yt:@joueurdugrenier | B43: Jeux vidéo | C43: Joueur du Grenier | D43: @joueurdugrenier | F43: à vérifier | H43: {"support": "ok", "def": {"id": "@joueurdugrenier", "nom": "Joueur du Grenier"}}
A44: yt:@squeezie | B44: Jeux vidéo | C44: Squeezie | D44: @Squeezie | F44: à vérifier | H44: {"support": "ok", "def": {"id": "@Squeezie", "nom": "Squeezie"}}
A45: yt:@gotaga | B45: Jeux vidéo | C45: Gotaga | D45: @Gotaga | F45: à vérifier | H45: {"support": "ok", "def": {"id": "@Gotaga", "nom": "Gotaga"}}
A46: yt:@gameblogfr | B46: Jeux vidéo | C46: Gameblog | D46: @gameblogfr | F46: à vérifier | H46: {"support": "ok", "def": {"id": "@gameblogfr", "nom": "Gameblog"}}
A47: yt:@ign | B47: Jeux vidéo | C47: IGN | D47: @IGN | F47: à vérifier | H47: {"support": "ok", "def": {"id": "@IGN", "nom": "IGN"}}
A48: sec:youtube:sport | B48: Sport | C48: ▸ toute la section | H48: {"id": "sport", "label": "Sport"}
A49: yt:@ligue1 | B49: Sport | C49: Ligue 1 | D49: @Ligue1 | F49: à vérifier | H49: {"support": "ok", "def": {"id": "@Ligue1", "nom": "Ligue 1"}}
A50: yt:@lequipe | B50: Sport | C50: L'Équipe | D50: @lequipe | F50: à vérifier | H50: {"support": "ok", "def": {"id": "@lequipe", "nom": "L'Équipe"}}
A51: yt:@formula1 | B51: Sport | C51: Formule 1 | D51: @Formula1 | F51: à vérifier | H51: {"support": "ok", "def": {"id": "@Formula1", "nom": "Formule 1"}}
A52: yt:@motogp | B52: Sport | C52: MotoGP | D52: @MotoGP | F52: à vérifier | H52: {"support": "ok", "def": {"id": "@MotoGP", "nom": "MotoGP"}}
A53: yt:@top14rugby | B53: Sport | C53: Top 14 | D53: @Top14Rugby | F53: à vérifier | H53: {"support": "ok", "def": {"id": "@Top14Rugby", "nom": "Top 14"}}
A54: yt:@nba | B54: Sport | C54: NBA | D54: @NBA | F54: à vérifier | H54: {"support": "ok", "def": {"id": "@NBA", "nom": "NBA"}}
A55: sec:youtube:cuisine | B55: Cuisine | C55: ▸ toute la section | H55: {"id": "cuisine", "label": "Cuisine"}
A56: yt:@chefmichaeldusseldorf | B56: Cuisine | C56: Chef Michael | D56: @Chefmichaeldusseldorf | F56: à vérifier | H56: {"support": "ok", "def": {"id": "@Chefmichaeldusseldorf", "nom": "Chef Michael"}}
A57: yt:@joshuaweissman | B57: Cuisine | C57: Joshua Weissman | D57: @JoshuaWeissman | F57: à vérifier | H57: {"support": "ok", "def": {"id": "@JoshuaWeissman", "nom": "Joshua Weissman"}}
A58: sec:youtube:divertissement | B58: Divertissement | C58: ▸ toute la section | H58: {"id": "divertissement", "label": "Divertissement"}
A59: yt:@cyprien | B59: Divertissement | C59: Cyprien | D59: @Cyprien | F59: à vérifier | H59: {"support": "ok", "def": {"id": "@Cyprien", "nom": "Cyprien"}}
A60: yt:@mcfly-et-carlito | B60: Divertissement | C60: McFly & Carlito | D60: @Mcfly-et-Carlito | F60: à vérifier | H60: {"support": "ok", "def": {"id": "@Mcfly-et-Carlito", "nom": "McFly & Carlito"}}
B63: MES AJOUTS — tape ce que tu veux ajouter : la tâche essaie de le récupérer et écrit le résultat (✅ / ⚠️ / ❌) dans la colonne « Résultat »
B64: Thème (existant ou nouveau) | C64: Nom de la chaîne | D64: @nom, lien ou identifiant UC… | E64: Oui | F64: Résultat | G64: Note
A65: exemple | B65: Mes chaînes actuelles | C65: Astronogeek | D65: @astronogeek | E65: Oui | G65: Ligne d'exemple : ignorée par la tâche
A66: ajout:1
A67: ajout:2
A68: ajout:3
A69: ajout:4
A70: ajout:5
A71: ajout:6
A72: ajout:7
A73: ajout:8
A74: ajout:9
A75: ajout:10
A76: ajout:11
A77: ajout:12
... A85: ajout:20

Sheet Programme TV
A1: module=tv;version=2 | B1: Programme TV · chaînes lues pour les matchs
B2: Chaînes dont le programme est récupéré pour savoir où regarder un match (page Sport). Les sources sont des guides TV publics ; une chaîne peut avoir plusieurs sources de secours.
B3: À remplir : cases jaunes (« Oui » ou « Non »). Ligne « ▸ toute la section » = tous ses éléments, sauf ceux marqués « Non ». Un seul élément coché suffit pour que sa section apparaisse. Colonne « Résultat » : remplie par la tâche GitHub après dépôt du classeur.
A5: ID | B5: Section | C5: Chaîne | D5: Sources du programme | E5: Oui | F5: Résultat | G5: Note | H5: Technique
A6: sec:tv:canal | B6: Canal+ | C6: ▸ toute la section | H6: {"id": "canal", "label": "Canal+"}
A7: tv:canal | B7: Canal+ | C7: Canal+ | D7: canalplus.com, epgshare01.online | E7: Oui | H7: {"support": "ok", "def": {"nom": "Canal+", "sources": [{"site": "canalplus.com", "site_id": "#301", "lang": "fr", "xmltv_id": "CPLUS", "nom": "Canal+", "ordre": 0}, {"site": "epgshare01.online", "site_id": "FR1#CANAL+.fr", "lang": "fr", "xmltv_id": "CPLUS_E", "nom": "Canal+", "ordre": 84}]}}
A8: tv:canal-sport | B8: Canal+ | C8: Canal+ Sport | D8: canalplus.com, epgshare01.online | E8: Oui | H8: {"support": "ok", "def": {"nom": "Canal+ Sport", "sources": [{"site": "canalplus.com", "site_id": "#177", "lang": "fr", "xmltv_id": "CPSPORT", "nom": "Canal+ Sport", "ordre": 1}, {"site": "epgshare01.online", "site_id": "FR1#Canal+.Sport.fr", "lang": "fr", "xmltv_id": "CPSPORT_E", "nom": "Canal+ Sport", "ordre": 81}]}}
A9: tv:canal-foot | B9: Canal+ | C9: Canal+ Foot | D9: canalplus.com, tv.sfr.fr, epgshare01.online | E9: Oui | H9: {"support": "ok", "def": {"nom": "Canal+ Foot", "sources": [{"site": "canalplus.com", "site_id": "#19", "lang": "fr", "xmltv_id": "CPFOOT", "nom": "Canal+ Foot", "ordre": 2}, {"site": "tv.sfr.fr", "site_id": "3501", "lang": "fr", "xmltv_id": "CPFOOT_S", "nom": "Canal+ Foot", "ordre": 56}, {"site": "epgshare01.online", "site_id": "FR1#Canal+.Foot.fr", "lang": "fr", "xmltv_id": "CPFOOT_E", "nom": "Canal+ Foot", "ordre": 82}]}}
A10: tv:canal-sport-360 | B10: Canal+ | C10: Canal+ Sport 360 | D10: canalplus.com, tv.sfr.fr, epgshare01.online | E10: Oui | H10: {"support": "ok", "def": {"nom": "Canal+ Sport 360", "sources": [{"site": "canalplus.com", "site_id": "#83", "lang": "fr", "xmltv_id": "CP360", "nom": "Canal+ Sport 360", "ordre": 3}, {"site": "tv.sfr.fr", "site_id": "3504", "lang": "fr", "xmltv_id": "CP360_S", "nom": "Canal+ Sport 360", "ordre": 57}, {"site": "epgshare01.online", "site_id": "FR1#Canal+.Sport.360.fr", "lang": "fr", "xmltv_id": "CP360_E", "nom": "Canal+ Sport 360", "ordre": 83}]}}
A11: tv:canal-live-1 | B11: Canal+ | C11: Canal+ Live 1 | D11: canalplus.com, tv.sfr.fr | E11: Oui | H11: {"support": "ok", "def": {"nom": "Canal+ Live 1", "sources": [{"site": "canalplus.com", "site_id": "#1135", "lang": "fr", "xmltv_id": "CPLIVE1", "nom": "Canal+ Live 1", "ordre": 4}, {"site": "tv.sfr.fr", "site_id": "4068", "lang": "fr", "xmltv_id": "CPLIVE1_S", "nom": "Canal+ Live 1", "ordre": 58}]}}
A12: tv:canal-live-2 | B12: Canal+ | C12: Canal+ Live 2 | D12: canalplus.com, tv.sfr.fr | E12: Oui | H12: {"support": "ok", "def": {"nom": "Canal+ Live 2", "sources": [{"site": "canalplus.com", "site_id": "#1136", "lang": "fr", "xmltv_id": "CPLIVE2", "nom": "Canal+ Live 2", "ordre": 5}, {"site": "tv.sfr.fr", "site_id": "4069", "lang": "fr", "xmltv_id": "CPLIVE2_S", "nom": "Canal+ Live 2", "ordre": 59}]}}
A13: tv:canal-live-3 | B13: Canal+ | C13: Canal+ Live 3 | D13: canalplus.com, tv.sfr.fr | E13: Oui | H13: {"support": "ok", "def": {"nom": "Canal+ Live 3", "sources": [{"site": "canalplus.com", "site_id": "#1137", "lang": "fr", "xmltv_id": "CPLIVE3", "nom": "Canal+ Live 3", "ordre": 6}, {"site": "tv.sfr.fr", "site_id": "4070", "lang": "fr", "xmltv_id": "CPLIVE3_S", "nom": "Canal+ Live 3", "ordre": 60}]}}
A14: tv:canal-live-4 | B14: Canal+ | C14: Canal+ Live 4 | D14: canalplus.com, tv.sfr.fr | E14: Oui | H14: {"support": "ok", "def": {"nom": "Canal+ Live 4", "sources": [{"site": "canalplus.com", "site_id": "#1138", "lang": "fr", "xmltv_id": "CPLIVE4", "nom": "Canal+ Live 4", "ordre": 7}, {"site": "tv.sfr.fr", "site_id": "4071", "lang": "fr", "xmltv_id": "CPLIVE4_S", "nom": "Canal+ Live 4", "ordre": 61}]}}
A15: tv:canal-live-5 | B15: Canal+ | C15: Canal+ Live 5 | D15: canalplus.com, tv.sfr.fr | E15: Oui | H15: {"support": "ok", "def": {"nom": "Canal+ Live 5", "sources": [{"site": "canalplus.com", "site_id": "#1139", "lang": "fr", "xmltv_id": "CPLIVE5", "nom": "Canal+ Live 5", "ordre": 8}, {"site": "tv.sfr.fr", "site_id": "4072", "lang": "fr", "xmltv_id": "CPLIVE5_S", "nom": "Canal+ Live 5", "ordre": 62}]}}
A16: tv:canal-live-6 | B16: Canal+ | C16: Canal+ Live 6 | D16: canalplus.com, tv.sfr.fr | E16: Oui | H16: {"support": "ok", "def": {"nom": "Canal+ Live 6", "sources": [{"site": "canalplus.com", "site_id": "#1140", "lang": "fr", "xmltv_id": "CPLIVE6", "nom": "Canal+ Live 6", "ordre": 9}, {"site": "tv.sfr.fr", "site_id": "4073", "lang": "fr", "xmltv_id": "CPLIVE6_S", "nom": "Canal+ Live 6", "ordre": 63}]}}
A17: tv:canal-live-7 | B17: Canal+ | C17: Canal+ Live 7 | D17: canalplus.com, tv.sfr.fr | E17: Oui | H17: {"support": "ok", "def": {"nom": "Canal+ Live 7", "sources": [{"site": "canalplus.com", "site_id": "#1141", "lang": "fr", "xmltv_id": "CPLIVE7", "nom": "Canal+ Live 7", "ordre": 10}, {"site": "tv.sfr.fr", "site_id": "4074", "lang": "fr", "xmltv_id": "CPLIVE7_S", "nom": "Canal+ Live 7", "ordre": 64}]}}
A18: tv:canal-live-8 | B18: Canal+ | C18: Canal+ Live 8 | D18: canalplus.com | E18: Oui | H18: {"support": "ok", "def": {"nom": "Canal+ Live 8", "sources": [{"site": "canalplus.com", "site_id": "#1142", "lang": "fr", "xmltv_id": "CPLIVE8", "nom": "Canal+ Live 8", "ordre": 11}]}}
... A32: tv:canal-top-14 | B32: Canal+ | C32: Canal+ Top 14 | D32: epgshare01.online | E32: Oui | H32: {"support": "ok", "def": {"nom": "Canal+ Top 14", "sources": [{"site": "epgshare01.online", "site_id": "FR1#CANAL+.TOP14.fr", "lang": "fr", "xmltv_id": "CPTOP14_E", "nom": "Canal+ Top 14", "ordre": 86}]}}
A33: sec:tv:bein | B33: beIN Sports | C33: ▸ toute la section | H33: {"id": "bein", "label": "beIN Sports"}
A34: tv:bein-sports-1 | B34: beIN Sports | C34: beIN Sports 1 | D34: chaines-tv.orange.fr, tv.sfr.fr, beinsports.com | E34: Oui | H34: {"support": "ok", "def": {"nom": "beIN Sports 1", "sources": [{"site": "chaines-tv.orange.fr", "site_id": "1290", "lang": "fr", "xmltv_id": "BEIN1", "nom": "beIN Sports 1", "ordre": 33}, {"site": "tv.sfr.fr", "site_id": "1290", "lang": "fr", "xmltv_id": "BEIN1_S", "nom": "beIN Sports 1", "ordre": 71}, {"site": "beinsports.com", "site_id": "66265DD1-D2AA-4A89-9412-2455186E90ED", "lang": "fr", "xmltv_id": "BEIN1_W", "nom": "beIN Sports 1", "ordre": 89}]}}
A35: tv:bein-sports-2 | B35: beIN Sports | C35: beIN Sports 2 | D35: chaines-tv.orange.fr, tv.sfr.fr, beinsports.com | E35: Oui | H35: {"support": "ok", "def": {"nom": "beIN Sports 2", "sources": [{"site": "chaines-tv.orange.fr", "site_id": "1304", "lang": "fr", "xmltv_id": "BEIN2", "nom": "beIN Sports 2", "ordre": 34}, {"site": "tv.sfr.fr", "site_id": "1304", "lang": "fr", "xmltv_id": "BEIN2_S", "nom": "beIN Sports 2", "ordre": 72}, {"site": "beinsports.com", "site_id": "1E886E98-3104-4D8E-A97F-734B23108E8A", "lang": "fr", "xmltv_id": "BEIN2_W", "nom": "beIN Sports 2", "ordre": 90}]}}
A36: tv:bein-sports-3 | B36: beIN Sports | C36: beIN Sports 3 | D36: chaines-tv.orange.fr, tv.sfr.fr, beinsports.com | E36: Oui | H36: {"support": "ok", "def": {"nom": "beIN Sports 3", "sources": [{"site": "chaines-tv.orange.fr", "site_id": "1335", "lang": "fr", "xmltv_id": "BEIN3", "nom": "beIN Sports 3", "ordre": 35}, {"site": "tv.sfr.fr", "site_id": "1335", "lang": "fr", "xmltv_id": "BEIN3_S", "nom": "beIN Sports 3", "ordre": 73}, {"site": "beinsports.com", "site_id": "6DB008B8-66DA-423E-805D-616211D4B174", "lang": "fr", "xmltv_id": "BEIN3_W", "nom": "beIN Sports 3", "ordre": 91}]}}
A37: tv:bein-sports-max-4 | B37: beIN Sports | C37: beIN Sports Max 4 | D37: chaines-tv.orange.fr, tv.sfr.fr, beinsports.com | E37: Oui | H37: {"support": "ok", "def": {"nom": "beIN Sports Max 4", "sources": [{"site": "chaines-tv.orange.fr", "site_id": "1336", "lang": "fr", "xmltv_id": "BEINMAX4", "nom": "beIN Sports Max 4", "ordre": 36}, {"site": "tv.sfr.fr", "site_id": "1336", "lang": "fr", "xmltv_id": "BEINMAX4_S", "nom": "beIN Sports Max 4", "ordre": 74}, {"site": "beinsports.com", "site_id": "EF7E0369-CFD9-4607-9238-EC483E6D58A3", "lang": "fr", "xmltv_id": "BEINMAX4_W", "nom": "beIN Sports Max 4", "ordre": 92}]}}
A38: tv:bein-sports-max-5 | B38: beIN Sports | C38: beIN Sports Max 5 | D38: chaines-tv.orange.fr, tv.sfr.fr, beinsports.com | E38: Oui | H38: {"support": "ok", "def": {"nom": "beIN Sports Max 5", "sources": [{"site": "chaines-tv.orange.fr", "site_id": "1337", "lang": "fr", "xmltv_id": "BEINMAX5", "nom": "beIN Sports Max 5", "ordre": 37}, {"site": "tv.sfr.fr", "site_id": "1337", "lang": "fr", "xmltv_id": "BEINMAX5_S", "nom": "beIN Sports Max 5", "ordre": 75}, {"site": "beinsports.com", "site_id": "A4425E44-B004-4137-ACB4-458BA4D710F8", "lang": "fr", "xmltv_id": "BEINMAX5_W", "nom": "beIN Sports Max 5", "ordre": 93}]}}
A39: tv:bein-sports-max-6 | B39: beIN Sports | C39: beIN Sports Max 6 | D39: chaines-tv.orange.fr, tv.sfr.fr, beinsports.com | E39: Oui | H39: {"support": "ok", "def": {"nom": "beIN Sports Max 6", "sources": [{"site": "chaines-tv.orange.fr", "site_id": "1338", "lang": "fr", "xmltv_id": "BEINMAX6", "nom": "beIN Sports Max 6", "ordre": 38}, {"site": "tv.sfr.fr", "site_id": "1338", "lang": "fr", "xmltv_id": "BEINMAX6_S", "nom": "beIN Sports Max 6", "ordre": 76}, {"site": "beinsports.com", "site_id": "BBD26D71-897D-4799-87A1-A87120130D48", "lang": "fr", "xmltv_id": "BEINMAX6_W", "nom": "beIN Sports Max 6", "ordre": 94}]}}
A40: tv:bein-sports-max-7 | B40: beIN Sports | C40: beIN Sports Max 7 | D40: chaines-tv.orange.fr, tv.sfr.fr, beinsports.com | E40: Oui | H40: {"support": "ok", "def": {"nom": "beIN Sports Max 7", "sources": [{"site": "chaines-tv.orange.fr", "site_id": "1339", "lang": "fr", "xmltv_id": "BEINMAX7", "nom": "beIN Sports Max 7", "ordre": 39}, {"site": "tv.sfr.fr", "site_id": "1339", "lang": "fr", "xmltv_id": "BEINMAX7_S", "nom": "beIN Sports Max 7", "ordre": 77}, {"site": "beinsports.com", "site_id": "9B4708C5-F5F0-452A-8157-4661C30FAE6A", "lang": "fr", "xmltv_id": "BEINMAX7_W", "nom": "beIN Sports Max 7", "ordre": 95}]}}
A41: tv:bein-sports-max-8 | B41: beIN Sports | C41: beIN Sports Max 8 | D41: chaines-tv.orange.fr, tv.sfr.fr, beinsports.com | E41: Oui | H41: {"support": "ok", "def": {"nom": "beIN Sports Max 8", "sources": [{"site": "chaines-tv.orange.fr", "site_id": "1340", "lang": "fr", "xmltv_id": "BEINMAX8", "nom": "beIN Sports Max 8", "ordre": 40}, {"site": "tv.sfr.fr", "site_id": "1340", "lang": "fr", "xmltv_id": "BEINMAX8_S", "nom": "beIN Sports Max 8", "ordre": 78}, {"site": "beinsports.com", "site_id": "76D2430C-8BCB-41BD-A1DE-FBA0D58C5E8A", "lang": "fr", "xmltv_id": "BEINMAX8_W", "nom": "beIN Sports Max 8", "ordre": 96}]}}
A42: tv:bein-sports-max-9 | B42: beIN Sports | C42: beIN Sports Max 9 | D42: chaines-tv.orange.fr, tv.sfr.fr, beinsports.com | E42: Oui | H42: {"support": "ok", "def": {"nom": "beIN Sports Max 9", "sources": [{"site": "chaines-tv.orange.fr", "site_id": "1341", "lang": "fr", "xmltv_id": "BEINMAX9", "nom": "beIN Sports Max 9", "ordre": 41}, {"site": "tv.sfr.fr", "site_id": "1341", "lang": "fr", "xmltv_id": "BEINMAX9_S", "nom": "beIN Sports Max 9", "ordre": 79}, {"site": "beinsports.com", "site_id": "FB208953-1C70-4D1E-B918-103AB02AB181", "lang": "fr", "xmltv_id": "BEINMAX9_W", "nom": "beIN Sports Max 9", "ordre": 97}]}}
A43: tv:bein-sports-max-10 | B43: beIN Sports | C43: beIN Sports Max 10 | D43: chaines-tv.orange.fr, tv.sfr.fr, beinsports.com | E43: Oui | H43: {"support": "ok", "def": {"nom": "beIN Sports Max 10", "sources": [{"site": "chaines-tv.orange.fr", "site_id": "1342", "lang": "fr", "xmltv_id": "BEINMAX10", "nom": "beIN Sports Max 10", "ordre": 42}, {"site": "tv.sfr.fr", "site_id": "1342", "lang": "fr", "xmltv_id": "BEINMAX10_S", "nom": "beIN Sports Max 10", "ordre": 80}, {"site": "beinsports.com", "site_id": "6F425028-14F0-4E38-B776-71A9DB3F3493", "lang": "fr", "xmltv_id": "BEINMAX10_W", "nom": "beIN Sports Max 10", "ordre": 98}]}}
A44: sec:tv:dazn | B44: DAZN | C44: ▸ toute la section | H44: {"id": "dazn", "label": "DAZN"}
A45: tv:dazn-1 | B45: DAZN | C45: DAZN 1 | D45: canalplus.com, tv.sfr.fr, epgshare01.online | E45: Oui | H45: {"support": "ok", "def": {"nom": "DAZN 1", "sources": [{"site": "canalplus.com", "site_id": "#1077", "lang": "fr", "xmltv_id": "DAZN1", "nom": "DAZN 1", "ordre": 23}, {"site": "tv.sfr.fr", "site_id": "3795", "lang": "fr", "xmltv_id": "DAZN1_S", "nom": "DAZN 1", "ordre": 65}, {"site": "epgshare01.online", "site_id": "FR1#DAZN.1.fr", "lang": "fr", "xmltv_id": "DAZN1_E", "nom": "DAZN 1", "ordre": 87}]}}
A46: tv:dazn-2 | B46: DAZN | C46: DAZN 2 | D46: canalplus.com | E46: Oui | H46: {"support": "ok", "def": {"nom": "DAZN 2", "sources": [{"site": "canalplus.com", "site_id": "#1155", "lang": "fr", "xmltv_id": "DAZN2", "nom": "DAZN 2", "ordre": 24}]}}
A47: tv:dazn-3 | B47: DAZN | C47: DAZN 3 | D47: canalplus.com | E47: Oui | H47: {"support": "ok", "def": {"nom": "DAZN 3", "sources": [{"site": "canalplus.com", "site_id": "#1156", "lang": "fr", "xmltv_id": "DAZN3", "nom": "DAZN 3", "ordre": 25}]}}
A48: tv:dazn-4 | B48: DAZN | C48: DAZN 4 | D48: canalplus.com | E48: Oui | H48: {"support": "ok", "def": {"nom": "DAZN 4", "sources": [{"site": "canalplus.com", "site_id": "#1157", "lang": "fr", "xmltv_id": "DAZN4", "nom": "DAZN 4", "ordre": 26}]}}
A49: tv:dazn-5 | B49: DAZN | C49: DAZN 5 | D49: canalplus.com | E49: Oui | H49: {"support": "ok", "def": {"nom": "DAZN 5", "sources": [{"site": "canalplus.com", "site_id": "#1158", "lang": "fr", "xmltv_id": "DAZN5", "nom": "DAZN 5", "ordre": 27}]}}
A50: sec:tv:l1 | B50: Ligue 1+ | C50: ▸ toute la section | H50: {"id": "l1", "label": "Ligue 1+"}
A51: tv:ligue-1 | B51: Ligue 1+ | C51: Ligue 1+ | D51: chaines-tv.orange.fr | E51: Oui | H51: {"support": "ok", "def": {"nom": "Ligue 1+", "sources": [{"site": "chaines-tv.orange.fr", "site_id": "4210", "lang": "fr", "xmltv_id": "L1P1", "nom": "Ligue 1+", "ordre": 43}]}}
A52: tv:ligue-1-2 | B52: Ligue 1+ | C52: Ligue 1+ 2 | D52: chaines-tv.orange.fr | E52: Oui | H52: {"support": "ok", "def": {"nom": "Ligue 1+ 2", "sources": [{"site": "chaines-tv.orange.fr", "site_id": "4211", "lang": "fr", "xmltv_id": "L1P2", "nom": "Ligue 1+ 2", "ordre": 44}]}}
A53: tv:ligue-1-3 | B53: Ligue 1+ | C53: Ligue 1+ 3 | D53: chaines-tv.orange.fr, canalplus.com | E53: Oui | H53: {"support": "ok", "def": {"nom": "Ligue 1+ 3", "sources": [{"site": "chaines-tv.orange.fr", "site_id": "4212", "lang": "fr", "xmltv_id": "L1P3", "nom": "Ligue 1+ 3", "ordre": 45}, {"site": "canalplus.com", "site_id": "#1174", "lang": "fr", "xmltv_id": "L1P3_W", "nom": "Ligue 1+ 3", "ordre": 53}]}}
A54: tv:ligue-1-4 | B54: Ligue 1+ | C54: Ligue 1+ 4 | D54: chaines-tv.orange.fr, canalplus.com | E54: Oui | H54: {"support": "ok", "def": {"nom": "Ligue 1+ 4", "sources": [{"site": "chaines-tv.orange.fr", "site_id": "4213", "lang": "fr", "xmltv_id": "L1P4", "nom": "Ligue 1+ 4", "ordre": 46}, {"site": "canalplus.com", "site_id": "#1179", "lang": "fr", "xmltv_id": "L1P4_W", "nom": "Ligue 1+ 4", "ordre": 54}]}}
A55: tv:ligue-1-5 | B55: Ligue 1+ | C55: Ligue 1+ 5 | D55: chaines-tv.orange.fr, canalplus.com | E55: Oui | H55: {"support": "ok", "def": {"nom": "Ligue 1+ 5", "sources": [{"site": "chaines-tv.orange.fr", "site_id": "4214", "lang": "fr", "xmltv_id": "L1P5", "nom": "Ligue 1+ 5", "ordre": 47}, {"site": "canalplus.com", "site_id": "#1180", "lang": "fr", "xmltv_id": "L1P5_W", "nom": "Ligue 1+ 5", "ordre": 55}]}}
A56: tv:ligue-1-6 | B56: Ligue 1+ | C56: Ligue 1+ 6 | D56: chaines-tv.orange.fr | E56: Oui | H56: {"support": "ok", "def": {"nom": "Ligue 1+ 6", "sources": [{"site": "chaines-tv.orange.fr", "site_id": "4219", "lang": "fr", "xmltv_id": "L1P6", "nom": "Ligue 1+ 6", "ordre": 48}]}}
A57: tv:ligue-1-7 | B57: Ligue 1+ | C57: Ligue 1+ 7 | D57: chaines-tv.orange.fr | E57: Oui | H57: {"support": "ok", "def": {"nom": "Ligue 1+ 7", "sources": [{"site": "chaines-tv.orange.fr", "site_id": "4220", "lang": "fr", "xmltv_id": "L1P7", "nom": "Ligue 1+ 7", "ordre": 49}]}}
A58: tv:ligue-1-8 | B58: Ligue 1+ | C58: Ligue 1+ 8 | D58: chaines-tv.orange.fr | E58: Oui | H58: {"support": "ok", "def": {"nom": "Ligue 1+ 8", "sources": [{"site": "chaines-tv.orange.fr", "site_id": "4221", "lang": "fr", "xmltv_id": "L1P8", "nom": "Ligue 1+ 8", "ordre": 50}]}}
A59: tv:ligue-1-9 | B59: Ligue 1+ | C59: Ligue 1+ 9 | D59: chaines-tv.orange.fr | E59: Oui | H59: {"support": "ok", "def": {"nom": "Ligue 1+ 9", "sources": [{"site": "chaines-tv.orange.fr", "site_id": "4222", "lang": "fr", "xmltv_id": "L1P9", "nom": "Ligue 1+ 9", "ordre": 51}]}}
A60: sec:tv:autres | B60: Autres chaînes sport | C60: ▸ toute la section | H60: {"id": "autres", "label": "Autres chaînes sport"}
A61: tv:eurosport-1 | B61: Autres chaînes sport | C61: Eurosport 1 | D61: canalplus.com, tv.sfr.fr | E61: Oui | H61: {"support": "ok", "def": {"nom": "Eurosport 1", "sources": [{"site": "canalplus.com", "site_id": "#101", "lang": "fr", "xmltv_id": "EUROSPORT1", "nom": "Eurosport 1", "ordre": 28}, {"site": "tv.sfr.fr", "site_id": "76", "lang": "fr", "xmltv_id": "EUROSPORT1_S", "nom": "Eurosport 1", "ordre": 68}]}}
A62: tv:eurosport-2 | B62: Autres chaînes sport | C62: Eurosport 2 | D62: canalplus.com, tv.sfr.fr | E62: Oui | H62: {"support": "ok", "def": {"nom": "Eurosport 2", "sources": [{"site": "canalplus.com", "site_id": "#436", "lang": "fr", "xmltv_id": "EUROSPORT2", "nom": "Eurosport 2", "ordre": 29}, {"site": "tv.sfr.fr", "site_id": "439", "lang": "fr", "xmltv_id": "EUROSPORT2_S", "nom": "Eurosport 2", "ordre": 69}]}}
A63: tv:rmc-sport-1 | B63: Autres chaînes sport | C63: RMC Sport 1 | D63: canalplus.com, tv.sfr.fr, epgshare01.online | E63: Oui | H63: {"support": "ok", "def": {"nom": "RMC Sport 1", "sources": [{"site": "canalplus.com", "site_id": "#732", "lang": "fr", "xmltv_id": "RMC1", "nom": "RMC Sport 1", "ordre": 31}, {"site": "tv.sfr.fr", "site_id": "2665", "lang": "fr", "xmltv_id": "RMC1_S", "nom": "RMC Sport 1", "ordre": 66}, {"site": "epgshare01.online", "site_id": "FR1#RMC.Sport.1.fr", "lang": "fr", "xmltv_id": "RMC1_E", "nom": "RMC Sport 1", "ordre": 88}]}}
A64: tv:rmc-sport-2 | B64: Autres chaînes sport | C64: RMC Sport 2 | D64: canalplus.com, tv.sfr.fr | E64: Oui | H64: {"support": "ok", "def": {"nom": "RMC Sport 2", "sources": [{"site": "canalplus.com", "site_id": "#733", "lang": "fr", "xmltv_id": "RMC2", "nom": "RMC Sport 2", "ordre": 32}, {"site": "tv.sfr.fr", "site_id": "2666", "lang": "fr", "xmltv_id": "RMC2_S", "nom": "RMC Sport 2", "ordre": 67}]}}
A65: tv:la-chaine-l-equipe | B65: Autres chaînes sport | C65: La chaîne L'Équipe | D65: chaines-tv.orange.fr, tv.sfr.fr | E65: Oui | H65: {"support": "ok", "def": {"nom": "La chaîne L'Équipe", "sources": [{"site": "chaines-tv.orange.fr", "site_id": "1401", "lang": "fr", "xmltv_id": "EQUIPE", "nom": "La chaîne L'Équipe", "ordre": 52}, {"site": "tv.sfr.fr", "site_id": "1401", "lang": "fr", "xmltv_id": "EQUIPE_S", "nom": "La chaîne L'Équipe", "ordre": 70}]}}
A66: sec:tv:gratuites | B66: Chaînes gratuites et autres | C66: ▸ toute la section | H66: {"id": "gratuites", "label": "Chaînes gratuites et autres"}
A67: tv:tf1 | B67: Chaînes gratuites et autres | C67: TF1 | D67: à trouver par la tâche | F67: à vérifier | G67: Matchs des Bleus, Coupe du monde de rugby | H67: {"support": "ok", "def": {"nom": "TF1", "sources": []}}
A68: tv:france-2 | B68: Chaînes gratuites et autres | C68: France 2 | D68: à trouver par la tâche | F68: à vérifier | G68: Six Nations, Roland-Garros, Tour de France | H68: {"support": "ok", "def": {"nom": "France 2", "sources": []}}
A69: tv:france-3 | B69: Chaînes gratuites et autres | C69: France 3 | D69: à trouver par la tâche | F69: à vérifier | G69: Tour de France, régions | H69: {"support": "ok", "def": {"nom": "France 3", "sources": []}}
A70: tv:france-4 | B70: Chaînes gratuites et autres | C70: France 4 | D70: à trouver par la tâche | F70: à vérifier | G70: Événements sportifs | H70: {"support": "ok", "def": {"nom": "France 4", "sources": []}}
A71: tv:m6 | B71: Chaînes gratuites et autres | C71: M6 | D71: à trouver par la tâche | F71: à vérifier | G71: Coupe du monde, Euro | H71: {"support": "ok", "def": {"nom": "M6", "sources": []}}
A72: tv:w9 | B72: Chaînes gratuites et autres | C72: W9 | D72: à trouver par la tâche | F72: à vérifier | G72: Football ponctuel | H72: {"support": "ok", "def": {"nom": "W9", "sources": []}}
A73: tv:tmc | B73: Chaînes gratuites et autres | C73: TMC | D73: à trouver par la tâche | F73: à vérifier | G73: Sport ponctuel | H73: {"support": "ok", "def": {"nom": "TMC", "sources": []}}
A74: tv:tfx | B74: Chaînes gratuites et autres | C74: TFX | D74: à trouver par la tâche | F74: à vérifier | G74: Sport ponctuel | H74: {"support": "ok", "def": {"nom": "TFX", "sources": []}}
A75: tv:sport-en-france | B75: Chaînes gratuites et autres | C75: Sport en France | D75: à trouver par la tâche | F75: à vérifier | G75: Sports olympiques, féminins | H75: {"support": "ok", "def": {"nom": "Sport en France", "sources": []}}
A76: tv:automoto-la-chaine | B76: Chaînes gratuites et autres | C76: Automoto La Chaîne | D76: à trouver par la tâche | F76: à vérifier | G76: Sports mécaniques | H76: {"support": "ok", "def": {"nom": "Automoto La Chaîne", "sources": []}}
A77: tv:equidia | B77: Chaînes gratuites et autres | C77: Equidia | D77: à trouver par la tâche | F77: à vérifier | G77: Courses hippiques | H77: {"support": "ok", "def": {"nom": "Equidia", "sources": []}}
A78: tv:golf | B78: Chaînes gratuites et autres | C78: Golf+ | D78: à trouver par la tâche | F78: à vérifier | G78: Golf (Canal+) | H78: {"support": "ok", "def": {"nom": "Golf+", "sources": []}}
A79: tv:eurosport-360-multiplex | B79: Chaînes gratuites et autres | C79: Eurosport 360 (multiplex) | D79: à trouver par la tâche | F79: à vérifier | G79: Tennis, cyclisme | H79: {"support": "ok", "def": {"nom": "Eurosport 360 (multiplex)", "sources": []}}
A80: tv:bein-sports-max-11 | B80: Chaînes gratuites et autres | C80: beIN Sports Max 11 | D80: à trouver par la tâche | F80: à vérifier | H80: {"support": "ok", "def": {"nom": "beIN Sports Max 11", "sources": []}}
A81: tv:ligue-1-10 | B81: Chaînes gratuites et autres | C81: Ligue 1+ 10 | D81: à trouver par la tâche | F81: à vérifier | H81: {"support": "ok", "def": {"nom": "Ligue 1+ 10", "sources": []}}
A82: tv:canal-docs | B82: Chaînes gratuites et autres | C82: Canal+ Docs | D82: à trouver par la tâche | F82: à vérifier | G82: Documentaires | H82: {"support": "ok", "def": {"nom": "Canal+ Docs", "sources": []}}
A83: tv:arte | B83: Chaînes gratuites et autres | C83: Arte | D83: à trouver par la tâche | F83: à vérifier | H83: {"support": "ok", "def": {"nom": "Arte", "sources": []}}
B86: MES AJOUTS — tape ce que tu veux ajouter : la tâche essaie de le récupérer et écrit le résultat (✅ / ⚠️ / ❌) dans la colonne « Résultat »
B87: Bouquet | C87: Nom de la chaîne | D87: Nom exact dans le guide TV si connu | E87: Oui | F87: Résultat | G87: Note
A88: exemple | B88: Canal+ | C88: Sport en France | E88: Oui | G88: Ligne d'exemple : ignorée par la tâche
A89: ajout:1
A90: ajout:2
A91: ajout:3
A92: ajout:4
A93: ajout:5
A94: ajout:6
A95: ajout:7
A96: ajout:8
A97: ajout:9
A98: ajout:10
A99: ajout:11
A100: ajout:12
... A108: ajout:20

Sheet Cotes
A1: module=cotes;version=2 | B1: Cotes des matchs · sites et compétitions
B2: Relevés automatiques (le matin, 15 min avant, à la mi-temps) avec la clé gratuite The Odds API (500 crédits par mois). Chaque compétition ajoutée consomme des crédits : vérifie la jauge dans État. Moins de 10 sites = 1 crédit par relevé.
B3: À remplir : cases jaunes (« Oui » ou « Non »). Ligne « ▸ toute la section » = tous ses éléments, sauf ceux marqués « Non ». Un seul élément coché suffit pour que sa section apparaisse. Colonne « Résultat » : remplie par la tâche GitHub après dépôt du classeur.
A5: ID | B5: Section | C5: Nom | D5: Clé The Odds API | E5: Détail | F5: Oui | G5: Résultat | H5: Note | I5: Technique
A6: sec:cotes:sites | B6: Sites de paris | C6: ▸ toute la section | I6: {"id": "sites", "label": "Sites de paris"}
A7: cs:winamax_fr | B7: Sites de paris | C7: Winamax | D7: winamax_fr | F7: Oui | I7: {"support": "ok", "def": "winamax_fr"}
A8: cs:betclic_fr | B8: Sites de paris | C8: Betclic | D8: betclic_fr | F8: Oui | I8: {"support": "ok", "def": "betclic_fr"}
A9: cs:unibet_fr | B9: Sites de paris | C9: Unibet | D9: unibet_fr | F9: Oui | I9: {"support": "ok", "def": "unibet_fr"}
A10: cs:pmu_fr | B10: Sites de paris | C10: PMU | D10: pmu_fr | F10: Oui | I10: {"support": "ok", "def": "pmu_fr"}
A11: cs:netbet_fr | B11: Sites de paris | C11: NetBet | D11: netbet_fr | F11: Oui | I11: {"support": "ok", "def": "netbet_fr"}
A12: cs:parionssport_fr | B12: Sites de paris | C12: Parions Sport (FDJ) | D12: parionssport_fr | E12: à vérifier dans la région « fr » de l'API | G12: à vérifier | I12: {"support": "ok", "def": "parionssport_fr"}
A13: sec:cotes:compets | B13: Compétitions relevées | C13: ▸ toute la section | I13: {"id": "compets", "label": "Compétitions relevées"}
A14: cc:fra.1 | B14: Compétitions relevées | C14: Ligue 1 | D14: soccer_france_ligue_one | E14: fra.1 | F14: Oui | I14: {"support": "ok", "def": {"id": "fra.1", "cle": "soccer_france_ligue_one", "re": {"re": "ligue 1", "flags": "i"}}}
A15: cc:eng.1 | B15: Compétitions relevées | C15: Premier League | D15: soccer_epl | E15: eng.1 | F15: Oui | I15: {"support": "ok", "def": {"id": "eng.1", "cle": "soccer_epl", "re": {"re": "^epl$|premier league", "flags": "i"}}}
A16: cc:esp.1 | B16: Compétitions relevées | C16: Liga | D16: soccer_spain_la_liga | E16: esp.1 | F16: Oui | I16: {"support": "ok", "def": {"id": "esp.1", "cle": "soccer_spain_la_liga", "re": {"re": "la ?liga", "flags": "i"}}}
A17: cc:ita.1 | B17: Compétitions relevées | C17: Serie A | D17: soccer_italy_serie_a | E17: ita.1 | F17: Oui | I17: {"support": "ok", "def": {"id": "ita.1", "cle": "soccer_italy_serie_a", "re": {"re": "serie a", "flags": "i"}}}
A18: cc:ger.1 | B18: Compétitions relevées | C18: Bundesliga | D18: soccer_germany_bundesliga | E18: ger.1 | F18: Oui | I18: {"support": "ok", "def": {"id": "ger.1", "cle": "soccer_germany_bundesliga", "re": {"re": "^bundesliga(?! 2)", "flags": "i"}}}
A19: cc:uefa.champions | B19: Compétitions relevées | C19: Ligue des champions | D19: soccer_uefa_champs_league | E19: uefa.champions | F19: Oui | I19: {"support": "ok", "def": {"id": "uefa.champions", "cle": "soccer_uefa_champs_league", "re": {"re": "champions league(?!.*qualif)", "flags": "i"}}}
A20: cc:uefa.europa | B20: Compétitions relevées | C20: Ligue Europa | D20: soccer_uefa_europa_league | E20: uefa.europa | F20: Oui | I20: {"support": "ok", "def": {"id": "uefa.europa", "cle": "soccer_uefa_europa_league", "re": {"re": "europa league", "flags": "i"}}}
A21: cc:uefa.europa.conf | B21: Compétitions relevées | C21: Ligue Conférence | D21: soccer_uefa_europa_conference_league | E21: uefa.europa.conf | F21: Oui | I21: {"support": "ok", "def": {"id": "uefa.europa.conf", "cle": "soccer_uefa_europa_conference_league", "re": {"re": "conference league", "flags": "i"}}}
A22: cc:fra.2 | B22: Compétitions relevées | C22: Ligue 2 | D22: soccer_france_ligue_two | E22: fra.2 | G22: à vérifier | I22: {"support": "ok", "def": {"id": "fra.2", "cle": "soccer_france_ligue_two", "re": {"re": "Ligue 2", "flags": "i"}}}
A23: cc:eng.2 | B23: Compétitions relevées | C23: Championship | D23: soccer_efl_champ | E23: eng.2 | G23: à vérifier | I23: {"support": "ok", "def": {"id": "eng.2", "cle": "soccer_efl_champ", "re": {"re": "Championship", "flags": "i"}}}
A24: cc:ger.2 | B24: Compétitions relevées | C24: 2. Bundesliga | D24: soccer_germany_bundesliga2 | E24: ger.2 | G24: à vérifier | I24: {"support": "ok", "def": {"id": "ger.2", "cle": "soccer_germany_bundesliga2", "re": {"re": "2\\. Bundesliga", "flags": "i"}}}
A25: cc:ita.2 | B25: Compétitions relevées | C25: Serie B | D25: soccer_italy_serie_b | E25: ita.2 | G25: à vérifier | I25: {"support": "ok", "def": {"id": "ita.2", "cle": "soccer_italy_serie_b", "re": {"re": "Serie B", "flags": "i"}}}
A26: cc:esp.2 | B26: Compétitions relevées | C26: Liga 2 | D26: soccer_spain_segunda_division | E26: esp.2 | G26: à vérifier | I26: {"support": "ok", "def": {"id": "esp.2", "cle": "soccer_spain_segunda_division", "re": {"re": "Liga 2", "flags": "i"}}}
A27: cc:ned.1 | B27: Compétitions relevées | C27: Eredivisie | D27: soccer_netherlands_eredivisie | E27: ned.1 | G27: à vérifier | I27: {"support": "ok", "def": {"id": "ned.1", "cle": "soccer_netherlands_eredivisie", "re": {"re": "Eredivisie", "flags": "i"}}}
A28: cc:por.1 | B28: Compétitions relevées | C28: Liga Portugal | D28: soccer_portugal_primeira_liga | E28: por.1 | G28: à vérifier | I28: {"support": "ok", "def": {"id": "por.1", "cle": "soccer_portugal_primeira_liga", "re": {"re": "Liga Portugal", "flags": "i"}}}
A29: cc:eng.fa | B29: Compétitions relevées | C29: FA Cup | D29: soccer_fa_cup | E29: eng.fa | G29: à vérifier | I29: {"support": "ok", "def": {"id": "eng.fa", "cle": "soccer_fa_cup", "re": {"re": "FA Cup", "flags": "i"}}}
A30: cc:fra.coupe_de_france | B30: Compétitions relevées | C30: Coupe de France | D30: soccer_france_coupe_de_france | E30: fra.coupe_de_france | G30: à vérifier | I30: {"support": "ok", "def": {"id": "fra.coupe_de_france", "cle": "soccer_france_coupe_de_france", "re": {"re": "Coupe de France", "flags": "i"}}}
A31: cc:fifa.world | B31: Compétitions relevées | C31: Coupe du monde | D31: soccer_fifa_world_cup | E31: fifa.world | G31: à vérifier | I31: {"support": "ok", "def": {"id": "fifa.world", "cle": "soccer_fifa_world_cup", "re": {"re": "Coupe du monde", "flags": "i"}}}
A32: cc:uefa.euro | B32: Compétitions relevées | C32: Euro | D32: soccer_uefa_european_championship | E32: uefa.euro | G32: à vérifier | I32: {"support": "ok", "def": {"id": "uefa.euro", "cle": "soccer_uefa_european_championship", "re": {"re": "Euro", "flags": "i"}}}
A33: cc:uefa.nations | B33: Compétitions relevées | C33: Ligue des nations | D33: soccer_uefa_nations_league | E33: uefa.nations | G33: à vérifier | I33: {"support": "ok", "def": {"id": "uefa.nations", "cle": "soccer_uefa_nations_league", "re": {"re": "Ligue des nations", "flags": "i"}}}
... A40: cc:ufc | B40: Compétitions relevées | C40: MMA | D40: mma_mixed_martial_arts | E40: ufc | G40: à vérifier | I40: {"support": "ok", "def": {"id": "ufc", "cle": "mma_mixed_martial_arts", "re": {"re": "MMA", "flags": "i"}}}
A41: sec:cotes:rapport_seuil | B41: Rapport des écarts · seuil d'affichage (un seul) | C41: ▸ toute la section | I41: {"id": "rapport_seuil", "label": "Rapport des écarts · seuil d'affichage (un seul)"}
A42: cr:seuil:3 | B42: Rapport des écarts · seuil d'affichage (un seul) | C42: Écart d'au moins 3 % | I42: {"support": "ok", "def": 0.03}
A43: cr:seuil:5 | B43: Rapport des écarts · seuil d'affichage (un seul) | C43: Écart d'au moins 5 % | F43: Oui | I43: {"support": "ok", "def": 0.05}
A44: cr:seuil:8 | B44: Rapport des écarts · seuil d'affichage (un seul) | C44: Écart d'au moins 8 % | I44: {"support": "ok", "def": 0.08}
A45: cr:seuil:10 | B45: Rapport des écarts · seuil d'affichage (un seul) | C45: Écart d'au moins 10 % | I45: {"support": "ok", "def": 0.1}
A46: sec:cotes:rapport_ref | B46: Rapport des écarts · comparaison (une seule) | C46: ▸ toute la section | I46: {"id": "rapport_ref", "label": "Rapport des écarts · comparaison (une seule)"}
A47: cr:ref:moyenne | B47: Rapport des écarts · comparaison (une seule) | C47: Moyenne des autres sites | E47: la cote du site comparée à la moyenne des autres | F47: Oui | I47: {"support": "ok", "def": "moyenne"}
A48: cr:ref:mediane | B48: Rapport des écarts · comparaison (une seule) | C48: Médiane des autres sites | E48: moins sensible à un autre site lui-même décalé | I48: {"support": "ok", "def": "mediane"}
B51: MES AJOUTS — tape ce que tu veux ajouter : la tâche essaie de le récupérer et écrit le résultat (✅ / ⚠️ / ❌) dans la colonne « Résultat »
B52: Section (Sites de paris ou Compétitions relevées) | C52: Nom | D52: Clé The Odds API ou id de compétition du dock | F52: Oui | G52: Résultat | H52: Note
A53: exemple | B53: Sites de paris | C53: Ligue 2 | D53: fra.2 | F53: Oui | H53: Ligne d'exemple : ignorée par la tâche
A54: ajout:1
A55: ajout:2
A56: ajout:3
A57: ajout:4
A58: ajout:5
A59: ajout:6
A60: ajout:7
A61: ajout:8
A62: ajout:9
A63: ajout:10
A64: ajout:11
A65: ajout:12
... A73: ajout:20

Sheet Accueil
A1: module=accueil;version=2 | B1: Accueil · pages, widgets et météo
B2: Version minimale : le placement des applis, des dossiers et du dock se fera directement dans l'appli (phase 2). La première ville cochée est celle affichée par défaut.
B3: À remplir : cases jaunes (« Oui » ou « Non »). Ligne « ▸ toute la section » = tous ses éléments, sauf ceux marqués « Non ». Un seul élément coché suffit pour que sa section apparaisse. Colonne « Résultat » : remplie par la tâche GitHub après dépôt du classeur.
A5: ID | B5: Section | C5: Élément | D5: Détail | E5: Oui | F5: Résultat | G5: Note | H5: Technique
A6: sec:accueil:pages | B6: Pages de l'appli | C6: ▸ toute la section | H6: {"id": "pages", "label": "Pages de l'appli"}
A7: pg:actus | B7: Pages de l'appli | C7: Actus | E7: Oui | H7: {"support": "ok", "def": "actus"}
A8: pg:sport | B8: Pages de l'appli | C8: Sport | E8: Oui | H8: {"support": "ok", "def": "sport"}
A9: pg:videos | B9: Pages de l'appli | C9: Vidéos | E9: Oui | H9: {"support": "ok", "def": "videos"}
A10: pg:invest | B10: Pages de l'appli | C10: Investissements | E10: Oui | H10: {"support": "ok", "def": "invest"}
A11: pg:cachee | B11: Pages de l'appli | C11: Coffre (page cachée) | E11: Oui | H11: {"support": "ok", "def": "cachee"}
A12: pg:etat | B12: Pages de l'appli | C12: État des données | E12: Oui | H12: {"support": "ok", "def": "etat"}
A13: sec:accueil:widgets | B13: Widgets de l'écran d'accueil | C13: ▸ toute la section | H13: {"id": "widgets", "label": "Widgets de l'écran d'accueil"}
A14: wg:meteo | B14: Widgets de l'écran d'accueil | C14: Horloge et météo | E14: Oui | H14: {"support": "ok", "def": "meteo"}
A15: wg:une | B15: Widgets de l'écran d'accueil | C15: À la une (actus) | E15: Oui | H15: {"support": "ok", "def": "une"}
A16: wg:invest | B16: Widgets de l'écran d'accueil | C16: Investissements | D16: glisser pour jour / mois / année | E16: Oui | H16: {"support": "ok", "def": "invest"}
A17: wg:spotify | B17: Widgets de l'écran d'accueil | C17: Spotify | D17: demande un compte Spotify | E17: Oui | H17: {"support": "ok", "def": "spotify"}
A18: wg:sport | B18: Widgets de l'écran d'accueil | C18: Bandeau Sports | D18: sur iPhone | E18: Oui | H18: {"support": "ok", "def": "sport"}
A19: wg:live | B19: Widgets de l'écran d'accueil | C19: Tuile LIVE Sports | D19: sur ordinateur | E19: Oui | H19: {"support": "ok", "def": "live"}
A20: sec:accueil:une | B20: Source du widget « À la une » (une seule) | C20: ▸ toute la section | H20: {"id": "une", "label": "Source du widget « À la une » (une seule)"}
A21: un:france-info | B21: Source du widget « À la une » (une seule) | C21: France Info | D21: https://www.francetvinfo.fr/titres.rss | E21: Oui | H21: {"support": "ok", "def": {"name": "France Info", "color": "--t-slate", "url": "https://www.francetvinfo.fr/titres.rss"}}
A22: un:le-monde | B22: Source du widget « À la une » (une seule) | C22: Le Monde | D22: https://www.lemonde.fr/rss/une.xml | H22: {"support": "ok", "def": {"name": "Le Monde", "color": "--t-slate", "url": "https://www.lemonde.fr/rss/une.xml"}}
A23: un:le-figaro | B23: Source du widget « À la une » (une seule) | C23: Le Figaro | D23: https://www.lefigaro.fr/rss/figaro_actualites.xml | H23: {"support": "ok", "def": {"name": "Le Figaro", "color": "--t-slate", "url": "https://www.lefigaro.fr/rss/figaro_actualites.xml"}}
A24: un:20-minutes | B24: Source du widget « À la une » (une seule) | C24: 20 Minutes | D24: https://www.20minutes.fr/feeds/rss-une.xml | H24: {"support": "ok", "def": {"name": "20 Minutes", "color": "--t-slate", "url": "https://www.20minutes.fr/feeds/rss-une.xml"}}
A25: un:liberation | B25: Source du widget « À la une » (une seule) | C25: Libération | D25: https://www.liberation.fr/arc/outboundfeeds/rss-all/?outputType=xml | H25: {"support": "ok", "def": {"name": "Libération", "color": "--t-slate", "url": "https://www.liberation.fr/arc/outboundfeeds/rss-all/?outputType=xml"}}
A26: sec:accueil:meteo | B26: Villes météo | C26: ▸ toute la section | H26: {"id": "meteo", "label": "Villes météo"}
A27: vi:realmont | B27: Villes météo | C27: Réalmont | D27: Tarn · 43.7767, 2.1897 | E27: Oui | H27: {"support": "ok", "def": {"name": "Réalmont", "region": "Tarn", "lat": 43.7767, "lon": 2.1897}}
A28: vi:mazamet | B28: Villes météo | C28: Mazamet | D28: Tarn · 43.492, 2.3736 | E28: Oui | H28: {"support": "ok", "def": {"name": "Mazamet", "region": "Tarn", "lat": 43.492, "lon": 2.3736}}
A29: vi:castres | B29: Villes météo | C29: Castres | D29: Tarn · 43.606, 2.24 | E29: Oui | H29: {"support": "ok", "def": {"name": "Castres", "region": "Tarn", "lat": 43.606, "lon": 2.24}}
A30: vi:albi | B30: Villes météo | C30: Albi | D30: Tarn · 43.9289, 2.1464 | E30: Oui | H30: {"support": "ok", "def": {"name": "Albi", "region": "Tarn", "lat": 43.9289, "lon": 2.1464}}
A31: vi:toulouse | B31: Villes météo | C31: Toulouse | D31: Haute-Garonne · 43.6045, 1.444 | E31: Oui | H31: {"support": "ok", "def": {"name": "Toulouse", "region": "Haute-Garonne", "lat": 43.6045, "lon": 1.444}}
A32: vi:paris | B32: Villes météo | C32: Paris | D32: Île-de-France · 48.8566, 2.3522 | H32: {"support": "ok", "def": {"name": "Paris", "region": "Île-de-France", "lat": 48.8566, "lon": 2.3522}}
A33: vi:montpellier | B33: Villes météo | C33: Montpellier | D33: Hérault · 43.6108, 3.8767 | H33: {"support": "ok", "def": {"name": "Montpellier", "region": "Hérault", "lat": 43.6108, "lon": 3.8767}}
A34: vi:carcassonne | B34: Villes météo | C34: Carcassonne | D34: Aude · 43.213, 2.3491 | H34: {"support": "ok", "def": {"name": "Carcassonne", "region": "Aude", "lat": 43.213, "lon": 2.3491}}
A35: vi:rodez | B35: Villes météo | C35: Rodez | D35: Aveyron · 44.3506, 2.575 | H35: {"support": "ok", "def": {"name": "Rodez", "region": "Aveyron", "lat": 44.3506, "lon": 2.575}}
A36: vi:lavaur | B36: Villes météo | C36: Lavaur | D36: Tarn · 43.699, 1.819 | H36: {"support": "ok", "def": {"name": "Lavaur", "region": "Tarn", "lat": 43.699, "lon": 1.819}}
A37: vi:gaillac | B37: Villes météo | C37: Gaillac | D37: Tarn · 43.9016, 1.897 | H37: {"support": "ok", "def": {"name": "Gaillac", "region": "Tarn", "lat": 43.9016, "lon": 1.897}}
B40: MES AJOUTS — tape ce que tu veux ajouter : la tâche essaie de le récupérer et écrit le résultat (✅ / ⚠️ / ❌) dans la colonne « Résultat »
B41: Section (Villes météo…) | C41: Nom | D41: Pour une ville : région (les coordonnées sont cherchées par la tâche) | E41: Oui | F41: Résultat | G41: Note
A42: exemple | B42: Pages de l'appli | C42: Lacaune | D42: Tarn | E42: Oui | G42: Ligne d'exemple : ignorée par la tâche
A43: ajout:1
A44: ajout:2
A45: ajout:3
A46: ajout:4
A47: ajout:5
A48: ajout:6
A49: ajout:7
A50: ajout:8
A51: ajout:9
A52: ajout:10
A53: ajout:11
A54: ajout:12
... A62: ajout:20

Sheet Applis
A1: module=applis;version=2 | B1: Accueil · applis, dossiers et liens
B2: Chaque appli a 3 liens : iPhone (lien d'ouverture de l'appli), Android (ouvre l'appli ou sa page Google Play) et web (site, utilisé sur PC ou si l'appli manque). Ces liens sont modifiables directement dans le tableau. Aujourd'hui le dock utilise les liens iPhone et web ; les liens Android préparent la version multi-plateforme.
B3: À remplir : cases jaunes (« Oui » ou « Non »). Ligne « ▸ toute la section » = tous ses éléments, sauf ceux marqués « Non ». Un seul élément coché suffit pour que sa section apparaisse. Colonne « Résultat » : remplie par la tâche GitHub après dépôt du classeur.
A5: ID | B5: Section | C5: Appli | D5: Lien iPhone | E5: Lien Android | F5: Lien web | G5: Oui | H5: Résultat | I5: Note | J5: Technique
A6: sec:applis:accueil | B6: Écran d'accueil (dossiers et pages) | C6: ▸ toute la section | J6: {"id": "accueil", "label": "Écran d'accueil", "type": "liste"}
A7: ap:accueil:finance | B7: Écran d'accueil (dossiers et pages) | C7: Finance | D7: dossier finance | G7: Oui | J7: {"support": "ok", "def": {"label": "Finance", "type": "folder", "target": "finance"}}
A8: ap:accueil:travail | B8: Écran d'accueil (dossiers et pages) | C8: Travail | D8: dossier travail | G8: Oui | J8: {"support": "ok", "def": {"label": "Travail", "type": "folder", "target": "travail"}}
A9: ap:accueil:medias | B9: Écran d'accueil (dossiers et pages) | C9: Médias | D9: dossier medias | G9: Oui | J9: {"support": "ok", "def": {"label": "Médias", "type": "folder", "target": "medias"}}
A10: ap:accueil:jeux | B10: Écran d'accueil (dossiers et pages) | C10: Jeux | D10: dossier jeux | G10: Oui | J10: {"support": "ok", "def": {"label": "Jeux", "type": "folder", "target": "jeux"}}
A11: ap:accueil:videos | B11: Écran d'accueil (dossiers et pages) | C11: Vidéos | D11: page videos.html | G11: Oui | J11: {"support": "ok", "def": {"label": "Vidéos", "type": "page", "url": "videos.html", "icon": "play", "color": "--t-brick"}}
A12: ap:accueil:sports | B12: Écran d'accueil (dossiers et pages) | C12: Sports | D12: page sport.html | G12: Oui | J12: {"support": "ok", "def": {"label": "Sports", "type": "page", "url": "sport.html", "live": true, "color": "--t-plum"}}
A13: sec:applis:dossier-finance | B13: Dossier Finance | C13: ▸ toute la section | J13: {"id": "finance", "label": "Finance", "type": "dossier"}
A14: ap:finance:trade-republic | B14: Dossier Finance | C14: Trade Republic | D14: traderepublic:// | E14: intent://#Intent;package=de.traderepublic.app;S.browser_fallback_url=https%3A%2F%2Fplay.google.com%2Fstore%2Fapps%2Fdetails%3Fid%3Dde.traderepublic.app;end | F14: https://app.traderepublic.com | G14: Oui | J14: {"support": "ok", "def": {"label": "Trade Republic", "mono": "TR", "color": "--t-char", "store": "Trade Republic", "app": "traderepublic://", "web": "https://app.traderepublic.com", "android": "intent://#Intent;package=de.traderepublic.app;S.browser_fallback_url=https%3A%2F%2Fplay.google.com%2Fstore%2Fapps%2Fdetails%3Fid%3Dde.traderepublic.app;end"}}
A15: ap:finance:boursobank | B15: Dossier Finance | C15: BoursoBank | D15: shortcuts://run-shortcut?name=BoursoBank | E15: intent://#Intent;package=com.boursorama.android.clients;S.browser_fallback_url=https%3A%2F%2Fplay.google.com%2Fstore%2Fapps%2Fdetails%3Fid%3Dcom.boursorama.android.clients;end | G15: Oui | J15: {"support": "ok", "def": {"label": "BoursoBank", "mono": "Bo", "color": "--t-rose", "store": "BoursoBank", "app": "shortcuts://run-shortcut?name=BoursoBank", "android": "intent://#Intent;package=com.boursorama.android.clients;S.browser_fallback_url=https%3A%2F%2Fplay.google.com%2Fstore%2Fapps%2Fdetails%3Fid%3Dcom.boursorama.android.clients;end"}}
A16: ap:finance:cyberplus | B16: Dossier Finance | C16: Cyberplus | D16: cyberplus:// | E16: intent://#Intent;package=fr.banquepopulaire.cyberplus;S.browser_fallback_url=https%3A%2F%2Fplay.google.com%2Fstore%2Fapps%2Fdetails%3Fid%3Dfr.banquepopulaire.cyberplus;end | F16: https://www.banquepopulaire.fr | G16: Oui | J16: {"support": "ok", "def": {"label": "Cyberplus", "mono": "BP", "color": "--t-brick", "store": "Banque Populaire", "app": "cyberplus://", "web": "https://www.banquepopulaire.fr", "android": "intent://#Intent;package=fr.banquepopulaire.cyberplus;S.browser_fallback_url=https%3A%2F%2Fplay.google.com%2Fstore%2Fapps%2Fdetails%3Fid%3Dfr.banquepopulaire.cyberplus;end"}}
A17: ap:finance:swile | B17: Dossier Finance | C17: Swile | D17: swile:// | F17: https://app.swile.co | G17: Oui | I17: identifiant Android à compléter | J17: {"support": "ok", "def": {"label": "Swile", "mono": "Sw", "color": "--t-plum", "store": "Swile", "app": "swile://", "web": "https://app.swile.co"}}
A18: ap:finance:esalia | B18: Dossier Finance | C18: Esalia | D18: shortcuts://run-shortcut?name=Esalia | G18: Oui | I18: identifiant Android à compléter | J18: {"support": "ok", "def": {"label": "Esalia", "mono": "Es", "color": "--t-teal", "store": "Esalia", "app": "shortcuts://run-shortcut?name=Esalia"}}
A19: sec:applis:dossier-medias | B19: Dossier Médias | C19: ▸ toute la section | J19: {"id": "medias", "label": "Médias", "type": "dossier"}
A20: ap:medias:videolite | B20: Dossier Médias | C20: VideoLite | D20: videolite:// | G20: Oui | I20: appli iPhone uniquement ? | J20: {"support": "ok", "def": {"label": "VideoLite", "mono": "VL", "color": "--t-plum", "store": "VideoLite", "app": "videolite://", "alt": "VideoLite"}}
A21: ap:medias:canal | B21: Dossier Médias | C21: Canal+ | D21: mycanal:// | E21: intent://#Intent;package=com.canal.android.canal;S.browser_fallback_url=https%3A%2F%2Fplay.google.com%2Fstore%2Fapps%2Fdetails%3Fid%3Dcom.canal.android.canal;end | F21: https://www.canalplus.com | G21: Oui | J21: {"support": "ok", "def": {"label": "Canal+", "mono": "C+", "color": "--t-char", "store": "CANAL+", "app": "mycanal://", "alt": "CANAL+", "web": "https://www.canalplus.com", "android": "intent://#Intent;package=com.canal.android.canal;S.browser_fallback_url=https%3A%2F%2Fplay.google.com%2Fstore%2Fapps%2Fdetails%3Fid%3Dcom.canal.android.canal;end"}}
A22: ap:medias:prime-video | B22: Dossier Médias | C22: Prime Video | D22: aiv:// | E22: intent://#Intent;package=com.amazon.avod.thirdpartyclient;S.browser_fallback_url=https%3A%2F%2Fplay.google.com%2Fstore%2Fapps%2Fdetails%3Fid%3Dcom.amazon.avod.thirdpartyclient;end | F22: https://www.primevideo.com | G22: Oui | J22: {"support": "ok", "def": {"label": "Prime Video", "mono": "PV", "color": "--t-slate", "store": "Amazon Prime Video", "app": "aiv://", "web": "https://www.primevideo.com", "android": "intent://#Intent;package=com.amazon.avod.thirdpartyclient;S.browser_fallback_url=https%3A%2F%2Fplay.google.com%2Fstore%2Fapps%2Fdetails%3Fid%3Dcom.amazon.avod.thirdpartyclient;end"}}
A23: ap:medias:smartersplayerlite | B23: Dossier Médias | C23: SmartersPlayerLite | D23: smartersplayerlite:// | G23: Oui | I23: identifiant Android à compléter | J23: {"support": "ok", "def": {"label": "SmartersPlayerLite", "mono": "SP", "color": "--t-teal", "store": "Smarters Player Lite", "app": "smartersplayerlite://", "alt": "SmartersPlayerLite"}}
A24: sec:applis:dossier-jeux | B24: Dossier Jeux | C24: ▸ toute la section | J24: {"id": "jeux", "label": "Jeux", "type": "dossier"}
A25: ap:jeux:chess | B25: Dossier Jeux | C25: Chess | D25: shortcuts://run-shortcut?name=Chess | E25: intent://#Intent;package=com.chess;S.browser_fallback_url=https%3A%2F%2Fplay.google.com%2Fstore%2Fapps%2Fdetails%3Fid%3Dcom.chess;end | G25: Oui | J25: {"support": "ok", "def": {"label": "Chess", "mono": "♞", "color": "--t-olive", "store": "Chess Play and Learn", "app": "shortcuts://run-shortcut?name=Chess", "android": "intent://#Intent;package=com.chess;S.browser_fallback_url=https%3A%2F%2Fplay.google.com%2Fstore%2Fapps%2Fdetails%3Fid%3Dcom.chess;end"}}
A26: ap:jeux:brawl-stars | B26: Dossier Jeux | C26: Brawl Stars | D26: brawlstars:// | E26: intent://#Intent;package=com.supercell.brawlstars;S.browser_fallback_url=https%3A%2F%2Fplay.google.com%2Fstore%2Fapps%2Fdetails%3Fid%3Dcom.supercell.brawlstars;end | G26: Oui | J26: {"support": "ok", "def": {"label": "Brawl Stars", "mono": "BS", "color": "--t-ochre", "store": "Brawl Stars", "app": "brawlstars://", "android": "intent://#Intent;package=com.supercell.brawlstars;S.browser_fallback_url=https%3A%2F%2Fplay.google.com%2Fstore%2Fapps%2Fdetails%3Fid%3Dcom.supercell.brawlstars;end"}}
A27: ap:jeux:songs-of-conquest | B27: Dossier Jeux | C27: Songs of Conquest | D27: shortcuts://run-shortcut?name=Songs%20of%20Conquest | G27: Oui | I27: version mobile à vérifier | J27: {"support": "ok", "def": {"label": "Songs of Conquest", "mono": "SC", "color": "--t-plum", "store": "Songs of Conquest", "app": "shortcuts://run-shortcut?name=Songs%20of%20Conquest"}}
A28: sec:applis:dossier-travail | B28: Dossier Travail | C28: ▸ toute la section | J28: {"id": "travail", "label": "Travail", "type": "dossier"}
A29: ap:travail:outlook | B29: Dossier Travail | C29: Outlook | D29: ms-outlook:// | E29: intent://#Intent;package=com.microsoft.office.outlook;S.browser_fallback_url=https%3A%2F%2Fplay.google.com%2Fstore%2Fapps%2Fdetails%3Fid%3Dcom.microsoft.office.outlook;end | F29: https://outlook.office.com | G29: Oui | J29: {"support": "ok", "def": {"label": "Outlook", "mono": "O", "color": "--t-slate", "store": "Microsoft Outlook", "app": "ms-outlook://", "web": "https://outlook.office.com", "android": "intent://#Intent;package=com.microsoft.office.outlook;S.browser_fallback_url=https%3A%2F%2Fplay.google.com%2Fstore%2Fapps%2Fdetails%3Fid%3Dcom.microsoft.office.outlook;end"}}
A30: ap:travail:teams | B30: Dossier Travail | C30: Teams | D30: msteams:// | E30: intent://#Intent;package=com.microsoft.teams;S.browser_fallback_url=https%3A%2F%2Fplay.google.com%2Fstore%2Fapps%2Fdetails%3Fid%3Dcom.microsoft.teams;end | F30: https://teams.microsoft.com | G30: Oui | J30: {"support": "ok", "def": {"label": "Teams", "mono": "T", "color": "--t-plum", "store": "Microsoft Teams", "app": "msteams://", "web": "https://teams.microsoft.com", "android": "intent://#Intent;package=com.microsoft.teams;S.browser_fallback_url=https%3A%2F%2Fplay.google.com%2Fstore%2Fapps%2Fdetails%3Fid%3Dcom.microsoft.teams;end"}}
A31: ap:travail:word | B31: Dossier Travail | C31: Word | D31: ms-word:// | E31: intent://#Intent;package=com.microsoft.office.word;S.browser_fallback_url=https%3A%2F%2Fplay.google.com%2Fstore%2Fapps%2Fdetails%3Fid%3Dcom.microsoft.office.word;end | F31: https://www.office.com | G31: Oui | J31: {"support": "ok", "def": {"label": "Word", "mono": "W", "color": "--t-brick", "store": "Microsoft Word", "app": "ms-word://", "web": "https://www.office.com", "android": "intent://#Intent;package=com.microsoft.office.word;S.browser_fallback_url=https%3A%2F%2Fplay.google.com%2Fstore%2Fapps%2Fdetails%3Fid%3Dcom.microsoft.office.word;end"}}
A32: ap:travail:powerpoint | B32: Dossier Travail | C32: PowerPoint | D32: ms-powerpoint:// | E32: intent://#Intent;package=com.microsoft.office.powerpoint;S.browser_fallback_url=https%3A%2F%2Fplay.google.com%2Fstore%2Fapps%2Fdetails%3Fid%3Dcom.microsoft.office.powerpoint;end | F32: https://www.office.com | G32: Oui | J32: {"support": "ok", "def": {"label": "PowerPoint", "mono": "P", "color": "--t-rose", "store": "Microsoft PowerPoint", "app": "ms-powerpoint://", "web": "https://www.office.com", "android": "intent://#Intent;package=com.microsoft.office.powerpoint;S.browser_fallback_url=https%3A%2F%2Fplay.google.com%2Fstore%2Fapps%2Fdetails%3Fid%3Dcom.microsoft.office.powerpoint;end"}}
A33: ap:travail:onenote | B33: Dossier Travail | C33: OneNote | D33: onenote:// | E33: intent://#Intent;package=com.microsoft.office.onenote;S.browser_fallback_url=https%3A%2F%2Fplay.google.com%2Fstore%2Fapps%2Fdetails%3Fid%3Dcom.microsoft.office.onenote;end | F33: https://www.onenote.com | G33: Oui | J33: {"support": "ok", "def": {"label": "OneNote", "mono": "N", "color": "--t-plum", "store": "Microsoft OneNote", "app": "onenote://", "web": "https://www.onenote.com", "android": "intent://#Intent;package=com.microsoft.office.onenote;S.browser_fallback_url=https%3A%2F%2Fplay.google.com%2Fstore%2Fapps%2Fdetails%3Fid%3Dcom.microsoft.office.onenote;end"}}
A34: ap:travail:power-bi | B34: Dossier Travail | C34: Power BI | D34: mspbi:// | E34: intent://#Intent;package=com.microsoft.powerbim;S.browser_fallback_url=https%3A%2F%2Fplay.google.com%2Fstore%2Fapps%2Fdetails%3Fid%3Dcom.microsoft.powerbim;end | F34: https://app.powerbi.com | G34: Oui | J34: {"support": "ok", "def": {"label": "Power BI", "mono": "BI", "color": "--t-ochre", "store": "Microsoft Power BI", "app": "mspbi://", "web": "https://app.powerbi.com", "android": "intent://#Intent;package=com.microsoft.powerbim;S.browser_fallback_url=https%3A%2F%2Fplay.google.com%2Fstore%2Fapps%2Fdetails%3Fid%3Dcom.microsoft.powerbim;end"}}
A35: ap:travail:sap-concur | B35: Dossier Travail | C35: SAP Concur | D35: shortcuts://run-shortcut?name=SAP%20Concur | E35: intent://#Intent;package=com.concur.breeze;S.browser_fallback_url=https%3A%2F%2Fplay.google.com%2Fstore%2Fapps%2Fdetails%3Fid%3Dcom.concur.breeze;end | G35: Oui | J35: {"support": "ok", "def": {"label": "SAP Concur", "mono": "Cc", "color": "--t-teal", "store": "SAP Concur", "app": "shortcuts://run-shortcut?name=SAP%20Concur", "android": "intent://#Intent;package=com.concur.breeze;S.browser_fallback_url=https%3A%2F%2Fplay.google.com%2Fstore%2Fapps%2Fdetails%3Fid%3Dcom.concur.breeze;end"}}
A36: ap:travail:fichiers | B36: Dossier Travail | C36: Fichiers | D36: shareddocuments:// | E36: intent://#Intent;package=com.google.android.apps.nbu.files;S.browser_fallback_url=https%3A%2F%2Fplay.google.com%2Fstore%2Fapps%2Fdetails%3Fid%3Dcom.google.android.apps.nbu.files;end | G36: Oui | I36: équivalent Android : Files by Google | J36: {"support": "ok", "def": {"label": "Fichiers", "icon": "folder", "color": "--t-slate", "storeId": "1232058109", "app": "shareddocuments://", "android": "intent://#Intent;package=com.google.android.apps.nbu.files;S.browser_fallback_url=https%3A%2F%2Fplay.google.com%2Fstore%2Fapps%2Fdetails%3Fid%3Dcom.google.android.apps.nbu.files;end"}}
A37: ap:travail:proton-drive | B37: Dossier Travail | C37: Proton Drive | D37: protondrive:// | E37: intent://#Intent;package=me.proton.android.drive;S.browser_fallback_url=https%3A%2F%2Fplay.google.com%2Fstore%2Fapps%2Fdetails%3Fid%3Dme.proton.android.drive;end | F37: https://drive.proton.me | G37: Oui | J37: {"support": "ok", "def": {"label": "Proton Drive", "mono": "PD", "color": "--t-char", "store": "Proton Drive", "app": "protondrive://", "web": "https://drive.proton.me", "android": "intent://#Intent;package=me.proton.android.drive;S.browser_fallback_url=https%3A%2F%2Fplay.google.com%2Fstore%2Fapps%2Fdetails%3Fid%3Dme.proton.android.drive;end"}}
